{
  "type": "Feature",
  "properties": {
    "iso:country":"XX",
    "qs_pg:name":"Arnona",
    "qs_pg:name_adm0":"Israel",
    "qs_pg:name_adm1":"Jerusalem",
    "qs_pg:photos":332,
    "qs_pg:photos_1k":67,
    "qs_pg:photos_9k":1,
    "qs_pg:photos_9r":5,
    "qs_pg:photos_all":332,
    "qs_pg:photos_sr":5,
    "qs_pg:pop_sr":0,
    "qs_pg:qs_pg_placetype":"neighbourhood",
    "qs_pg:qs_pg_placetype_gp":"Suburb",
    "qs_pg:woe_adm0":23424852,
    "woe:adm0_id":23424852,
    "woe:name_adm0":"Israel",
    "woe:name_adm1":"Jerusalem",
    "woe:placetype":"Suburb",
    "wof:name":"Arnona",
    "wof:placetype":"neighbourhood"
},
  "geometry": {"coordinates":[35.22294,31.753203],"type":"Point"}
}