{
  "type": "Feature",
  "properties": {
    "iso:country":"XX",
    "qs_pg:name":"Extension El Comandante",
    "qs_pg:name_adm0":"Puerto Rico",
    "qs_pg:name_adm1":"Carolina",
    "qs_pg:photos":3,
    "qs_pg:photos_1k":1,
    "qs_pg:photos_9k":1,
    "qs_pg:photos_9r":1,
    "qs_pg:photos_all":3,
    "qs_pg:photos_sr":1,
    "qs_pg:pop_sr":0,
    "qs_pg:qs_pg_placetype":"neighbourhood",
    "qs_pg:qs_pg_placetype_gp":"Suburb",
    "qs_pg:woe_adm0":23424935,
    "woe:adm0_id":23424935,
    "woe:name_adm0":"Puerto Rico",
    "woe:name_adm1":"Carolina",
    "woe:placetype":"Suburb",
    "wof:name":"Extension El Comandante",
    "wof:placetype":"neighbourhood"
},
  "geometry": {"coordinates":[-65.987877,18.398774],"type":"Point"}
}