{
  "type": "Feature",
  "properties": {
    "iso:country":"XX",
    "name:ceb_x_preferred":[
        "Flatey"
    ],
    "name:deu_x_preferred":[
        "Flatey"
    ],
    "name:epo_x_preferred":[
        "Flatey"
    ],
    "name:fra_x_preferred":[
        "Flatey"
    ],
    "name:isl_x_preferred":[
        "Flatey"
    ],
    "name:nld_x_preferred":[
        "Flatey"
    ],
    "name:pol_x_preferred":[
        "Flatey"
    ],
    "name:swe_x_preferred":[
        "Flatey"
    ],
    "qs_pg:name":"Flatey",
    "qs_pg:name_adm0":"\u00cdsland",
    "qs_pg:name_adm1":"Sudur-Tingeyjarsysla",
    "qs_pg:photos":90,
    "qs_pg:photos_1k":18,
    "qs_pg:photos_9k":1,
    "qs_pg:photos_9r":3,
    "qs_pg:photos_all":90,
    "qs_pg:photos_sr":3,
    "qs_pg:pop_sr":0,
    "qs_pg:qs_pg_placetype":"locality",
    "qs_pg:qs_pg_placetype_gp":"Town",
    "qs_pg:woe_adm0":23424845,
    "woe:adm0_id":23424845,
    "woe:name_adm0":"\u00cdsland",
    "woe:name_adm1":"Sudur-Tingeyjarsysla",
    "woe:placetype":"Town",
    "wof:name":"Flatey",
    "wof:placetype":"locality"
},
  "geometry": {"coordinates":[-17.8647865,66.16023300000001],"type":"Point"}
}