{
  "type": "Feature",
  "properties": {
    "iso:country":"XX",
    "qs_pg:name":"Lomas Del Pedregal",
    "qs_pg:name_adm0":"M\u00e9xico",
    "qs_pg:name_adm1":"Guanajuato",
    "qs_pg:photos":17,
    "qs_pg:photos_1k":3,
    "qs_pg:photos_9k":1,
    "qs_pg:photos_9r":1,
    "qs_pg:photos_all":17,
    "qs_pg:photos_sr":1,
    "qs_pg:pop_sr":0,
    "qs_pg:qs_pg_placetype":"neighbourhood",
    "qs_pg:qs_pg_placetype_gp":"Suburb",
    "qs_pg:woe_adm0":23424900,
    "woe:adm0_id":23424900,
    "woe:name_adm0":"M\u00e9xico",
    "woe:name_adm1":"Guanajuato",
    "woe:placetype":"Suburb",
    "wof:name":"Lomas Del Pedregal",
    "wof:placetype":"neighbourhood"
},
  "geometry": {"coordinates":[-101.394581,20.695866],"type":"Point"}
}