{
  "type": "Feature",
  "properties": {
    "iso:country":"XX",
    "qs_pg:name":"Gilheads",
    "qs_pg:name_adm0":"Bonaire Saint Eustatius and Saba",
    "qs_pg:name_adm1":"St. Eustatius",
    "qs_pg:photos":17,
    "qs_pg:photos_1k":3,
    "qs_pg:photos_9k":1,
    "qs_pg:photos_9r":1,
    "qs_pg:photos_all":17,
    "qs_pg:photos_sr":1,
    "qs_pg:pop_sr":0,
    "qs_pg:qs_pg_placetype":"locality",
    "qs_pg:qs_pg_placetype_gp":"Town",
    "qs_pg:woe_adm0":56558056,
    "woe:adm0_id":56558056,
    "woe:name_adm0":"Bonaire Saint Eustatius and Saba",
    "woe:name_adm1":"St. Eustatius",
    "woe:placetype":"Town",
    "wof:name":"Gilheads",
    "wof:placetype":"locality"
},
  "geometry": {"coordinates":[-62.959041,17.474139],"type":"Point"}
}