{
  "type": "Feature",
  "properties": {
    "iso:country":"XX",
    "qs_pg:name":"Kibbutz Ramat Rakhel",
    "qs_pg:name_adm0":"Israel",
    "qs_pg:name_adm1":"Jerusalem",
    "qs_pg:photos":150,
    "qs_pg:photos_1k":30,
    "qs_pg:photos_9k":1,
    "qs_pg:photos_9r":3,
    "qs_pg:photos_all":150,
    "qs_pg:photos_sr":3,
    "qs_pg:pop_sr":0,
    "qs_pg:qs_pg_placetype":"neighbourhood",
    "qs_pg:qs_pg_placetype_gp":"Suburb",
    "qs_pg:woe_adm0":23424852,
    "woe:adm0_id":23424852,
    "woe:name_adm0":"Israel",
    "woe:name_adm1":"Jerusalem",
    "woe:placetype":"Suburb",
    "wof:name":"Kibbutz Ramat Rakhel",
    "wof:placetype":"neighbourhood"
},
  "geometry": {"coordinates":[35.214099,31.7387425],"type":"Point"}
}