{
  "type": "Feature",
  "properties": {
    "iso:country":"XX",
    "qs_pg:name":"Petr\u00f3polis",
    "qs_pg:name_adm0":"Brasil",
    "qs_pg:name_adm1":"Rio Grande do Sul",
    "qs_pg:photos":1216,
    "qs_pg:photos_1k":246,
    "qs_pg:photos_9k":5,
    "qs_pg:photos_9r":7,
    "qs_pg:photos_all":1216,
    "qs_pg:photos_sr":11,
    "qs_pg:pop_sr":0,
    "qs_pg:qs_pg_placetype":"neighbourhood",
    "qs_pg:qs_pg_placetype_gp":"Suburb",
    "qs_pg:woe_adm0":23424768,
    "woe:adm0_id":23424768,
    "woe:name_adm0":"Brasil",
    "woe:name_adm1":"Rio Grande do Sul",
    "woe:placetype":"Suburb",
    "wof:name":"Petr\u00f3polis",
    "wof:placetype":"neighbourhood"
},
  "geometry": {"coordinates":[-51.184135,-30.044058],"type":"Point"}
}