{
  "type": "Feature",
  "properties": {
    "iso:country":"XX",
    "qs_pg:name":"Strassburg in K\u00e4rnten",
    "qs_pg:name_adm0":"\u00d6sterreich",
    "qs_pg:name_adm1":"K\u00e4rnten",
    "qs_pg:photos":211,
    "qs_pg:photos_1k":43,
    "qs_pg:photos_9k":1,
    "qs_pg:photos_9r":4,
    "qs_pg:photos_all":211,
    "qs_pg:photos_sr":4,
    "qs_pg:pop_sr":0,
    "qs_pg:qs_pg_placetype":"locality",
    "qs_pg:qs_pg_placetype_gp":"Town",
    "qs_pg:woe_adm0":23424750,
    "woe:adm0_id":23424750,
    "woe:name_adm0":"\u00d6sterreich",
    "woe:name_adm1":"K\u00e4rnten",
    "woe:placetype":"Town",
    "wof:name":"Strassburg in K\u00e4rnten",
    "wof:placetype":"locality"
},
  "geometry": {"coordinates":[14.330463,46.8907],"type":"Point"}
}