{
  "type": "Feature",
  "properties": {
    "iso:country":"XX",
    "qs_pg:name":"Arlington Ridge",
    "qs_pg:name_adm0":"United States",
    "qs_pg:name_adm1":"Florida",
    "qs_pg:photos":61,
    "qs_pg:photos_1k":12,
    "qs_pg:photos_9k":1,
    "qs_pg:photos_9r":2,
    "qs_pg:photos_all":61,
    "qs_pg:photos_sr":2,
    "qs_pg:pop_sr":0,
    "qs_pg:qs_pg_placetype":"neighbourhood",
    "qs_pg:qs_pg_placetype_gp":"Suburb",
    "qs_pg:woe_adm0":23424977,
    "woe:adm0_id":23424977,
    "woe:name_adm0":"United States",
    "woe:name_adm1":"Florida",
    "woe:placetype":"Suburb",
    "wof:name":"Arlington Ridge",
    "wof:placetype":"neighbourhood"
},
  "geometry": {"coordinates":[-81.877852,28.734133],"type":"Point"}
}