{
  "type": "Feature",
  "properties": {
    "iso:country":"XX",
    "name:ceb_x_preferred":[
        "Hickory Ridge"
    ],
    "name:deu_x_preferred":[
        "Hickory Ridge"
    ],
    "name:pol_x_preferred":[
        "Hickory Ridge"
    ],
    "qs_pg:name":"Hickory Ridge",
    "qs_pg:name_adm0":"United States",
    "qs_pg:name_adm1":"Michigan",
    "qs_pg:photos":11,
    "qs_pg:photos_1k":2,
    "qs_pg:photos_9k":1,
    "qs_pg:photos_9r":1,
    "qs_pg:photos_all":11,
    "qs_pg:photos_sr":1,
    "qs_pg:pop_sr":0,
    "qs_pg:qs_pg_placetype":"neighbourhood",
    "qs_pg:qs_pg_placetype_gp":"Suburb",
    "qs_pg:woe_adm0":23424977,
    "woe:adm0_id":23424977,
    "woe:name_adm0":"United States",
    "woe:name_adm1":"Michigan",
    "woe:placetype":"Suburb",
    "wof:name":"Hickory Ridge",
    "wof:placetype":"neighbourhood"
},
  "geometry": {"coordinates":[-83.665587,42.678428],"type":"Point"}
}