{
  "type": "Feature",
  "properties": {
    "iso:country":"XX",
    "qs_pg:name":"Waters Edge",
    "qs_pg:name_adm0":"United States",
    "qs_pg:name_adm1":"California",
    "qs_pg:photos":161,
    "qs_pg:photos_1k":33,
    "qs_pg:photos_9k":1,
    "qs_pg:photos_9r":4,
    "qs_pg:photos_all":161,
    "qs_pg:photos_sr":4,
    "qs_pg:pop_sr":0,
    "qs_pg:qs_pg_placetype":"neighbourhood",
    "qs_pg:qs_pg_placetype_gp":"Suburb",
    "qs_pg:woe_adm0":23424977,
    "woe:adm0_id":23424977,
    "woe:name_adm0":"United States",
    "woe:name_adm1":"California",
    "woe:placetype":"Suburb",
    "wof:name":"Waters Edge",
    "wof:placetype":"neighbourhood"
},
  "geometry": {"coordinates":[-120.13133500000001,39.068553],"type":"Point"}
}