{
  "type": "Feature",
  "properties": {
    "iso:country":"XX",
    "name:deu_x_preferred":[
        "Uptown"
    ],
    "name:fra_x_preferred":[
        "Uptown"
    ],
    "name:jpn_x_preferred":[
        "\u30a2\u30c3\u30d7\u30bf\u30a6\u30f3"
    ],
    "name:kor_x_preferred":[
        "\uc5c5\ud0c0\uc6b4"
    ],
    "qs_pg:name":"Uptown",
    "qs_pg:name_adm0":"United States",
    "qs_pg:name_adm1":"Texas",
    "qs_pg:photos":285,
    "qs_pg:photos_1k":58,
    "qs_pg:photos_9k":1,
    "qs_pg:photos_9r":4,
    "qs_pg:photos_all":285,
    "qs_pg:photos_sr":5,
    "qs_pg:pop_sr":0,
    "qs_pg:qs_pg_placetype":"neighbourhood",
    "qs_pg:qs_pg_placetype_gp":"Suburb",
    "qs_pg:woe_adm0":23424977,
    "woe:adm0_id":23424977,
    "woe:name_adm0":"United States",
    "woe:name_adm1":"Texas",
    "woe:placetype":"Suburb",
    "wof:name":"Uptown",
    "wof:placetype":"neighbourhood"
},
  "geometry": {"coordinates":[-95.482325,29.758345],"type":"Point"}
}