{
  "type": "Feature",
  "properties": {
    "iso:country":"XX",
    "qs_pg:name":"Torreta Florida",
    "qs_pg:name_adm0":"Espa\u00f1a",
    "qs_pg:name_adm1":"Comunitat Valenciana",
    "qs_pg:photos":60,
    "qs_pg:photos_1k":12,
    "qs_pg:photos_9k":1,
    "qs_pg:photos_9r":2,
    "qs_pg:photos_all":60,
    "qs_pg:photos_sr":2,
    "qs_pg:pop_sr":0,
    "qs_pg:qs_pg_placetype":"locality",
    "qs_pg:qs_pg_placetype_gp":"Town",
    "qs_pg:woe_adm0":23424950,
    "woe:adm0_id":23424950,
    "woe:name_adm0":"Espa\u00f1a",
    "woe:name_adm1":"Comunitat Valenciana",
    "woe:placetype":"Town",
    "wof:name":"Torreta Florida",
    "wof:placetype":"locality"
},
  "geometry": {"coordinates":[-0.698715,37.992357],"type":"Point"}
}