{
  "type": "Feature",
  "properties": {
    "iso:country":"XX",
    "qs_pg:name":"Saint-marcouf de l'Isle Les Gougins",
    "qs_pg:name_adm0":"France",
    "qs_pg:name_adm1":"Basse-Normandie",
    "qs_pg:photos":18,
    "qs_pg:photos_1k":4,
    "qs_pg:photos_9k":1,
    "qs_pg:photos_9r":1,
    "qs_pg:photos_all":18,
    "qs_pg:photos_sr":1,
    "qs_pg:pop_sr":0,
    "qs_pg:qs_pg_placetype":"locality",
    "qs_pg:qs_pg_placetype_gp":"Town",
    "qs_pg:woe_adm0":23424819,
    "woe:adm0_id":23424819,
    "woe:name_adm0":"France",
    "woe:name_adm1":"Basse-Normandie",
    "woe:placetype":"Town",
    "wof:name":"Saint-marcouf de l'Isle Les Gougins",
    "wof:placetype":"locality"
},
  "geometry": {"coordinates":[-1.267244,49.497204],"type":"Point"}
}