{
  "type": "Feature",
  "properties": {
    "iso:country":"XX",
    "qs_pg:name":"Tourtet",
    "qs_pg:name_adm0":"Martinique",
    "qs_pg:name_adm1":"Fort-de-France",
    "qs_pg:photos":124,
    "qs_pg:photos_1k":25,
    "qs_pg:photos_9k":1,
    "qs_pg:photos_9r":3,
    "qs_pg:photos_all":124,
    "qs_pg:photos_sr":3,
    "qs_pg:pop_sr":0,
    "qs_pg:qs_pg_placetype":"locality",
    "qs_pg:qs_pg_placetype_gp":"Town",
    "qs_pg:woe_adm0":23424884,
    "woe:adm0_id":23424884,
    "woe:name_adm0":"Martinique",
    "woe:name_adm1":"Fort-de-France",
    "woe:placetype":"Town",
    "wof:name":"Tourtet",
    "wof:placetype":"locality"
},
  "geometry": {"coordinates":[-61.094112,14.648946],"type":"Point"}
}