{
  "type": "Feature",
  "properties": {
    "iso:country":"XX",
    "wof:name":"Le Roucas Blanc",
    "wof:placetype":"neighbourhood"
},
  "geometry": {"coordinates":[5.36751967505458,43.2746756400369],"type":"Point"}
}