{
  "type": "Feature",
  "properties": {
    "iso:country":"XX",
    "name:ara_x_preferred":[
        "\u0636\u064a\u0627\u0621 \u0643\u0648\u0643 \u0623\u0644\u0628"
    ],
    "name:azb_x_preferred":[
        "\u0636\u06cc\u0627 \u06af\u0648\u06a9\u200c\u0622\u0644\u067e"
    ],
    "name:aze_x_preferred":[
        "Ziya G\u00f6yalp"
    ],
    "name:ces_x_preferred":[
        "Ziya G\u00f6kalp"
    ],
    "name:dan_x_preferred":[
        "Ziya G\u00f6kalp"
    ],
    "name:deu_x_preferred":[
        "Ziya G\u00f6kalp"
    ],
    "name:diq_x_preferred":[
        "Ziya G\u00f6kalp"
    ],
    "name:fas_x_preferred":[
        "\u0636\u06cc\u0627 \u06af\u0648\u06a9 \u0622\u0644\u067e"
    ],
    "name:fra_x_preferred":[
        "Ziya G\u00f6kalp"
    ],
    "name:heb_x_preferred":[
        "\u05d6\u05d9\u05d0 \u05d2\u05e7\u05d0\u05dc\u05e4"
    ],
    "name:hye_x_preferred":[
        "\u0536\u056b\u0561 \u0533\u0575\u0578\u0584\u0561\u056c\u0583"
    ],
    "name:ind_x_preferred":[
        "Ziya Gokalp"
    ],
    "name:ita_x_preferred":[
        "Ziya G\u00f6kalp"
    ],
    "name:kaz_x_preferred":[
        "\u0417\u0438\u044f \u0413\u04e9\u043a\u0430\u043b\u043f"
    ],
    "name:kir_x_preferred":[
        "\u0417\u0438\u044f \u0413\u04e9\u043a\u0430\u043b\u043f"
    ],
    "name:kur_x_preferred":[
        "Ziya G\u00f6kalp"
    ],
    "name:mrj_x_preferred":[
        "\u0413\u04e7\u043a\u0430\u043b\u043f"
    ],
    "name:nld_x_preferred":[
        "Ziya G\u00f6kalp"
    ],
    "name:pol_x_preferred":[
        "Ziya G\u00f6kalp"
    ],
    "name:ron_x_preferred":[
        "Ziya G\u00f6kalp"
    ],
    "name:rus_x_preferred":[
        "\u0417\u0438\u044f \u0413\u0451\u043a\u0430\u043b\u044c\u043f"
    ],
    "name:spa_x_preferred":[
        "Ziya G\u00f6kalp"
    ],
    "name:swe_x_preferred":[
        "Ziya G\u00f6kalp"
    ],
    "name:tgk_x_preferred":[
        "\u0417\u0438\u0451 \u0413\u0451\u043a\u0430\u043b\u043f"
    ],
    "name:tur_x_preferred":[
        "Ziya G\u00f6kalp"
    ],
    "name:urd_x_preferred":[
        "\u0636\u06cc\u0627\u0621 \u06af\u0648\u06a9 \u0627\u0644\u067e"
    ],
    "name:uzb_x_preferred":[
        "Ziyo ko\u02bbkalp"
    ],
    "name:zho_x_preferred":[
        "\u9f50\u4e9a\u00b7\u683c\u5361\u5c14\u666e"
    ],
    "qs_pg:name":"Ziya G\u00f6kalp",
    "qs_pg:name_adm0":"Turkey",
    "qs_pg:name_adm1":"\u0130stanbul",
    "qs_pg:photos":163,
    "qs_pg:photos_1k":33,
    "qs_pg:photos_9k":1,
    "qs_pg:photos_9r":4,
    "qs_pg:photos_all":163,
    "qs_pg:photos_sr":4,
    "qs_pg:pop_sr":0,
    "qs_pg:qs_pg_placetype":"neighbourhood",
    "qs_pg:qs_pg_placetype_gp":"Suburb",
    "qs_pg:woe_adm0":23424969,
    "woe:adm0_id":23424969,
    "woe:name_adm0":"Turkey",
    "woe:name_adm1":"\u0130stanbul",
    "woe:placetype":"Suburb",
    "wof:name":"Ziya G\u00f6kalp",
    "wof:placetype":"neighbourhood"
},
  "geometry": {"coordinates":[28.765468,41.074471],"type":"Point"}
}