{
  "type": "Feature",
  "properties": {
    "iso:country":"XX",
    "qs_pg:name":"Playas Del sur",
    "qs_pg:name_adm0":"M\u00e9xico",
    "qs_pg:name_adm1":"Sinaloa",
    "qs_pg:photos":250,
    "qs_pg:photos_1k":51,
    "qs_pg:photos_9k":1,
    "qs_pg:photos_9r":4,
    "qs_pg:photos_all":250,
    "qs_pg:photos_sr":4,
    "qs_pg:pop_sr":0,
    "qs_pg:qs_pg_placetype":"neighbourhood",
    "qs_pg:qs_pg_placetype_gp":"Suburb",
    "qs_pg:woe_adm0":23424900,
    "woe:adm0_id":23424900,
    "woe:name_adm0":"M\u00e9xico",
    "woe:name_adm1":"Sinaloa",
    "woe:placetype":"Suburb",
    "wof:name":"Playas Del sur",
    "wof:placetype":"neighbourhood"
},
  "geometry": {"coordinates":[-106.42576200000001,23.184235],"type":"Point"}
}