{
  "type": "Feature",
  "properties": {
    "iso:country":"XX",
    "qs_pg:name":"Jaffa Old City",
    "qs_pg:name_adm0":"Israel",
    "qs_pg:name_adm1":"Tel Aviv",
    "qs_pg:photos":4941,
    "qs_pg:photos_1k":1000,
    "qs_pg:photos_9k":22,
    "qs_pg:photos_9r":14,
    "qs_pg:photos_all":4941,
    "qs_pg:photos_sr":24,
    "qs_pg:pop_sr":0,
    "qs_pg:qs_pg_placetype":"neighbourhood",
    "qs_pg:qs_pg_placetype_gp":"Suburb",
    "qs_pg:woe_adm0":23424852,
    "woe:adm0_id":23424852,
    "woe:name_adm0":"Israel",
    "woe:name_adm1":"Tel Aviv",
    "woe:placetype":"Suburb",
    "wof:name":"Jaffa Old City",
    "wof:placetype":"neighbourhood"
},
  "geometry": {"coordinates":[34.753197,32.055399],"type":"Point"}
}