{
  "type": "Feature",
  "properties": {
    "iso:country":"XX",
    "name:deu_x_preferred":[
        "Willowbank"
    ],
    "qs_pg:name":"Willowbank",
    "qs_pg:name_adm0":"United States",
    "qs_pg:name_adm1":"California",
    "qs_pg:photos":497,
    "qs_pg:photos_1k":101,
    "qs_pg:photos_9k":2,
    "qs_pg:photos_9r":5,
    "qs_pg:photos_all":497,
    "qs_pg:photos_sr":7,
    "qs_pg:pop_sr":0,
    "qs_pg:qs_pg_placetype":"neighbourhood",
    "qs_pg:qs_pg_placetype_gp":"Suburb",
    "qs_pg:woe_adm0":23424977,
    "woe:adm0_id":23424977,
    "woe:name_adm0":"United States",
    "woe:name_adm1":"California",
    "woe:placetype":"Suburb",
    "wof:name":"Willowbank",
    "wof:placetype":"neighbourhood"
},
  "geometry": {"coordinates":[-121.69083500000001,38.533156],"type":"Point"}
}