{
  "type": "Feature",
  "properties": {
    "iso:country":"XX",
    "qs_pg:name":"Badarpur Extension",
    "qs_pg:name_adm0":"India",
    "qs_pg:name_adm1":"Delhi",
    "qs_pg:photos":4,
    "qs_pg:photos_1k":1,
    "qs_pg:photos_9k":1,
    "qs_pg:photos_9r":1,
    "qs_pg:photos_all":4,
    "qs_pg:photos_sr":1,
    "qs_pg:pop_sr":0,
    "qs_pg:qs_pg_placetype":"neighbourhood",
    "qs_pg:qs_pg_placetype_gp":"Suburb",
    "qs_pg:woe_adm0":23424848,
    "woe:adm0_id":23424848,
    "woe:name_adm0":"India",
    "woe:name_adm1":"Delhi",
    "woe:placetype":"Suburb",
    "wof:name":"Badarpur Extension",
    "wof:placetype":"neighbourhood"
},
  "geometry": {"coordinates":[77.302719,28.4945975],"type":"Point"}
}