{
  "type": "Feature",
  "properties": {
    "iso:country":"XX",
    "name:ces_x_preferred":[
        "Hoop"
    ],
    "name:deu_x_preferred":[
        "Hoop"
    ],
    "name:frr_x_preferred":[
        "Hoop"
    ],
    "name:jpn_x_preferred":[
        "\u30d5\u30fc\u30d7"
    ],
    "name:nds_x_preferred":[
        "Hoop"
    ],
    "name:nld_x_preferred":[
        "Hoop"
    ],
    "name:pol_x_preferred":[
        "Hoop"
    ],
    "name:rus_x_preferred":[
        "\u0425\u043e\u043e\u043f"
    ],
    "qs_pg:name":"Hoop",
    "qs_pg:name_adm0":"Bonaire Saint Eustatius and Saba",
    "qs_pg:name_adm1":"Bonaire",
    "qs_pg:photos":1685,
    "qs_pg:photos_1k":341,
    "qs_pg:photos_9k":7,
    "qs_pg:photos_9r":8,
    "qs_pg:photos_all":1685,
    "qs_pg:photos_sr":14,
    "qs_pg:pop_sr":0,
    "qs_pg:qs_pg_placetype":"locality",
    "qs_pg:qs_pg_placetype_gp":"Town",
    "qs_pg:woe_adm0":56558056,
    "woe:adm0_id":56558056,
    "woe:name_adm0":"Bonaire Saint Eustatius and Saba",
    "woe:name_adm1":"Bonaire",
    "woe:placetype":"Town",
    "wof:name":"Hoop",
    "wof:placetype":"locality"
},
  "geometry": {"coordinates":[-68.28789999999999,12.10878],"type":"Point"}
}