{
  "type": "Feature",
  "properties": {
    "iso:country":"XX",
    "qs_pg:name":"Glenelg Jetty Road",
    "qs_pg:name_adm0":"Australia",
    "qs_pg:name_adm1":"South Australia",
    "qs_pg:photos":3266,
    "qs_pg:photos_1k":662,
    "qs_pg:photos_9k":14,
    "qs_pg:photos_9r":11,
    "qs_pg:photos_all":3266,
    "qs_pg:photos_sr":20,
    "qs_pg:pop_sr":0,
    "qs_pg:qs_pg_placetype":"neighbourhood",
    "qs_pg:qs_pg_placetype_gp":"Suburb",
    "qs_pg:woe_adm0":23424748,
    "woe:adm0_id":23424748,
    "woe:name_adm0":"Australia",
    "woe:name_adm1":"South Australia",
    "woe:placetype":"Suburb",
    "wof:name":"Glenelg Jetty Road",
    "wof:placetype":"neighbourhood"
},
  "geometry": {"coordinates":[138.51084900000001,-34.979605],"type":"Point"}
}