{
  "type": "Feature",
  "properties": {
    "iso:country":"XX",
    "name:ara_x_preferred":[
        "\u0628\u064a\u062a\u0634\u064a"
    ],
    "name:bos_x_preferred":[
        "Be\u010dej"
    ],
    "name:bul_x_preferred":[
        "\u0411\u0435\u0447\u0435\u0439"
    ],
    "name:ces_x_preferred":[
        "Be\u010dej"
    ],
    "name:ckb_x_preferred":[
        "\u0628\u06ce\u0686\u06ce\u06cc"
    ],
    "name:dan_x_preferred":[
        "Be\u010dej"
    ],
    "name:deu_x_preferred":[
        "Be\u010dej"
    ],
    "name:eng_x_preferred":[
        "Be\u010dej"
    ],
    "name:epo_x_preferred":[
        "Be\u0109ej"
    ],
    "name:fas_x_preferred":[
        "\u0628\u0686\u06cc"
    ],
    "name:fin_x_preferred":[
        "Be\u010dej"
    ],
    "name:fra_x_preferred":[
        "Be\u010dej"
    ],
    "name:heb_x_preferred":[
        "\u05d1\u05e6'\u05d9\u05d9"
    ],
    "name:hrv_x_preferred":[
        "Be\u010dej"
    ],
    "name:hun_x_preferred":[
        "\u00d3becse"
    ],
    "name:hye_x_preferred":[
        "\u0532\u0565\u0579\u0565\u0575"
    ],
    "name:ind_x_preferred":[
        "Be\u010dej"
    ],
    "name:ita_x_preferred":[
        "Be\u010dej"
    ],
    "name:jpn_x_preferred":[
        "\u30d9\u30c1\u30a7\u30a4"
    ],
    "name:kor_x_preferred":[
        "\ubca0\uccb4\uc774"
    ],
    "name:lit_x_preferred":[
        "Be\u010dejus"
    ],
    "name:msa_x_preferred":[
        "Be\u010dej"
    ],
    "name:nld_x_preferred":[
        "Be\u010dej"
    ],
    "name:oci_x_preferred":[
        "Be\u010dej"
    ],
    "name:pnb_x_preferred":[
        "\u0628\u06cc\u0686\u06cc\u06cc"
    ],
    "name:pol_x_preferred":[
        "Be\u010dej"
    ],
    "name:rus_x_preferred":[
        "\u0411\u0435\u0447\u0435\u0439"
    ],
    "name:sco_x_preferred":[
        "Be\u010dej"
    ],
    "name:slv_x_preferred":[
        "Be\u010dej"
    ],
    "name:srp_x_preferred":[
        "\u0411\u0435\u0447\u0435\u0458"
    ],
    "name:swe_x_preferred":[
        "Be\u010dej"
    ],
    "name:tat_x_preferred":[
        "\u0411\u0435\u0447\u0435\u0439"
    ],
    "name:tur_x_preferred":[
        "Be\u00e7e"
    ],
    "name:vie_x_preferred":[
        "Be\u010dej"
    ],
    "name:zho_x_preferred":[
        "\u8d1d\u5207\u4f0a"
    ],
    "qs_pg:name":"Be\u010dej",
    "qs_pg:name_adm0":"Serbia",
    "qs_pg:name_adm1":"Juzhna Bachka",
    "qs_pg:photos":147,
    "qs_pg:photos_1k":30,
    "qs_pg:photos_9k":1,
    "qs_pg:photos_9r":3,
    "qs_pg:photos_all":147,
    "qs_pg:photos_sr":3,
    "qs_pg:pop_sr":0,
    "qs_pg:qs_pg_placetype":"locality",
    "qs_pg:qs_pg_placetype_gp":"Town",
    "qs_pg:woe_adm0":20069818,
    "woe:adm0_id":20069818,
    "woe:name_adm0":"Serbia",
    "woe:name_adm1":"Juzhna Bachka",
    "woe:placetype":"Town",
    "wof:name":"Be\u010dej",
    "wof:placetype":"locality"
},
  "geometry": {"coordinates":[20.047479,45.61992],"type":"Point"}
}