{
  "type": "Feature",
  "properties": {
    "iso:country":"XX",
    "qs_pg:name":"Morro Jos\u00e9 Menino",
    "qs_pg:name_adm0":"Brasil",
    "qs_pg:name_adm1":"S\u00e3o Paulo",
    "qs_pg:photos":457,
    "qs_pg:photos_1k":93,
    "qs_pg:photos_9k":2,
    "qs_pg:photos_9r":5,
    "qs_pg:photos_all":457,
    "qs_pg:photos_sr":7,
    "qs_pg:pop_sr":0,
    "qs_pg:qs_pg_placetype":"neighbourhood",
    "qs_pg:qs_pg_placetype_gp":"Suburb",
    "qs_pg:woe_adm0":23424768,
    "woe:adm0_id":23424768,
    "woe:name_adm0":"Brasil",
    "woe:name_adm1":"S\u00e3o Paulo",
    "woe:placetype":"Suburb",
    "wof:name":"Morro Jos\u00e9 Menino",
    "wof:placetype":"neighbourhood"
},
  "geometry": {"coordinates":[-46.363625,-23.967195],"type":"Point"}
}