{
  "type": "Feature",
  "properties": {
    "iso:country":"XX",
    "qs_pg:name":"65 de Infanteria",
    "qs_pg:name_adm0":"Puerto Rico",
    "qs_pg:name_adm1":"San Juan",
    "qs_pg:photos":319,
    "qs_pg:photos_1k":65,
    "qs_pg:photos_9k":1,
    "qs_pg:photos_9r":5,
    "qs_pg:photos_all":319,
    "qs_pg:photos_sr":5,
    "qs_pg:pop_sr":0,
    "qs_pg:qs_pg_placetype":"neighbourhood",
    "qs_pg:qs_pg_placetype_gp":"Suburb",
    "qs_pg:woe_adm0":23424935,
    "woe:adm0_id":23424935,
    "woe:name_adm0":"Puerto Rico",
    "woe:name_adm1":"San Juan",
    "woe:placetype":"Suburb",
    "wof:name":"65 de Infanteria",
    "wof:placetype":"neighbourhood"
},
  "geometry": {"coordinates":[-66.051969,18.400918],"type":"Point"}
}