{
  "type": "Feature",
  "properties": {
    "iso:country":"XX",
    "qs_pg:name":"Da Barra",
    "qs_pg:name_adm0":"Brasil",
    "qs_pg:name_adm1":"Santa Catarina",
    "qs_pg:photos":765,
    "qs_pg:photos_1k":155,
    "qs_pg:photos_9k":3,
    "qs_pg:photos_9r":6,
    "qs_pg:photos_all":765,
    "qs_pg:photos_sr":9,
    "qs_pg:pop_sr":0,
    "qs_pg:qs_pg_placetype":"neighbourhood",
    "qs_pg:qs_pg_placetype_gp":"Suburb",
    "qs_pg:woe_adm0":23424768,
    "woe:adm0_id":23424768,
    "woe:name_adm0":"Brasil",
    "woe:name_adm1":"Santa Catarina",
    "woe:placetype":"Suburb",
    "wof:name":"Da Barra",
    "wof:placetype":"neighbourhood"
},
  "geometry": {"coordinates":[-48.604202,-27.004537],"type":"Point"}
}