{
  "type": "Feature",
  "properties": {
    "iso:country":"XX",
    "qs_pg:name":"Perpetuo Socorro",
    "qs_pg:name_adm0":"Costa Rica",
    "qs_pg:name_adm1":"San Jose",
    "qs_pg:photos":96,
    "qs_pg:photos_1k":19,
    "qs_pg:photos_9k":1,
    "qs_pg:photos_9r":3,
    "qs_pg:photos_all":96,
    "qs_pg:photos_sr":3,
    "qs_pg:pop_sr":0,
    "qs_pg:qs_pg_placetype":"neighbourhood",
    "qs_pg:qs_pg_placetype_gp":"Suburb",
    "qs_pg:woe_adm0":23424791,
    "woe:adm0_id":23424791,
    "woe:name_adm0":"Costa Rica",
    "woe:name_adm1":"San Jose",
    "woe:placetype":"Suburb",
    "wof:name":"Perpetuo Socorro",
    "wof:placetype":"neighbourhood"
},
  "geometry": {"coordinates":[-84.103689,9.933715],"type":"Point"}
}