{
  "type": "Feature",
  "properties": {
    "iso:country":"XX",
    "qs_pg:name":"Kirkjub\u00f3l",
    "qs_pg:name_adm0":"\u00cdsland",
    "qs_pg:name_adm1":"Sudur-Mulasysla",
    "qs_pg:photos":258,
    "qs_pg:photos_1k":52,
    "qs_pg:photos_9k":1,
    "qs_pg:photos_9r":4,
    "qs_pg:photos_all":258,
    "qs_pg:photos_sr":5,
    "qs_pg:pop_sr":0,
    "qs_pg:qs_pg_placetype":"locality",
    "qs_pg:qs_pg_placetype_gp":"Town",
    "qs_pg:woe_adm0":23424845,
    "woe:adm0_id":23424845,
    "woe:name_adm0":"\u00cdsland",
    "woe:name_adm1":"Sudur-Mulasysla",
    "woe:placetype":"Town",
    "wof:name":"Kirkjub\u00f3l",
    "wof:placetype":"locality"
},
  "geometry": {"coordinates":[-13.880195,64.83538799999999],"type":"Point"}
}