{
  "type": "Feature",
  "properties": {
    "iso:country":"XX",
    "qs_pg:name":"Mekor Barukh",
    "qs_pg:name_adm0":"Israel",
    "qs_pg:name_adm1":"Jerusalem",
    "qs_pg:photos":101,
    "qs_pg:photos_1k":20,
    "qs_pg:photos_9k":1,
    "qs_pg:photos_9r":3,
    "qs_pg:photos_all":101,
    "qs_pg:photos_sr":3,
    "qs_pg:pop_sr":0,
    "qs_pg:qs_pg_placetype":"neighbourhood",
    "qs_pg:qs_pg_placetype_gp":"Suburb",
    "qs_pg:woe_adm0":23424852,
    "woe:adm0_id":23424852,
    "woe:name_adm0":"Israel",
    "woe:name_adm1":"Jerusalem",
    "woe:placetype":"Suburb",
    "wof:name":"Mekor Barukh",
    "wof:placetype":"neighbourhood"
},
  "geometry": {"coordinates":[35.20513,31.788711],"type":"Point"}
}