{
  "type": "Feature",
  "properties": {
    "iso:country":"XX",
    "name:dan_x_preferred":[
        "No More"
    ],
    "name:deu_x_preferred":[
        "La Paloma"
    ],
    "name:ell_x_preferred":[
        "La Paloma"
    ],
    "name:fin_x_preferred":[
        "La Paloma"
    ],
    "name:fra_x_preferred":[
        "La paloma"
    ],
    "name:hun_x_preferred":[
        "La Paloma"
    ],
    "name:ita_x_preferred":[
        "La paloma"
    ],
    "name:nld_x_preferred":[
        "La Paloma ade"
    ],
    "name:nno_x_preferred":[
        "La Paloma"
    ],
    "name:nor_x_preferred":[
        "La paloma"
    ],
    "name:pol_x_preferred":[
        "La Paloma"
    ],
    "name:por_x_preferred":[
        "La Paloma"
    ],
    "name:pus_x_preferred":[
        "\u0644\u0647 \u067e\u0644\u0648\u0645\u0627"
    ],
    "name:rus_x_preferred":[
        "\u0413\u043e\u043b\u0443\u0431\u043a\u0430"
    ],
    "name:spa_x_preferred":[
        "La paloma"
    ],
    "name:tha_x_preferred":[
        "\u0e25\u0e32\u0e1b\u0e32\u0e42\u0e25\u0e21\u0e32"
    ],
    "name:tur_x_preferred":[
        "La Paloma"
    ],
    "name:ukr_x_preferred":[
        "\u0413\u043e\u043b\u0443\u0431\u043a\u0430"
    ],
    "name:vie_x_preferred":[
        "C\u00e1nh bu\u1ed3m xa x\u01b0a"
    ],
    "qs_pg:name":"La Paloma",
    "qs_pg:name_adm0":"M\u00e9xico",
    "qs_pg:name_adm1":"Baja California",
    "qs_pg:photos":216,
    "qs_pg:photos_1k":44,
    "qs_pg:photos_9k":1,
    "qs_pg:photos_9r":4,
    "qs_pg:photos_all":216,
    "qs_pg:photos_sr":4,
    "qs_pg:pop_sr":0,
    "qs_pg:qs_pg_placetype":"neighbourhood",
    "qs_pg:qs_pg_placetype_gp":"Suburb",
    "qs_pg:woe_adm0":23424900,
    "woe:adm0_id":23424900,
    "woe:name_adm0":"M\u00e9xico",
    "woe:name_adm1":"Baja California",
    "woe:placetype":"Suburb",
    "wof:name":"La Paloma",
    "wof:placetype":"neighbourhood"
},
  "geometry": {"coordinates":[-117.055831,32.3345575],"type":"Point"}
}