{
  "type": "Feature",
  "properties": {
    "iso:country":"XX",
    "qs_pg:name":"La Paloma",
    "qs_pg:name_adm0":"M\u00e9xico",
    "qs_pg:name_adm1":"Baja California",
    "qs_pg:photos":216,
    "qs_pg:photos_1k":44,
    "qs_pg:photos_9k":1,
    "qs_pg:photos_9r":4,
    "qs_pg:photos_all":216,
    "qs_pg:photos_sr":4,
    "qs_pg:pop_sr":0,
    "qs_pg:qs_pg_placetype":"neighbourhood",
    "qs_pg:qs_pg_placetype_gp":"Suburb",
    "qs_pg:woe_adm0":23424900,
    "woe:adm0_id":23424900,
    "woe:name_adm0":"M\u00e9xico",
    "woe:name_adm1":"Baja California",
    "woe:placetype":"Suburb",
    "wof:name":"La Paloma",
    "wof:placetype":"neighbourhood"
},
  "geometry": {"coordinates":[-117.055831,32.3345575],"type":"Point"}
}