{
  "type": "Feature",
  "properties": {
    "iso:country":"XX",
    "name:bpy_x_preferred":[
        "\u09b8\u09be\u09a8\u09cd\u099f\u09cb \u0987\u09a8\u09be\u09b8\u09bf\u0993"
    ],
    "name:epo_x_preferred":[
        "Santo In\u00e1cio"
    ],
    "name:eus_x_preferred":[
        "Santo In\u00e1cio"
    ],
    "name:fra_x_preferred":[
        "Santo In\u00e1cio"
    ],
    "name:ita_x_preferred":[
        "Santo In\u00e1cio"
    ],
    "name:kat_x_preferred":[
        "\u10e1\u10d0\u10dc\u10e2\u10e3-\u10d8\u10dc\u10d0\u10e1\u10d8\u10e3"
    ],
    "name:mlg_x_preferred":[
        "Santo In\u00e1cio"
    ],
    "name:nld_x_preferred":[
        "Santo In\u00e1cio"
    ],
    "name:nor_x_preferred":[
        "Santo In\u00e1cio"
    ],
    "name:pol_x_preferred":[
        "Santo In\u00e1cio"
    ],
    "name:por_x_preferred":[
        "Santo In\u00e1cio"
    ],
    "name:ron_x_preferred":[
        "Santo In\u00e1cio"
    ],
    "name:rus_x_preferred":[
        "\u0421\u0430\u043d\u0442\u0443-\u0418\u043d\u0430\u0441\u0438\u0443"
    ],
    "name:spa_x_preferred":[
        "Santo In\u00e1cio"
    ],
    "name:vie_x_preferred":[
        "Santo In\u00e1cio"
    ],
    "name:vol_x_preferred":[
        "Santo In\u00e1cio"
    ],
    "name:war_x_preferred":[
        "Santo In\u00e1cio"
    ],
    "name:zho_x_preferred":[
        "\u5723\u4f0a\u7eb3\u897f\u4e4c"
    ],
    "qs_pg:name":"Santo In\u00e1cio",
    "qs_pg:name_adm0":"Brasil",
    "qs_pg:name_adm1":"Paran\u00e1",
    "qs_pg:photos":1020,
    "qs_pg:photos_1k":207,
    "qs_pg:photos_9k":5,
    "qs_pg:photos_9r":7,
    "qs_pg:photos_all":1020,
    "qs_pg:photos_sr":11,
    "qs_pg:pop_sr":0,
    "qs_pg:qs_pg_placetype":"neighbourhood",
    "qs_pg:qs_pg_placetype_gp":"Suburb",
    "qs_pg:woe_adm0":23424768,
    "woe:adm0_id":23424768,
    "woe:name_adm0":"Brasil",
    "woe:name_adm1":"Paran\u00e1",
    "woe:placetype":"Suburb",
    "wof:name":"Santo In\u00e1cio",
    "wof:placetype":"neighbourhood"
},
  "geometry": {"coordinates":[-49.324352,-25.425989],"type":"Point"}
}