{
  "type": "Feature",
  "properties": {
    "iso:country":"XX",
    "qs_pg:name":"Uuslinn",
    "qs_pg:name_adm0":"Eesti",
    "qs_pg:name_adm1":"Harjumaa",
    "qs_pg:photos":1463,
    "qs_pg:photos_1k":296,
    "qs_pg:photos_9k":6,
    "qs_pg:photos_9r":7,
    "qs_pg:photos_all":1463,
    "qs_pg:photos_sr":12,
    "qs_pg:pop_sr":0,
    "qs_pg:qs_pg_placetype":"neighbourhood",
    "qs_pg:qs_pg_placetype_gp":"Suburb",
    "qs_pg:woe_adm0":23424805,
    "woe:adm0_id":23424805,
    "woe:name_adm0":"Eesti",
    "woe:name_adm1":"Harjumaa",
    "woe:placetype":"Suburb",
    "wof:name":"Uuslinn",
    "wof:placetype":"neighbourhood"
},
  "geometry": {"coordinates":[24.807128,59.444409],"type":"Point"}
}