{
  "type": "Feature",
  "properties": {
    "iso:country":"XX",
    "qs_pg:name":"Bakar-Dio",
    "qs_pg:name_adm0":"Hrvatska",
    "qs_pg:name_adm1":"Primorsko-Goranska",
    "qs_pg:photos":96,
    "qs_pg:photos_1k":19,
    "qs_pg:photos_9k":1,
    "qs_pg:photos_9r":3,
    "qs_pg:photos_all":96,
    "qs_pg:photos_sr":3,
    "qs_pg:pop_sr":0,
    "qs_pg:qs_pg_placetype":"locality",
    "qs_pg:qs_pg_placetype_gp":"Town",
    "qs_pg:woe_adm0":23424843,
    "woe:adm0_id":23424843,
    "woe:name_adm0":"Hrvatska",
    "woe:name_adm1":"Primorsko-Goranska",
    "woe:placetype":"Town",
    "wof:name":"Bakar-Dio",
    "wof:placetype":"locality"
},
  "geometry": {"coordinates":[14.53592,45.306726],"type":"Point"}
}