{
  "type": "Feature",
  "properties": {
    "iso:country":"XX",
    "name:eng_x_preferred":[
        "Carver"
    ],
    "name:nld_x_preferred":[
        "Carver"
    ],
    "qs_pg:name":"Carver",
    "qs_pg:name_adm0":"United States",
    "qs_pg:name_adm1":"Virginia",
    "qs_pg:photos":1053,
    "qs_pg:photos_1k":213,
    "qs_pg:photos_9k":5,
    "qs_pg:photos_9r":7,
    "qs_pg:photos_all":1053,
    "qs_pg:photos_sr":11,
    "qs_pg:pop_sr":0,
    "qs_pg:qs_pg_placetype":"neighbourhood",
    "qs_pg:qs_pg_placetype_gp":"Suburb",
    "qs_pg:woe_adm0":23424977,
    "woe:adm0_id":23424977,
    "woe:name_adm0":"United States",
    "woe:name_adm1":"Virginia",
    "woe:placetype":"Suburb",
    "wof:name":"Carver",
    "wof:placetype":"neighbourhood"
},
  "geometry": {"coordinates":[-77.452336,37.55293],"type":"Point"}
}