{
  "type": "Feature",
  "properties": {
    "iso:country":"XX",
    "qs_pg:name":"Subotica",
    "qs_pg:name_adm0":"Serbia",
    "qs_pg:name_adm1":"Severna Bachka",
    "qs_pg:photos":2027,
    "qs_pg:photos_1k":411,
    "qs_pg:photos_9k":9,
    "qs_pg:photos_9r":9,
    "qs_pg:photos_all":2027,
    "qs_pg:photos_sr":15,
    "qs_pg:pop_sr":0,
    "qs_pg:qs_pg_placetype":"locality",
    "qs_pg:qs_pg_placetype_gp":"Town",
    "qs_pg:woe_adm0":20069818,
    "woe:adm0_id":20069818,
    "woe:name_adm0":"Serbia",
    "woe:name_adm1":"Severna Bachka",
    "woe:placetype":"Town",
    "wof:name":"Subotica",
    "wof:placetype":"locality"
},
  "geometry": {"coordinates":[19.672908,46.098412],"type":"Point"}
}