{
  "type": "Feature",
  "properties": {
    "iso:country":"XX",
    "qs_pg:name":"Rigot",
    "qs_pg:name_adm0":"Bonaire Saint Eustatius and Saba",
    "qs_pg:name_adm1":"Bonaire",
    "qs_pg:photos":81,
    "qs_pg:photos_1k":16,
    "qs_pg:photos_9k":1,
    "qs_pg:photos_9r":3,
    "qs_pg:photos_all":81,
    "qs_pg:photos_sr":3,
    "qs_pg:pop_sr":0,
    "qs_pg:qs_pg_placetype":"locality",
    "qs_pg:qs_pg_placetype_gp":"Town",
    "qs_pg:woe_adm0":56558056,
    "woe:adm0_id":56558056,
    "woe:name_adm0":"Bonaire Saint Eustatius and Saba",
    "woe:name_adm1":"Bonaire",
    "woe:placetype":"Town",
    "wof:name":"Rigot",
    "wof:placetype":"locality"
},
  "geometry": {"coordinates":[-68.355131,12.257231],"type":"Point"}
}