{
  "type": "Feature",
  "properties": {
    "iso:country":"XX",
    "name:ceb_x_preferred":[
        "Moldovi\u021ba"
    ],
    "name:eng_x_preferred":[
        "Moldovi\u021ba"
    ],
    "name:fra_x_preferred":[
        "Moldovi\u021ba"
    ],
    "name:ita_x_preferred":[
        "Moldovi\u021ba"
    ],
    "name:msa_x_preferred":[
        "Moldovi\u021ba"
    ],
    "name:nld_x_preferred":[
        "Moldovi\u021ba"
    ],
    "name:pol_x_preferred":[
        "Mo\u0142dawica"
    ],
    "name:por_x_preferred":[
        "Moldovi\u021ba"
    ],
    "name:ron_x_preferred":[
        "Moldovi\u021ba"
    ],
    "name:srp_x_preferred":[
        "\u041c\u043e\u043b\u0434\u0430\u0432\u0438\u0446\u0430"
    ],
    "name:ukr_x_preferred":[
        "\u041c\u043e\u043b\u0434\u043e\u0432\u0438\u0446\u044f"
    ],
    "name:vie_x_preferred":[
        "Moldovita"
    ],
    "name:vol_x_preferred":[
        "Moldovi\u021ba"
    ],
    "qs_pg:name":"Moldovi\u021ba",
    "qs_pg:name_adm0":"Rom\u00e2nia",
    "qs_pg:name_adm1":"Suceava",
    "qs_pg:photos":342,
    "qs_pg:photos_1k":69,
    "qs_pg:photos_9k":2,
    "qs_pg:photos_9r":5,
    "qs_pg:photos_all":342,
    "qs_pg:photos_sr":5,
    "qs_pg:pop_sr":0,
    "qs_pg:qs_pg_placetype":"locality",
    "qs_pg:qs_pg_placetype_gp":"Town",
    "qs_pg:woe_adm0":23424933,
    "woe:adm0_id":23424933,
    "woe:name_adm0":"Rom\u00e2nia",
    "woe:name_adm1":"Suceava",
    "woe:placetype":"Town",
    "wof:name":"Moldovi\u021ba",
    "wof:placetype":"locality"
},
  "geometry": {"coordinates":[25.534286,47.680703],"type":"Point"}
}