{
  "type": "Feature",
  "properties": {
    "iso:country":"XX",
    "name:arm_x_preferred":[
        "\u054e\u056b\u0584"
    ],
    "name:baq_x_preferred":[
        "V\u00edk \u00ed M\u00fdrdal"
    ],
    "name:bel_x_preferred":[
        "\u0412\u0451\u0441\u043a\u0430 \u0412\u0456\u043a"
    ],
    "name:cat_x_preferred":[
        "V\u00edk \u00ed M\u00fdrdal"
    ],
    "name:chi_x_preferred":[
        "\u7dad\u514b"
    ],
    "name:cze_x_preferred":[
        "V\u00edk \u00ed M\u00fdrdal"
    ],
    "name:dan_x_preferred":[
        "V\u00edk \u00ed M\u00fdrdal"
    ],
    "name:dut_x_preferred":[
        "V\u00edk \u00ed M\u00fdrdal"
    ],
    "name:eng_x_preferred":[
        "V\u00edk \u00ed M\u00fdrdal"
    ],
    "name:fre_x_preferred":[
        "V\u00edk \u00ed M\u00fdrdal"
    ],
    "name:ger_x_preferred":[
        "V\u00edk \u00ed M\u00fdrdal"
    ],
    "name:hun_x_preferred":[
        "V\u00edk \u00ed M\u00fdrdal"
    ],
    "name:ice_x_preferred":[
        "V\u00edk \u00ed M\u00fdrdal"
    ],
    "name:ita_x_preferred":[
        "V\u00edk \u00ed M\u00fdrdal"
    ],
    "name:jpn_x_preferred":[
        "\u30f4\u30a3\u30fc\u30af"
    ],
    "name:kor_x_preferred":[
        "\ube44\ud06c"
    ],
    "name:lit_x_preferred":[
        "Vikas"
    ],
    "name:nob_x_preferred":[
        "V\u00edk \u00ed M\u00fdrdal"
    ],
    "name:oss_x_preferred":[
        "\u0412\u0438\u043a"
    ],
    "name:pms_x_preferred":[
        "V\u00edk"
    ],
    "name:pol_x_preferred":[
        "V\u00edk \u00ed M\u00fdrdal"
    ],
    "name:por_x_preferred":[
        "V\u00edk \u00ed M\u00fdrdal"
    ],
    "name:rus_x_preferred":[
        "\u0412\u0438\u043a"
    ],
    "name:spa_x_preferred":[
        "V\u00edk \u00ed M\u00fdrdal"
    ],
    "name:swe_x_preferred":[
        "V\u00edk \u00ed M\u00fdrdal"
    ],
    "name:tur_x_preferred":[
        "V\u00edk \u00ed M\u00fdrdal"
    ],
    "name:ukr_x_preferred":[
        "\u0412\u0456\u043a \u0456 \u041c\u0456\u0440\u0434\u0430\u043b"
    ],
    "name:vol_x_preferred":[
        "V\u00edk \u00ed M\u00fdrdal"
    ],
    "qs_pg:name":"Vik I Myrdal",
    "qs_pg:name_adm0":"\u00cdsland",
    "qs_pg:name_adm1":"Vestur-Skaftafellssysla",
    "qs_pg:photos":1016,
    "qs_pg:photos_1k":206,
    "qs_pg:photos_9k":5,
    "qs_pg:photos_9r":7,
    "qs_pg:photos_all":1016,
    "qs_pg:photos_sr":11,
    "qs_pg:pop_sr":0,
    "qs_pg:qs_pg_placetype":"locality",
    "qs_pg:qs_pg_placetype_gp":"Town",
    "qs_pg:woe_adm0":23424845,
    "woe:adm0_id":23424845,
    "woe:name_adm0":"\u00cdsland",
    "woe:name_adm1":"Vestur-Skaftafellssysla",
    "woe:placetype":"Town",
    "wof:name":"Vik I Myrdal",
    "wof:placetype":"locality"
},
  "geometry": {"coordinates":[-19.125909,63.403667],"type":"Point"}
}