{
  "type": "Feature",
  "properties": {
    "iso:country":"XX",
    "name:cha_x_preferred":[
        "Yo\u00f1a"
    ],
    "name:dut_x_preferred":[
        "Yona"
    ],
    "name:eng_x_preferred":[
        "Yona"
    ],
    "name:fre_x_preferred":[
        "Yona"
    ],
    "name:ita_x_preferred":[
        "Yona"
    ],
    "name:jpn_x_preferred":[
        "\u30b8\u30e7\u30fc\u30cb\u30e3"
    ],
    "name:kor_x_preferred":[
        "\uc870\ub0d0"
    ],
    "name:per_x_preferred":[
        "\u06cc\u0648\u0646\u0627\u060c \u06af\u0648\u0622\u0645"
    ],
    "name:pol_x_preferred":[
        "Yona"
    ],
    "name:rus_x_preferred":[
        "\u0414\u0437\u043e\u043d\u044c\u044f"
    ],
    "name:spa_x_preferred":[
        "Yona"
    ],
    "name:swe_x_preferred":[
        "Yona Village"
    ],
    "name:urd_x_preferred":[
        "\u06cc\u0648\u0646\u06c1\u060c \u06af\u0648\u0627\u0645"
    ],
    "name:war_x_preferred":[
        "Yona"
    ],
    "qs_pg:name":"Yona",
    "qs_pg:name_adm0":"Guam",
    "qs_pg:name_adm1":"Yona",
    "qs_pg:photos":108,
    "qs_pg:photos_1k":22,
    "qs_pg:photos_9k":1,
    "qs_pg:photos_9r":3,
    "qs_pg:photos_all":108,
    "qs_pg:photos_sr":3,
    "qs_pg:pop_sr":0,
    "qs_pg:qs_pg_placetype":"locality",
    "qs_pg:qs_pg_placetype_gp":"Town",
    "qs_pg:woe_adm0":23424832,
    "woe:adm0_id":23424832,
    "woe:name_adm0":"Guam",
    "woe:name_adm1":"Yona",
    "woe:placetype":"Town",
    "wof:name":"Yona",
    "wof:placetype":"locality"
},
  "geometry": {"coordinates":[144.77299400000001,13.4152225],"type":"Point"}
}