{
  "type": "Feature",
  "properties": {
    "gn:country":"XX",
    "iso:country":"XX",
    "name:ben_x_preferred":[
        "\u09ab\u09cb\u09a4\u09c1 \u0997\u09bf\u09b0\u09bf\u09ac\u09b0\u09cd\u09a4\u09cd\u09ae"
    ],
    "name:ceb_x_preferred":[
        "Fotu La"
    ],
    "name:deu_x_preferred":[
        "Fotu La"
    ],
    "name:eng_x_preferred":[
        "Fotu La"
    ],
    "name:guj_x_preferred":[
        "\u0aab\u0acb\u0aa4\u0ac1 \u0a98\u0abe\u0a9f"
    ],
    "name:hin_x_preferred":[
        "\u092b\u094b\u0924\u0941 \u0932\u093e"
    ],
    "name:nld_x_preferred":[
        "Fatu La"
    ],
    "name:por_x_preferred":[
        "Fotu La"
    ],
    "name:swe_x_preferred":[
        "Fotu La"
    ],
    "name:urd_x_preferred":[
        "\u0641\u0648\u0679\u0648 \u0644\u0627"
    ],
    "qs:name":"Fotu La",
    "qs:name_adm0":"India",
    "qs:name_adm1":"Jammu and Kashmir",
    "qs:photos":57,
    "qs:photos_1k":12,
    "qs:photos_9k":1,
    "qs:photos_9r":2,
    "qs:photos_all":57,
    "qs:photos_sr":2,
    "qs:placetype":"Town",
    "qs:pop_sr":"0",
    "wd:wordcount":128,
    "wof:name":"Fotu La",
    "wof:placetype":"locality"
},
  "geometry": {"coordinates":[76.702423,34.2938],"type":"Point"}
}