{
  "type": "Feature",
  "properties": {
    "gn:country":"XX",
    "iso:country":"XX",
    "qs:name":"Fotu La",
    "qs:name_adm0":"India",
    "qs:name_adm1":"Jammu and Kashmir",
    "qs:photos":57,
    "qs:photos_1k":12,
    "qs:photos_9k":1,
    "qs:photos_9r":2,
    "qs:photos_all":57,
    "qs:photos_sr":2,
    "qs:placetype":"Town",
    "qs:pop_sr":"0",
    "wd:wordcount":128,
    "wof:name":"Fotu La",
    "wof:placetype":"locality"
},
  "geometry": {"coordinates":[76.702423,34.2938],"type":"Point"}
}