{
  "type": "Feature",
  "properties": {
    "iso:country":"XX",
    "name:ara_x_preferred":[
        "\u0644\u0627\u0633\u0627\u0631\u062a\u064a-\u0623\u0648\u0631\u064a\u0627"
    ],
    "name:arg_x_preferred":[
        "Lasarte-Oria"
    ],
    "name:ast_x_preferred":[
        "Lasarte-Oria"
    ],
    "name:bre_x_preferred":[
        "Lasarte-Oria"
    ],
    "name:cat_x_preferred":[
        "Lasarte-Oria"
    ],
    "name:ceb_x_preferred":[
        "Lasarte-Oria"
    ],
    "name:dan_x_preferred":[
        "Lasarte-Oria"
    ],
    "name:deu_x_preferred":[
        "Lasarte-Oria"
    ],
    "name:eng_x_preferred":[
        "Lasarte-Oria"
    ],
    "name:epo_x_preferred":[
        "Lasarto-Orio"
    ],
    "name:eus_x_preferred":[
        "Lasarte-Oria"
    ],
    "name:fao_x_preferred":[
        "Lasarte-Oria"
    ],
    "name:fra_x_preferred":[
        "Lasarte-Oria"
    ],
    "name:glg_x_preferred":[
        "Lasarte-Oria"
    ],
    "name:hun_x_preferred":[
        "Lasarte-Oria"
    ],
    "name:ita_x_preferred":[
        "Lasarte-Oria"
    ],
    "name:jpn_x_preferred":[
        "\u30e9\u30b5\u30eb\u30c6\uff1d\u30aa\u30ea\u30a2"
    ],
    "name:kal_x_preferred":[
        "Lasarte-Oria"
    ],
    "name:lit_x_preferred":[
        "Lasarte Orija"
    ],
    "name:msa_x_preferred":[
        "Lasarte-Oria"
    ],
    "name:nld_x_preferred":[
        "Lasarte-Oria"
    ],
    "name:nno_x_preferred":[
        "Lasarte-Oria"
    ],
    "name:nob_x_preferred":[
        "Lasarte-Oria"
    ],
    "name:oci_x_preferred":[
        "Lasarte-Oria"
    ],
    "name:pol_x_preferred":[
        "Lasarte-Oria"
    ],
    "name:por_x_preferred":[
        "Lasarte-Oria"
    ],
    "name:rus_x_preferred":[
        "\u041b\u0430\u0441\u0430\u0440\u0442\u0435-\u041e\u0440\u0438\u0430"
    ],
    "name:sco_x_preferred":[
        "Lasarte-Oria"
    ],
    "name:spa_x_preferred":[
        "Lasarte-Oria"
    ],
    "name:swe_x_preferred":[
        "Lasarte-Oria"
    ],
    "name:szl_x_preferred":[
        "Lasarte-Oria"
    ],
    "name:ukr_x_preferred":[
        "\u041b\u0430\u0441\u0430\u0440\u0442\u0435-\u041e\u0440\u0456\u044f"
    ],
    "name:uzb_x_preferred":[
        "Lasarte-Oria"
    ],
    "name:vie_x_preferred":[
        "Lasarte-Oria"
    ],
    "name:war_x_preferred":[
        "Lasarte-Oria"
    ],
    "name:zho_x_preferred":[
        "\u62c9\u8428\u5c14\u7279-\u5965\u91cc\u4e9a"
    ],
    "qs_pg:name":"Lasarte-Oria",
    "qs_pg:name_adm0":"Espa\u00f1a",
    "qs_pg:name_adm1":"Euskadi",
    "qs_pg:photos":375,
    "qs_pg:photos_1k":76,
    "qs_pg:photos_9k":2,
    "qs_pg:photos_9r":5,
    "qs_pg:photos_all":375,
    "qs_pg:photos_sr":6,
    "qs_pg:pop_sr":0,
    "qs_pg:qs_pg_placetype":"locality",
    "qs_pg:qs_pg_placetype_gp":"Town",
    "qs_pg:woe_adm0":23424950,
    "woe:adm0_id":23424950,
    "woe:name_adm0":"Espa\u00f1a",
    "woe:name_adm1":"Euskadi",
    "woe:placetype":"Town",
    "wof:name":"Lasarte-Oria",
    "wof:placetype":"locality"
},
  "geometry": {"coordinates":[-2.02041,43.270514],"type":"Point"}
}