{
  "type": "Feature",
  "properties": {
    "iso:country":"XX",
    "qs_pg:name":"Obrera",
    "qs_pg:name_adm0":"M\u00e9xico",
    "qs_pg:name_adm1":"Tamaulipas",
    "qs_pg:photos":192,
    "qs_pg:photos_1k":39,
    "qs_pg:photos_9k":1,
    "qs_pg:photos_9r":4,
    "qs_pg:photos_all":192,
    "qs_pg:photos_sr":4,
    "qs_pg:pop_sr":0,
    "qs_pg:qs_pg_placetype":"neighbourhood",
    "qs_pg:qs_pg_placetype_gp":"Suburb",
    "qs_pg:woe_adm0":23424900,
    "woe:adm0_id":23424900,
    "woe:name_adm0":"M\u00e9xico",
    "woe:name_adm1":"Tamaulipas",
    "woe:placetype":"Suburb",
    "wof:name":"Obrera",
    "wof:placetype":"neighbourhood"
},
  "geometry": {"coordinates":[-97.852048,22.234327],"type":"Point"}
}