{
  "type": "Feature",
  "properties": {
    "iso:country":"XX",
    "name:kor_x_preferred":[
        "\uc778\ub354\uc2a4\ud2b8\ub9ac\uc5bc"
    ],
    "name:nld_x_preferred":[
        "Industrial"
    ],
    "name:por_x_preferred":[
        "Industrial"
    ],
    "name:rus_x_preferred":[
        "\u0418\u043d\u0434\u0430\u0441\u0442\u0440\u0438\u0430\u043b"
    ],
    "name:spa_x_preferred":[
        "Industrial"
    ],
    "name:tur_x_preferred":[
        "End\u00fcstriyel"
    ],
    "name:urd_x_preferred":[
        "\u0635\u0646\u0639\u062a\u06cc"
    ],
    "qs_pg:name":"Industrial",
    "qs_pg:name_adm0":"M\u00e9xico",
    "qs_pg:name_adm1":"Distrito Federal",
    "qs_pg:photos":179,
    "qs_pg:photos_1k":36,
    "qs_pg:photos_9k":1,
    "qs_pg:photos_9r":4,
    "qs_pg:photos_all":179,
    "qs_pg:photos_sr":4,
    "qs_pg:pop_sr":0,
    "qs_pg:qs_pg_placetype":"neighbourhood",
    "qs_pg:qs_pg_placetype_gp":"Suburb",
    "qs_pg:woe_adm0":23424900,
    "woe:adm0_id":23424900,
    "woe:name_adm0":"M\u00e9xico",
    "woe:name_adm1":"Distrito Federal",
    "woe:placetype":"Suburb",
    "wof:name":"Industrial",
    "wof:placetype":"neighbourhood"
},
  "geometry": {"coordinates":[-99.12531199999999,19.482281],"type":"Point"}
}