{
  "type": "Feature",
  "properties": {
    "iso:country":"XX",
    "qs_pg:name":"Near West",
    "qs_pg:name_adm0":"United States",
    "qs_pg:name_adm1":"Virginia",
    "qs_pg:photos":3439,
    "qs_pg:photos_1k":697,
    "qs_pg:photos_9k":15,
    "qs_pg:photos_9r":11,
    "qs_pg:photos_all":3439,
    "qs_pg:photos_sr":20,
    "qs_pg:pop_sr":0,
    "qs_pg:qs_pg_placetype":"neighbourhood",
    "qs_pg:qs_pg_placetype_gp":"Suburb",
    "qs_pg:woe_adm0":23424977,
    "woe:adm0_id":23424977,
    "woe:name_adm0":"United States",
    "woe:name_adm1":"Virginia",
    "woe:placetype":"Suburb",
    "wof:name":"Near West",
    "wof:placetype":"neighbourhood"
},
  "geometry": {"coordinates":[-77.476572,37.54063],"type":"Point"}
}