{
  "type": "Feature",
  "properties": {
    "iso:country":"XX",
    "qs_pg:name":"Batemans Bay Central",
    "qs_pg:name_adm0":"Australia",
    "qs_pg:name_adm1":"New South Wales",
    "qs_pg:photos":829,
    "qs_pg:photos_1k":168,
    "qs_pg:photos_9k":4,
    "qs_pg:photos_9r":6,
    "qs_pg:photos_all":829,
    "qs_pg:photos_sr":9,
    "qs_pg:pop_sr":0,
    "qs_pg:qs_pg_placetype":"neighbourhood",
    "qs_pg:qs_pg_placetype_gp":"Suburb",
    "qs_pg:woe_adm0":23424748,
    "woe:adm0_id":23424748,
    "woe:name_adm0":"Australia",
    "woe:name_adm1":"New South Wales",
    "woe:placetype":"Suburb",
    "wof:name":"Batemans Bay Central",
    "wof:placetype":"neighbourhood"
},
  "geometry": {"coordinates":[150.176582,-35.708259],"type":"Point"}
}