{
  "type": "Feature",
  "properties": {
    "iso:country":"XX",
    "name:ara_x_preferred":[
        "\u0634\u0641\u064a\u062f\u062a"
    ],
    "name:cat_x_preferred":[
        "Schwedt"
    ],
    "name:ces_x_preferred":[
        "Schwedt"
    ],
    "name:csb_x_preferred":[
        "Swiec\u00e9"
    ],
    "name:dan_x_preferred":[
        "Schwedt/Oder"
    ],
    "name:deu_x_preferred":[
        "Schwedt/Oder"
    ],
    "name:ell_x_preferred":[
        "\u03a3\u03b2\u03b5\u03c4"
    ],
    "name:eng_x_preferred":[
        "Schwedt"
    ],
    "name:epo_x_preferred":[
        "Schwedt"
    ],
    "name:fas_x_preferred":[
        "\u0634\u0648\u062f\u062a"
    ],
    "name:fra_x_preferred":[
        "Schwedt"
    ],
    "name:hak_x_preferred":[
        "Schwedt"
    ],
    "name:heb_x_preferred":[
        "\u05e9\u05d5\u05d5\u05d8 \u05e2\u05dc \u05d4\u05d0\u05d5\u05d3\u05e8"
    ],
    "name:hsb_x_preferred":[
        "Schwedt"
    ],
    "name:hun_x_preferred":[
        "Schwedt/Oder"
    ],
    "name:hye_x_preferred":[
        "\u0547\u057e\u0565\u0564\u057f"
    ],
    "name:ind_x_preferred":[
        "Schwedt"
    ],
    "name:ita_x_preferred":[
        "Schwedt/Oder"
    ],
    "name:jpn_x_preferred":[
        "\u30b7\u30e5\u30f4\u30a7\u30fc\u30c8/\u30aa\u30fc\u30c0\u30fc"
    ],
    "name:lav_x_preferred":[
        "\u0160vete/Odera"
    ],
    "name:mkd_x_preferred":[
        "\u0428\u0432\u0435\u0442"
    ],
    "name:msa_x_preferred":[
        "Schwedt"
    ],
    "name:nld_x_preferred":[
        "Schwedt/Oder"
    ],
    "name:nob_x_preferred":[
        "Schwedt"
    ],
    "name:oci_x_preferred":[
        "Schwedt"
    ],
    "name:pol_x_preferred":[
        "Schwedt/Oder"
    ],
    "name:por_x_preferred":[
        "Schwedt"
    ],
    "name:ron_x_preferred":[
        "Schwedt/Oder"
    ],
    "name:rus_x_preferred":[
        "\u0428\u0432\u0435\u0434\u0442"
    ],
    "name:slv_x_preferred":[
        "Schwedt"
    ],
    "name:spa_x_preferred":[
        "Schwedt"
    ],
    "name:sqi_x_preferred":[
        "Schwedt"
    ],
    "name:srp_x_preferred":[
        "\u0428\u0432\u0435\u0442"
    ],
    "name:swe_x_preferred":[
        "Schwedt"
    ],
    "name:ukr_x_preferred":[
        "\u0428\u0432\u0435\u0434\u0442"
    ],
    "name:uzb_x_preferred":[
        "Schwedt"
    ],
    "name:vie_x_preferred":[
        "Schwedt"
    ],
    "name:vol_x_preferred":[
        "Schwedt/Oder"
    ],
    "name:war_x_preferred":[
        "Schwedt"
    ],
    "name:zho_x_preferred":[
        "\u65bd\u97e6\u7279"
    ],
    "qs_pg:name":"Schwedt",
    "qs_pg:name_adm0":"Deutschland",
    "qs_pg:name_adm1":"Bundesland Brandenburg",
    "qs_pg:photos":622,
    "qs_pg:photos_1k":126,
    "qs_pg:photos_9k":3,
    "qs_pg:photos_9r":5,
    "qs_pg:photos_all":622,
    "qs_pg:photos_sr":8,
    "qs_pg:pop_sr":0,
    "qs_pg:qs_pg_placetype":"locality",
    "qs_pg:qs_pg_placetype_gp":"Town",
    "qs_pg:woe_adm0":23424829,
    "woe:adm0_id":23424829,
    "woe:name_adm0":"Deutschland",
    "woe:name_adm1":"Bundesland Brandenburg",
    "woe:placetype":"Town",
    "wof:name":"Schwedt",
    "wof:placetype":"locality"
},
  "geometry": {"coordinates":[14.286003,53.054679],"type":"Point"}
}