{
  "type": "Feature",
  "properties": {
    "iso:country":"XX",
    "qs_pg:name":"\uff11\u4e01\u76ee",
    "qs_pg:name_adm0":"\u65e5\u672c",
    "qs_pg:name_adm1":"\u5e83\u5cf6\u770c",
    "qs_pg:photos":2437,
    "qs_pg:photos_1k":494,
    "qs_pg:photos_9k":11,
    "qs_pg:photos_9r":10,
    "qs_pg:photos_all":2437,
    "qs_pg:photos_sr":17,
    "qs_pg:pop_sr":0,
    "qs_pg:qs_pg_placetype":"neighbourhood",
    "qs_pg:qs_pg_placetype_gp":"Suburb",
    "qs_pg:woe_adm0":23424856,
    "woe:adm0_id":23424856,
    "woe:name_adm0":"\u65e5\u672c",
    "woe:name_adm1":"\u5e83\u5cf6\u770c",
    "woe:placetype":"Suburb",
    "wof:name":"\uff11\u4e01\u76ee",
    "wof:placetype":"neighbourhood"
},
  "geometry": {"coordinates":[132.45346699999999,34.39487],"type":"Point"}
}