{
  "type": "Feature",
  "properties": {
    "iso:country":"XX",
    "qs_pg:name":"Y\u00f8sef\u00e5b\u00e5d",
    "qs_pg:name_adm0":"Iran",
    "qs_pg:name_adm1":"Tehran",
    "qs_pg:photos":129,
    "qs_pg:photos_1k":26,
    "qs_pg:photos_9k":1,
    "qs_pg:photos_9r":3,
    "qs_pg:photos_all":129,
    "qs_pg:photos_sr":3,
    "qs_pg:pop_sr":0,
    "qs_pg:qs_pg_placetype":"neighbourhood",
    "qs_pg:qs_pg_placetype_gp":"Suburb",
    "qs_pg:woe_adm0":23424851,
    "woe:adm0_id":23424851,
    "woe:name_adm0":"Iran",
    "woe:name_adm1":"Tehran",
    "woe:placetype":"Suburb",
    "wof:name":"Y\u00f8sef\u00e5b\u00e5d",
    "wof:placetype":"neighbourhood"
},
  "geometry": {"coordinates":[51.386994,35.736532],"type":"Point"}
}