{
  "type": "Feature",
  "properties": {
    "iso:country":"XX",
    "qs_pg:name":"West Ridge B\u00e5z\u00e5r",
    "qs_pg:name_adm0":"Pakistan",
    "qs_pg:name_adm1":"Punjab",
    "qs_pg:photos":114,
    "qs_pg:photos_1k":23,
    "qs_pg:photos_9k":1,
    "qs_pg:photos_9r":3,
    "qs_pg:photos_all":114,
    "qs_pg:photos_sr":3,
    "qs_pg:pop_sr":0,
    "qs_pg:qs_pg_placetype":"neighbourhood",
    "qs_pg:qs_pg_placetype_gp":"Suburb",
    "qs_pg:woe_adm0":23424922,
    "woe:adm0_id":23424922,
    "woe:name_adm0":"Pakistan",
    "woe:name_adm1":"Punjab",
    "woe:placetype":"Suburb",
    "wof:name":"West Ridge B\u00e5z\u00e5r",
    "wof:placetype":"neighbourhood"
},
  "geometry": {"coordinates":[73.000502,33.61369],"type":"Point"}
}