{
  "type": "Feature",
  "properties": {
    "iso:country":"XX",
    "name:dut_x_preferred":[
        "P\u0103tr\u0103u\u021bi"
    ],
    "name:eng_x_preferred":[
        "P\u0103tr\u0103u\u021bi"
    ],
    "name:fre_x_preferred":[
        "P\u0103tr\u0103u\u021bi"
    ],
    "name:hun_x_preferred":[
        "P\u0103tr\u0103u\u021bi"
    ],
    "name:ita_x_preferred":[
        "P\u0103tr\u0103u\u021bi"
    ],
    "name:may_x_preferred":[
        "P\u0103tr\u0103u\u021bi"
    ],
    "name:pol_x_preferred":[
        "P\u0103tr\u0103u\u021bi"
    ],
    "name:por_x_preferred":[
        "P\u0103tr\u0103u\u021bi"
    ],
    "name:rum_x_preferred":[
        "P\u0103tr\u0103u\u021bi"
    ],
    "name:ukr_x_preferred":[
        "\u041f\u0435\u0442\u0440\u0435\u0443\u0446\u044c"
    ],
    "name:vie_x_preferred":[
        "Patrauti"
    ],
    "name:vol_x_preferred":[
        "P\u0103tr\u0103u\u021bi"
    ],
    "qs_pg:name":"P\u0103tr\u0103u\u021bi",
    "qs_pg:name_adm0":"Rom\u00e2nia",
    "qs_pg:name_adm1":"Suceava",
    "qs_pg:photos":14,
    "qs_pg:photos_1k":3,
    "qs_pg:photos_9k":1,
    "qs_pg:photos_9r":1,
    "qs_pg:photos_all":14,
    "qs_pg:photos_sr":1,
    "qs_pg:pop_sr":0,
    "qs_pg:qs_pg_placetype":"locality",
    "qs_pg:qs_pg_placetype_gp":"Town",
    "qs_pg:woe_adm0":23424933,
    "woe:adm0_id":23424933,
    "woe:name_adm0":"Rom\u00e2nia",
    "woe:name_adm1":"Suceava",
    "woe:placetype":"Town",
    "wof:name":"P\u0103tr\u0103u\u021bi",
    "wof:placetype":"locality"
},
  "geometry": {"coordinates":[26.1925135,47.7235045],"type":"Point"}
}