{
  "type": "Feature",
  "properties": {
    "iso:country":"XX",
    "qs_pg:name":"`Ula`ino Ahupua`a",
    "qs_pg:name_adm0":"United States",
    "qs_pg:name_adm1":"Hawaii",
    "qs_pg:photos":112,
    "qs_pg:photos_1k":23,
    "qs_pg:photos_9k":1,
    "qs_pg:photos_9r":3,
    "qs_pg:photos_all":112,
    "qs_pg:photos_sr":3,
    "qs_pg:pop_sr":0,
    "qs_pg:qs_pg_placetype":"neighbourhood",
    "qs_pg:qs_pg_placetype_gp":"Suburb",
    "qs_pg:woe_adm0":23424977,
    "woe:adm0_id":23424977,
    "woe:name_adm0":"United States",
    "woe:name_adm1":"Hawaii",
    "woe:placetype":"Suburb",
    "wof:name":"`Ula`ino Ahupua`a",
    "wof:placetype":"neighbourhood"
},
  "geometry": {"coordinates":[-156.06503549999999,20.799127],"type":"Point"}
}