{
  "type": "Feature",
  "properties": {
    "iso:country":"XX",
    "qs_pg:name":"Eidsv\u00e5g I Romsdal",
    "qs_pg:name_adm0":"Norge",
    "qs_pg:name_adm1":"M\u00f8re og Romsdal Fylke",
    "qs_pg:photos":75,
    "qs_pg:photos_1k":15,
    "qs_pg:photos_9k":1,
    "qs_pg:photos_9r":2,
    "qs_pg:photos_all":75,
    "qs_pg:photos_sr":2,
    "qs_pg:pop_sr":0,
    "qs_pg:qs_pg_placetype":"locality",
    "qs_pg:qs_pg_placetype_gp":"Town",
    "qs_pg:woe_adm0":23424910,
    "woe:adm0_id":23424910,
    "woe:name_adm0":"Norge",
    "woe:name_adm1":"M\u00f8re og Romsdal Fylke",
    "woe:placetype":"Town",
    "wof:name":"Eidsv\u00e5g I Romsdal",
    "wof:placetype":"locality"
},
  "geometry": {"coordinates":[8.068084,62.781747],"type":"Point"}
}