{
  "type": "Feature",
  "properties": {
    "iso:country":"XX",
    "qs_pg:name":"\u010ca\u010dak",
    "qs_pg:name_adm0":"Serbia",
    "qs_pg:name_adm1":"Moravica",
    "qs_pg:photos":595,
    "qs_pg:photos_1k":121,
    "qs_pg:photos_9k":3,
    "qs_pg:photos_9r":5,
    "qs_pg:photos_all":595,
    "qs_pg:photos_sr":8,
    "qs_pg:pop_sr":0,
    "qs_pg:qs_pg_placetype":"locality",
    "qs_pg:qs_pg_placetype_gp":"Town",
    "qs_pg:woe_adm0":20069818,
    "woe:adm0_id":20069818,
    "woe:name_adm0":"Serbia",
    "woe:name_adm1":"Moravica",
    "woe:placetype":"Town",
    "wof:name":"\u010ca\u010dak",
    "wof:placetype":"locality"
},
  "geometry": {"coordinates":[20.344553,43.887825],"type":"Point"}
}