{
  "type": "Feature",
  "properties": {
    "iso:country":"XX",
    "qs_pg:name":"Adelberg Kloster",
    "qs_pg:name_adm0":"Deutschland",
    "qs_pg:name_adm1":"Baden-W\u00fcrttemberg",
    "qs_pg:photos":32,
    "qs_pg:photos_1k":6,
    "qs_pg:photos_9k":1,
    "qs_pg:photos_9r":2,
    "qs_pg:photos_all":32,
    "qs_pg:photos_sr":2,
    "qs_pg:pop_sr":0,
    "qs_pg:qs_pg_placetype":"locality",
    "qs_pg:qs_pg_placetype_gp":"Town",
    "qs_pg:woe_adm0":23424829,
    "woe:adm0_id":23424829,
    "woe:name_adm0":"Deutschland",
    "woe:name_adm1":"Baden-W\u00fcrttemberg",
    "woe:placetype":"Town",
    "wof:name":"Adelberg Kloster",
    "wof:placetype":"locality"
},
  "geometry": {"coordinates":[9.592866,48.758713],"type":"Point"}
}