{
  "type": "Feature",
  "properties": {
    "gn:country":"XX",
    "iso:country":"XX",
    "qs_pg:aaroncc":"XX",
    "qs_pg:gn_country":"XX",
    "qs_pg:name":"Kiagar La",
    "qs_pg:name_adm0":"India",
    "qs_pg:name_adm1":"Jammu and Kashmir",
    "qs_pg:photos":26,
    "qs_pg:photos_1k":5,
    "qs_pg:photos_9k":1,
    "qs_pg:photos_9r":2,
    "qs_pg:photos_all":26,
    "qs_pg:photos_sr":2,
    "qs_pg:pop_sr":0,
    "qs_pg:qs_pg_placetype":"locality",
    "qs_pg:qs_pg_placetype_gp":"Town",
    "qs_pg:woe_adm0":23424848,
    "woe:adm0_id":23424848,
    "woe:name_adm0":"India",
    "woe:name_adm1":"Jammu and Kashmir",
    "woe:placetype":"Town",
    "wof:name":"Kiagar La",
    "wof:placetype":"locality"
},
  "geometry": {"coordinates":[78.33609,33.126999],"type":"Point"}
}