{
  "type": "Feature",
  "properties": {
    "iso:country":"XX",
    "qs_pg:name":"Vestamager",
    "qs_pg:name_adm0":"Danmark",
    "qs_pg:name_adm1":"Hovedstaden",
    "qs_pg:photos":5681,
    "qs_pg:photos_1k":1000,
    "qs_pg:photos_9k":25,
    "qs_pg:photos_9r":14,
    "qs_pg:photos_all":5681,
    "qs_pg:photos_sr":24,
    "qs_pg:pop_sr":0,
    "qs_pg:qs_pg_placetype":"neighbourhood",
    "qs_pg:qs_pg_placetype_gp":"Suburb",
    "qs_pg:woe_adm0":23424796,
    "woe:adm0_id":23424796,
    "woe:name_adm0":"Danmark",
    "woe:name_adm1":"Hovedstaden",
    "woe:placetype":"Suburb",
    "wof:name":"Vestamager",
    "wof:placetype":"neighbourhood"
},
  "geometry": {"coordinates":[12.562533,55.641779],"type":"Point"}
}