{
  "type": "Feature",
  "properties": {
    "iso:country":"XX",
    "qs_pg:name":"Umchung",
    "qs_pg:name_adm0":"India",
    "qs_pg:name_adm1":"Sikkim",
    "qs_pg:photos":38,
    "qs_pg:photos_1k":8,
    "qs_pg:photos_9k":1,
    "qs_pg:photos_9r":2,
    "qs_pg:photos_all":38,
    "qs_pg:photos_sr":2,
    "qs_pg:pop_sr":0,
    "qs_pg:qs_pg_placetype":"neighbourhood",
    "qs_pg:qs_pg_placetype_gp":"Suburb",
    "qs_pg:woe_adm0":23424848,
    "woe:adm0_id":23424848,
    "woe:name_adm0":"India",
    "woe:name_adm1":"Sikkim",
    "woe:placetype":"Suburb",
    "wof:name":"Umchung",
    "wof:placetype":"neighbourhood"
},
  "geometry": {"coordinates":[88.29578600000001,27.2945945],"type":"Point"}
}