{
  "type": "Feature",
  "properties": {
    "iso:country":"XX",
    "qs_pg:name":"Bullenbaai",
    "qs_pg:name_adm0":"Cura\u00e7ao",
    "qs_pg:photos":217,
    "qs_pg:photos_1k":44,
    "qs_pg:photos_9k":1,
    "qs_pg:photos_9r":4,
    "qs_pg:photos_all":217,
    "qs_pg:photos_sr":4,
    "qs_pg:pop_sr":0,
    "qs_pg:qs_pg_placetype":"locality",
    "qs_pg:qs_pg_placetype_gp":"Town",
    "qs_pg:woe_adm0":56558057,
    "woe:adm0_id":56558057,
    "woe:name_adm0":"Cura\u00e7ao",
    "woe:placetype":"Town",
    "wof:name":"Bullenbaai",
    "wof:placetype":"locality"
},
  "geometry": {"coordinates":[-69.00032,12.152535],"type":"Point"}
}