{
  "type": "Feature",
  "properties": {
    "gn:country":"XX",
    "iso:country":"XX",
    "qs:name":"Shinkhun La",
    "qs:name_adm0":"India",
    "qs:name_adm1":"Himachal Pradesh",
    "qs:photos":63,
    "qs:photos_1k":13,
    "qs:photos_9k":1,
    "qs:photos_9r":2,
    "qs:photos_all":63,
    "qs:photos_sr":2,
    "qs:placetype":"Town",
    "qs:pop_sr":"0",
    "wof:name":"Shinkhun La",
    "wof:placetype":"locality"
},
  "geometry": {"coordinates":[77.20092699999999,32.908811],"type":"Point"}
}