{
  "type": "Feature",
  "properties": {
    "iso:country":"XX",
    "qs_pg:name":"Centro",
    "qs_pg:name_adm0":"Brasil",
    "qs_pg:name_adm1":"Santa Catarina",
    "qs_pg:photos":705,
    "qs_pg:photos_1k":143,
    "qs_pg:photos_9k":3,
    "qs_pg:photos_9r":5,
    "qs_pg:photos_all":705,
    "qs_pg:photos_sr":8,
    "qs_pg:pop_sr":0,
    "qs_pg:qs_pg_placetype":"neighbourhood",
    "qs_pg:qs_pg_placetype_gp":"Suburb",
    "qs_pg:woe_adm0":23424768,
    "woe:adm0_id":23424768,
    "woe:name_adm0":"Brasil",
    "woe:name_adm1":"Santa Catarina",
    "woe:placetype":"Suburb",
    "wof:name":"Centro",
    "wof:placetype":"neighbourhood"
},
  "geometry": {"coordinates":[-48.631496,-26.988744],"type":"Point"}
}