{
  "type": "Feature",
  "properties": {
    "iso:country":"XX",
    "qs_pg:name":"Barrio la Inalambrica",
    "qs_pg:name_adm0":"M\u00e9xico",
    "qs_pg:name_adm1":"Baja California Sur",
    "qs_pg:photos":40,
    "qs_pg:photos_1k":8,
    "qs_pg:photos_9k":1,
    "qs_pg:photos_9r":2,
    "qs_pg:photos_all":40,
    "qs_pg:photos_sr":2,
    "qs_pg:pop_sr":0,
    "qs_pg:qs_pg_placetype":"neighbourhood",
    "qs_pg:qs_pg_placetype_gp":"Suburb",
    "qs_pg:woe_adm0":23424900,
    "woe:adm0_id":23424900,
    "woe:name_adm0":"M\u00e9xico",
    "woe:name_adm1":"Baja California Sur",
    "woe:placetype":"Suburb",
    "wof:name":"Barrio la Inalambrica",
    "wof:placetype":"neighbourhood"
},
  "geometry": {"coordinates":[-110.32753449999998,24.153406],"type":"Point"}
}