{
  "type": "Feature",
  "properties": {
    "iso:country":"XX",
    "qs_pg:name":"Fuglafj\u00f8r\u00ffur",
    "qs_pg:name_adm0":"F\u00e6r\u00f8erne",
    "qs_pg:name_adm1":"Sy\u00f0ra Eysturoy",
    "qs_pg:photos":100,
    "qs_pg:photos_1k":20,
    "qs_pg:photos_9k":1,
    "qs_pg:photos_9r":3,
    "qs_pg:photos_all":100,
    "qs_pg:photos_sr":3,
    "qs_pg:pop_sr":0,
    "qs_pg:qs_pg_placetype":"locality",
    "qs_pg:qs_pg_placetype_gp":"Town",
    "qs_pg:woe_adm0":23424816,
    "woe:adm0_id":23424816,
    "woe:name_adm0":"F\u00e6r\u00f8erne",
    "woe:name_adm1":"Sy\u00f0ra Eysturoy",
    "woe:placetype":"Town",
    "wof:name":"Fuglafj\u00f8r\u00ffur",
    "wof:placetype":"locality"
},
  "geometry": {"coordinates":[-6.810198,62.244548],"type":"Point"}
}