{
  "type": "Feature",
  "properties": {
    "iso:country":"XX",
    "qs_pg:name":"Farooq-i-Azam Lines",
    "qs_pg:name_adm0":"Pakistan",
    "qs_pg:name_adm1":"Sindh",
    "qs_pg:photos":54,
    "qs_pg:photos_1k":11,
    "qs_pg:photos_9k":1,
    "qs_pg:photos_9r":2,
    "qs_pg:photos_all":54,
    "qs_pg:photos_sr":2,
    "qs_pg:pop_sr":0,
    "qs_pg:qs_pg_placetype":"neighbourhood",
    "qs_pg:qs_pg_placetype_gp":"Suburb",
    "qs_pg:woe_adm0":23424922,
    "woe:adm0_id":23424922,
    "woe:name_adm0":"Pakistan",
    "woe:name_adm1":"Sindh",
    "woe:placetype":"Suburb",
    "wof:name":"Farooq-i-Azam Lines",
    "wof:placetype":"neighbourhood"
},
  "geometry": {"coordinates":[67.03224299999999,24.852046],"type":"Point"}
}