{
  "type": "Feature",
  "properties": {
    "iso:country":"XX",
    "name:eng_x_preferred":[
        "Yeongheung-Myeon"
    ],
    "name:eng_x_variant":[
        "Yeongheung",
        "Yeongheungmyeon",
        "Yeongheung-Myeon"
    ],
    "name:kor_x_preferred":[
        "\uc601\ud765\uba74"
    ],
    "qs:gn_adm0_cc":"KR",
    "qs:gn_local":1843564,
    "qs:local_max":2394,
    "qs:local_sum":10431,
    "qs:localhoods":47,
    "qs:name":"\uc601\ud765\uba74",
    "qs:name_adm0":"\ud55c\uad6d",
    "qs:name_adm1":"\uc778\ucc9c",
    "qs:name_adm2":"\uc639\uc9c4\uad70",
    "qs:name_en":"Yeongheung-Myeon",
    "qs:name_lau":"\uc601\ud765\uba74",
    "qs:name_local":"\uc778\ucc9c",
    "qs:photo_max":17,
    "qs:photo_sum":77,
    "qs:placetype":"Suburb",
    "qs:quad_count":20,
    "qs:woe_adm0":23424868,
    "qs:woe_adm1":20069922,
    "qs:woe_adm2":28289263,
    "qs:woe_lau":28806435,
    "qs:woe_local":1132496,
    "qs:woe_ver":"7.10.0",
    "wof:lang":[
        "kor"
    ],
    "wof:name":"\uc601\ud765\uba74",
    "wof:placetype":"neighbourhood"
},
  "geometry": {"coordinates":[126.48263799999999,37.255216],"type":"Point"}
}