{
  "type": "Feature",
  "properties": {
    "iso:country":"XX",
    "name:cat_x_preferred":[
        "Yal\u0131k\u00f6y"
    ],
    "name:ceb_x_preferred":[
        "Yal\u0131k\u00f6y"
    ],
    "name:ces_x_preferred":[
        "Yal\u0131k\u00f6y"
    ],
    "name:dan_x_preferred":[
        "Yal\u0131k\u00f6y"
    ],
    "name:deu_x_preferred":[
        "Yal\u0131k\u00f6y"
    ],
    "name:eng_x_preferred":[
        "Yal\u0131k\u00f6y"
    ],
    "name:eus_x_preferred":[
        "Yal\u0131k\u00f6y"
    ],
    "name:fin_x_preferred":[
        "Yal\u0131k\u00f6y"
    ],
    "name:glg_x_preferred":[
        "Yal\u0131k\u00f6y"
    ],
    "name:ita_x_preferred":[
        "Yal\u0131k\u00f6y"
    ],
    "name:nld_x_preferred":[
        "Yal\u0131k\u00f6y"
    ],
    "name:nno_x_preferred":[
        "Yal\u0131k\u00f6y"
    ],
    "name:nob_x_preferred":[
        "Yal\u0131k\u00f6y"
    ],
    "name:oci_x_preferred":[
        "Yal\u0131k\u00f6y"
    ],
    "name:pol_x_preferred":[
        "Yal\u0131k\u00f6y"
    ],
    "name:por_x_preferred":[
        "Yal\u0131k\u00f6y"
    ],
    "name:ron_x_preferred":[
        "Yal\u0131k\u00f6y"
    ],
    "name:sco_x_preferred":[
        "Yal\u0131k\u00f6y"
    ],
    "name:slk_x_preferred":[
        "Yal\u0131k\u00f6y"
    ],
    "name:slv_x_preferred":[
        "Yal\u0131k\u00f6y"
    ],
    "name:spa_x_preferred":[
        "Yal\u0131k\u00f6y"
    ],
    "name:swe_x_preferred":[
        "Yal\u0131k\u00f6y"
    ],
    "name:tgl_x_preferred":[
        "Yal\u0131k\u00f6y"
    ],
    "name:tur_x_preferred":[
        "Yal\u0131k\u00f6y"
    ],
    "name:war_x_preferred":[
        "Yal\u0131k\u00f6y"
    ],
    "qs_pg:name":"Yalik\u00f6y",
    "qs_pg:name_adm0":"Turkey",
    "qs_pg:name_adm1":"\u0130stanbul",
    "qs_pg:photos":259,
    "qs_pg:photos_1k":52,
    "qs_pg:photos_9k":1,
    "qs_pg:photos_9r":4,
    "qs_pg:photos_all":259,
    "qs_pg:photos_sr":5,
    "qs_pg:pop_sr":0,
    "qs_pg:qs_pg_placetype":"neighbourhood",
    "qs_pg:qs_pg_placetype_gp":"Suburb",
    "qs_pg:woe_adm0":23424969,
    "woe:adm0_id":23424969,
    "woe:name_adm0":"Turkey",
    "woe:name_adm1":"\u0130stanbul",
    "woe:placetype":"Suburb",
    "wof:name":"Yalik\u00f6y",
    "wof:placetype":"neighbourhood"
},
  "geometry": {"coordinates":[29.075832,41.131995],"type":"Point"}
}