{
  "type": "Feature",
  "properties": {
    "iso:country":"XX",
    "name:ces_x_preferred":[
        "Ha-Rakevet"
    ],
    "name:eng_x_preferred":[
        "HaRakevet"
    ],
    "qs_pg:name":"Ha-rakevet",
    "qs_pg:name_adm0":"Israel",
    "qs_pg:name_adm1":"Tel Aviv",
    "qs_pg:photos":1152,
    "qs_pg:photos_1k":233,
    "qs_pg:photos_9k":5,
    "qs_pg:photos_9r":7,
    "qs_pg:photos_all":1152,
    "qs_pg:photos_sr":11,
    "qs_pg:pop_sr":0,
    "qs_pg:qs_pg_placetype":"neighbourhood",
    "qs_pg:qs_pg_placetype_gp":"Suburb",
    "qs_pg:woe_adm0":23424852,
    "woe:adm0_id":23424852,
    "woe:name_adm0":"Israel",
    "woe:name_adm1":"Tel Aviv",
    "woe:placetype":"Suburb",
    "wof:name":"Ha-rakevet",
    "wof:placetype":"neighbourhood"
},
  "geometry": {"coordinates":[34.782,32.065846],"type":"Point"}
}