{
  "type": "Feature",
  "properties": {
    "iso:country":"XX",
    "qs_pg:name":"\uff12\u4e01\u76ee",
    "qs_pg:name_adm0":"\u65e5\u672c",
    "qs_pg:name_adm1":"\u611b\u77e5\u770c",
    "qs_pg:photos":46,
    "qs_pg:photos_1k":9,
    "qs_pg:photos_9k":1,
    "qs_pg:photos_9r":2,
    "qs_pg:photos_all":46,
    "qs_pg:photos_sr":2,
    "qs_pg:pop_sr":0,
    "qs_pg:qs_pg_placetype":"neighbourhood",
    "qs_pg:qs_pg_placetype_gp":"Suburb",
    "qs_pg:woe_adm0":23424856,
    "woe:adm0_id":23424856,
    "woe:name_adm0":"\u65e5\u672c",
    "woe:name_adm1":"\u611b\u77e5\u770c",
    "woe:placetype":"Suburb",
    "wof:name":"\uff12\u4e01\u76ee",
    "wof:placetype":"neighbourhood"
},
  "geometry": {"coordinates":[136.91392099999999,35.151705],"type":"Point"}
}