{
  "type": "Feature",
  "properties": {
    "iso:country":"XX",
    "wof:name":"Cibali",
    "wof:placetype":"neighbourhood"
},
  "geometry": {"coordinates":[28.95929596091472,41.022657669273],"type":"Point"}
}