{
  "type": "Feature",
  "properties": {
    "iso:country":"XX",
    "qs_pg:name":"Harmon",
    "qs_pg:name_adm0":"Guam",
    "qs_pg:name_adm1":"Tamuning",
    "qs_pg:photos":634,
    "qs_pg:photos_1k":128,
    "qs_pg:photos_9k":3,
    "qs_pg:photos_9r":5,
    "qs_pg:photos_all":634,
    "qs_pg:photos_sr":8,
    "qs_pg:pop_sr":0,
    "qs_pg:qs_pg_placetype":"locality",
    "qs_pg:qs_pg_placetype_gp":"Town",
    "qs_pg:woe_adm0":23424832,
    "woe:adm0_id":23424832,
    "woe:name_adm0":"Guam",
    "woe:name_adm1":"Tamuning",
    "woe:placetype":"Town",
    "wof:name":"Harmon",
    "wof:placetype":"locality"
},
  "geometry": {"coordinates":[144.8072525,13.5349285],"type":"Point"}
}