{
  "type": "Feature",
  "properties": {
    "iso:country":"XX",
    "name:bos_x_preferred":[
        "Ivan\u010dna Gorica"
    ],
    "name:ceb_x_preferred":[
        "Ivan\u010dna Gorica"
    ],
    "name:eng_x_preferred":[
        "Ivan\u010dna Gorica"
    ],
    "name:fra_x_preferred":[
        "Ivan\u010dna Gorica"
    ],
    "name:nld_x_preferred":[
        "Ivan\u010dna Gorica"
    ],
    "name:pol_x_preferred":[
        "Ivan\u010dna Gorica"
    ],
    "name:ron_x_preferred":[
        "Ivan\u010dna Gorica"
    ],
    "name:slv_x_preferred":[
        "Ivan\u010dna Gorica"
    ],
    "name:srp_x_preferred":[
        "\u0418\u0432\u0430\u043d\u0447\u043d\u0430 \u0413\u043e\u0440\u0438\u0446\u0430"
    ],
    "name:ukr_x_preferred":[
        "\u0406\u0432\u0430\u043d\u0447\u043d\u0430 \u0413\u043e\u0440\u0438\u0446\u044f"
    ],
    "qs_pg:name":"Ivan\u010dna Gorica",
    "qs_pg:name_adm0":"Slovenija",
    "qs_pg:name_adm1":"Grosuplje",
    "qs_pg:photos":435,
    "qs_pg:photos_1k":88,
    "qs_pg:photos_9k":2,
    "qs_pg:photos_9r":5,
    "qs_pg:photos_all":435,
    "qs_pg:photos_sr":6,
    "qs_pg:pop_sr":0,
    "qs_pg:qs_pg_placetype":"locality",
    "qs_pg:qs_pg_placetype_gp":"Town",
    "qs_pg:woe_adm0":23424945,
    "woe:adm0_id":23424945,
    "woe:name_adm0":"Slovenija",
    "woe:name_adm1":"Grosuplje",
    "woe:placetype":"Town",
    "wof:name":"Ivan\u010dna Gorica",
    "wof:placetype":"locality"
},
  "geometry": {"coordinates":[14.800879,45.938303],"type":"Point"}
}