{
  "type": "Feature",
  "properties": {
    "iso:country":"XX",
    "qs_pg:name":"Invercargill Central",
    "qs_pg:name_adm0":"New Zealand",
    "qs_pg:name_adm1":"Southland",
    "qs_pg:photos":817,
    "qs_pg:photos_1k":166,
    "qs_pg:photos_9k":4,
    "qs_pg:photos_9r":6,
    "qs_pg:photos_all":817,
    "qs_pg:photos_sr":9,
    "qs_pg:pop_sr":0,
    "qs_pg:qs_pg_placetype":"neighbourhood",
    "qs_pg:qs_pg_placetype_gp":"Suburb",
    "qs_pg:woe_adm0":23424916,
    "woe:adm0_id":23424916,
    "woe:name_adm0":"New Zealand",
    "woe:name_adm1":"Southland",
    "woe:placetype":"Suburb",
    "wof:name":"Invercargill Central",
    "wof:placetype":"neighbourhood"
},
  "geometry": {"coordinates":[168.34818300000001,-46.410707],"type":"Point"}
}