{
  "type": "Feature",
  "properties": {
    "iso:country":"XX",
    "name:eng_x_preferred":[
        "Foxup"
    ],
    "name:fra_x_preferred":[
        "Foxup"
    ],
    "name:nld_x_preferred":[
        "Foxup"
    ],
    "name:pol_x_preferred":[
        "Foxup"
    ],
    "qs_pg:name":"Foxup",
    "qs_pg:name_adm0":"United Kingdom",
    "qs_pg:name_adm1":"England",
    "qs_pg:photos":564,
    "qs_pg:photos_1k":114,
    "qs_pg:photos_9k":2,
    "qs_pg:photos_9r":5,
    "qs_pg:photos_all":564,
    "qs_pg:photos_sr":8,
    "qs_pg:pop_sr":0,
    "qs_pg:qs_pg_placetype":"locality",
    "qs_pg:qs_pg_placetype_gp":"Town",
    "qs_pg:woe_adm0":23424975,
    "woe:adm0_id":23424975,
    "woe:name_adm0":"United Kingdom",
    "woe:name_adm1":"England",
    "woe:placetype":"Town",
    "wof:name":"Foxup",
    "wof:placetype":"locality"
},
  "geometry": {"coordinates":[-2.249622,54.160825],"type":"Point"}
}