{
  "type": "Feature",
  "properties": {
    "iso:country":"XX",
    "qs_pg:name":"Charleston Place",
    "qs_pg:name_adm0":"United States",
    "qs_pg:name_adm1":"Florida",
    "qs_pg:photos":12,
    "qs_pg:photos_1k":2,
    "qs_pg:photos_9k":1,
    "qs_pg:photos_9r":1,
    "qs_pg:photos_all":12,
    "qs_pg:photos_sr":1,
    "qs_pg:pop_sr":0,
    "qs_pg:qs_pg_placetype":"neighbourhood",
    "qs_pg:qs_pg_placetype_gp":"Suburb",
    "qs_pg:woe_adm0":23424977,
    "woe:adm0_id":23424977,
    "woe:name_adm0":"United States",
    "woe:name_adm1":"Florida",
    "woe:placetype":"Suburb",
    "wof:name":"Charleston Place",
    "wof:placetype":"neighbourhood"
},
  "geometry": {"coordinates":[-80.27894000000001,27.25679],"type":"Point"}
}