{
  "type": "Feature",
  "properties": {
    "iso:country":"XX",
    "qs_pg:name":"Kale",
    "qs_pg:name_adm0":"Turkey",
    "qs_pg:name_adm1":"Ankara",
    "qs_pg:photos":652,
    "qs_pg:photos_1k":132,
    "qs_pg:photos_9k":3,
    "qs_pg:photos_9r":5,
    "qs_pg:photos_all":652,
    "qs_pg:photos_sr":8,
    "qs_pg:pop_sr":0,
    "qs_pg:qs_pg_placetype":"neighbourhood",
    "qs_pg:qs_pg_placetype_gp":"Suburb",
    "qs_pg:woe_adm0":23424969,
    "woe:adm0_id":23424969,
    "woe:name_adm0":"Turkey",
    "woe:name_adm1":"Ankara",
    "woe:placetype":"Suburb",
    "wof:name":"Kale",
    "wof:placetype":"neighbourhood"
},
  "geometry": {"coordinates":[32.865235,39.939142],"type":"Point"}
}