{
  "type": "Feature",
  "properties": {
    "iso:country":"XX",
    "qs_pg:name":"Peninsula de Las Playas",
    "qs_pg:name_adm0":"M\u00e9xico",
    "qs_pg:name_adm1":"Guerrero",
    "qs_pg:photos":114,
    "qs_pg:photos_1k":23,
    "qs_pg:photos_9k":1,
    "qs_pg:photos_9r":3,
    "qs_pg:photos_all":114,
    "qs_pg:photos_sr":3,
    "qs_pg:pop_sr":0,
    "qs_pg:qs_pg_placetype":"neighbourhood",
    "qs_pg:qs_pg_placetype_gp":"Suburb",
    "qs_pg:woe_adm0":23424900,
    "woe:adm0_id":23424900,
    "woe:name_adm0":"M\u00e9xico",
    "woe:name_adm1":"Guerrero",
    "woe:placetype":"Suburb",
    "wof:name":"Peninsula de Las Playas",
    "wof:placetype":"neighbourhood"
},
  "geometry": {"coordinates":[-99.90135749999999,16.830631],"type":"Point"}
}