{
  "type": "Feature",
  "properties": {
    "iso:country":"XX",
    "name:afr_x_preferred":[
        "Chris Hani"
    ],
    "name:cat_x_preferred":[
        "Chris Hani"
    ],
    "name:dan_x_preferred":[
        "Chris Hani"
    ],
    "name:deu_x_preferred":[
        "Chris Hani"
    ],
    "name:eus_x_preferred":[
        "Chris Hani"
    ],
    "name:fas_x_preferred":[
        "\u06a9\u0631\u06cc\u0633 \u0647\u0627\u0646\u06cc"
    ],
    "name:fin_x_preferred":[
        "Chris Hani"
    ],
    "name:fra_x_preferred":[
        "Chris Hani"
    ],
    "name:heb_x_preferred":[
        "\u05db\u05e8\u05d9\u05e1 \u05d4\u05d0\u05e0\u05d9"
    ],
    "name:ind_x_preferred":[
        "Chris Hani"
    ],
    "name:ita_x_preferred":[
        "Chris Hani"
    ],
    "name:mal_x_preferred":[
        "\u0d15\u0d4d\u0d30\u0d3f\u0d38\u0d4d \u0d39\u0d3e\u0d28\u0d3f"
    ],
    "name:nld_x_preferred":[
        "Chris Hani"
    ],
    "name:nno_x_preferred":[
        "Chris Hani"
    ],
    "name:nor_x_preferred":[
        "Chris Hani"
    ],
    "name:pol_x_preferred":[
        "Chris Hani"
    ],
    "name:rus_x_preferred":[
        "\u0425\u0430\u043d\u0438"
    ],
    "name:spa_x_preferred":[
        "Chris Hani"
    ],
    "name:swe_x_preferred":[
        "Chris Hani"
    ],
    "name:tam_x_preferred":[
        "\u0b95\u0bbf\u0bb0\u0bbf\u0b9a\u0bc1 \u0bb9\u0bbe\u0ba9\u0bbf"
    ],
    "name:zul_x_preferred":[
        "Chris Hani"
    ],
    "qs_pg:name":"Chris Hani",
    "qs_pg:name_adm0":"South Africa",
    "qs_pg:name_adm1":"Western Cape",
    "qs_pg:photos":80,
    "qs_pg:photos_1k":16,
    "qs_pg:photos_9k":1,
    "qs_pg:photos_9r":3,
    "qs_pg:photos_all":80,
    "qs_pg:photos_sr":3,
    "qs_pg:pop_sr":0,
    "qs_pg:qs_pg_placetype":"neighbourhood",
    "qs_pg:qs_pg_placetype_gp":"Suburb",
    "qs_pg:woe_adm0":23424942,
    "woe:adm0_id":23424942,
    "woe:name_adm0":"South Africa",
    "woe:name_adm1":"Western Cape",
    "woe:placetype":"Suburb",
    "wof:name":"Chris Hani",
    "wof:placetype":"neighbourhood"
},
  "geometry": {"coordinates":[19.139139,-33.285],"type":"Point"}
}