{
  "type": "Feature",
  "properties": {
    "iso:country":"XX",
    "qs_pg:name":"Buhara",
    "qs_pg:name_adm0":"Turkey",
    "qs_pg:name_adm1":"Konya",
    "qs_pg:photos":25,
    "qs_pg:photos_1k":5,
    "qs_pg:photos_9k":1,
    "qs_pg:photos_9r":1,
    "qs_pg:photos_all":25,
    "qs_pg:photos_sr":1,
    "qs_pg:pop_sr":0,
    "qs_pg:qs_pg_placetype":"neighbourhood",
    "qs_pg:qs_pg_placetype_gp":"Suburb",
    "qs_pg:woe_adm0":23424969,
    "woe:adm0_id":23424969,
    "woe:name_adm0":"Turkey",
    "woe:name_adm1":"Konya",
    "woe:placetype":"Suburb",
    "wof:name":"Buhara",
    "wof:placetype":"neighbourhood"
},
  "geometry": {"coordinates":[32.491035,37.928153],"type":"Point"}
}