{
  "type": "Feature",
  "properties": {
    "iso:country":"XX",
    "name:ara_x_preferred":[
        "\u062f\u0627\u0648\u0646 \u062a\u0627\u0648\u0646"
    ],
    "name:ast_x_preferred":[
        "Distritu financieru"
    ],
    "name:ben_x_preferred":[
        "\u09b6\u09b9\u09b0\u09c7\u09b0 \u0995\u09c7\u09a8\u09cd\u09a6\u09cd\u09b0\u09b8\u09cd\u09a5\u09b2"
    ],
    "name:ces_x_preferred":[
        "Downtown"
    ],
    "name:deu_x_preferred":[
        "Downtown"
    ],
    "name:fas_x_preferred":[
        "\u0647\u0633\u062a\u0647 \u0634\u0647\u0631"
    ],
    "name:jpn_x_preferred":[
        "\u7e41\u83ef\u8857"
    ],
    "name:kor_x_preferred":[
        "\ubc88\ud654\uac00"
    ],
    "name:nld_x_preferred":[
        "Downtown"
    ],
    "name:rus_x_preferred":[
        "\u0414\u0430\u0443\u043d\u0442\u0430\u0443\u043d"
    ],
    "name:sco_x_preferred":[
        "Downtown"
    ],
    "name:spa_x_preferred":[
        "Downtown"
    ],
    "name:swe_x_preferred":[
        "Downtown"
    ],
    "name:ukr_x_preferred":[
        "\u0414\u0430\u0443\u043d\u0442\u0430\u0443\u043d"
    ],
    "name:wuu_x_preferred":[
        "\u4e0b\u57ce"
    ],
    "name:zho_x_preferred":[
        "\u4e0b\u57ce"
    ],
    "qs_pg:name":"Downtown",
    "qs_pg:name_adm0":"United States",
    "qs_pg:name_adm1":"California",
    "qs_pg:photos":639,
    "qs_pg:photos_1k":129,
    "qs_pg:photos_9k":3,
    "qs_pg:photos_9r":5,
    "qs_pg:photos_all":639,
    "qs_pg:photos_sr":8,
    "qs_pg:pop_sr":0,
    "qs_pg:qs_pg_placetype":"neighbourhood",
    "qs_pg:qs_pg_placetype_gp":"Suburb",
    "qs_pg:woe_adm0":23424977,
    "woe:adm0_id":23424977,
    "woe:name_adm0":"United States",
    "woe:name_adm1":"California",
    "woe:placetype":"Suburb",
    "wof:name":"Downtown",
    "wof:placetype":"neighbourhood"
},
  "geometry": {"coordinates":[-118.03016599999999,34.078833],"type":"Point"}
}