{
  "type": "Feature",
  "properties": {
    "iso:country":"XX",
    "qs_pg:name":"Downtown",
    "qs_pg:name_adm0":"United States",
    "qs_pg:name_adm1":"California",
    "qs_pg:photos":639,
    "qs_pg:photos_1k":129,
    "qs_pg:photos_9k":3,
    "qs_pg:photos_9r":5,
    "qs_pg:photos_all":639,
    "qs_pg:photos_sr":8,
    "qs_pg:pop_sr":0,
    "qs_pg:qs_pg_placetype":"neighbourhood",
    "qs_pg:qs_pg_placetype_gp":"Suburb",
    "qs_pg:woe_adm0":23424977,
    "woe:adm0_id":23424977,
    "woe:name_adm0":"United States",
    "woe:name_adm1":"California",
    "woe:placetype":"Suburb",
    "wof:name":"Downtown",
    "wof:placetype":"neighbourhood"
},
  "geometry": {"coordinates":[-118.03016599999999,34.078833],"type":"Point"}
}