{
  "type": "Feature",
  "properties": {
    "iso:country":"XX",
    "qs_pg:name":"Andersen Airforce Base",
    "qs_pg:name_adm0":"Guam",
    "qs_pg:name_adm1":"Yigo",
    "qs_pg:photos":155,
    "qs_pg:photos_1k":31,
    "qs_pg:photos_9k":1,
    "qs_pg:photos_9r":4,
    "qs_pg:photos_all":155,
    "qs_pg:photos_sr":4,
    "qs_pg:pop_sr":0,
    "qs_pg:qs_pg_placetype":"locality",
    "qs_pg:qs_pg_placetype_gp":"Town",
    "qs_pg:woe_adm0":23424832,
    "woe:adm0_id":23424832,
    "woe:name_adm0":"Guam",
    "woe:name_adm1":"Yigo",
    "woe:placetype":"Town",
    "wof:name":"Andersen Airforce Base",
    "wof:placetype":"locality"
},
  "geometry": {"coordinates":[144.91996700000001,13.562063],"type":"Point"}
}