{
  "type": "Feature",
  "properties": {
    "iso:country":"XX",
    "qs_pg:name":"Santo Agostinho",
    "qs_pg:name_adm0":"Brasil",
    "qs_pg:name_adm1":"Amazonas",
    "qs_pg:photos":55,
    "qs_pg:photos_1k":11,
    "qs_pg:photos_9k":1,
    "qs_pg:photos_9r":2,
    "qs_pg:photos_all":55,
    "qs_pg:photos_sr":2,
    "qs_pg:pop_sr":0,
    "qs_pg:qs_pg_placetype":"neighbourhood",
    "qs_pg:qs_pg_placetype_gp":"Suburb",
    "qs_pg:woe_adm0":23424768,
    "woe:adm0_id":23424768,
    "woe:name_adm0":"Brasil",
    "woe:name_adm1":"Amazonas",
    "woe:placetype":"Suburb",
    "wof:name":"Santo Agostinho",
    "wof:placetype":"neighbourhood"
},
  "geometry": {"coordinates":[-60.083595,-3.110953],"type":"Point"}
}