{
  "type": "Feature",
  "properties": {
    "iso:country":"XX",
    "qs_pg:name":"Vintgar",
    "qs_pg:name_adm0":"Slovenija",
    "qs_pg:name_adm1":"Radovljica",
    "qs_pg:photos":427,
    "qs_pg:photos_1k":87,
    "qs_pg:photos_9k":2,
    "qs_pg:photos_9r":5,
    "qs_pg:photos_all":427,
    "qs_pg:photos_sr":6,
    "qs_pg:pop_sr":0,
    "qs_pg:qs_pg_placetype":"locality",
    "qs_pg:qs_pg_placetype_gp":"Town",
    "qs_pg:woe_adm0":23424945,
    "woe:adm0_id":23424945,
    "woe:name_adm0":"Slovenija",
    "woe:name_adm1":"Radovljica",
    "woe:placetype":"Town",
    "wof:name":"Vintgar",
    "wof:placetype":"locality"
},
  "geometry": {"coordinates":[14.083786,46.389835],"type":"Point"}
}