{
  "type": "Feature",
  "properties": {
    "iso:country":"XX",
    "qs_pg:name":"Jaffa Center",
    "qs_pg:name_adm0":"Israel",
    "qs_pg:name_adm1":"Tel Aviv",
    "qs_pg:photos":1180,
    "qs_pg:photos_1k":239,
    "qs_pg:photos_9k":5,
    "qs_pg:photos_9r":7,
    "qs_pg:photos_all":1180,
    "qs_pg:photos_sr":11,
    "qs_pg:pop_sr":0,
    "qs_pg:qs_pg_placetype":"neighbourhood",
    "qs_pg:qs_pg_placetype_gp":"Suburb",
    "qs_pg:woe_adm0":23424852,
    "woe:adm0_id":23424852,
    "woe:name_adm0":"Israel",
    "woe:name_adm1":"Tel Aviv",
    "woe:placetype":"Suburb",
    "wof:name":"Jaffa Center",
    "wof:placetype":"neighbourhood"
},
  "geometry": {"coordinates":[34.7583355,32.053335],"type":"Point"}
}