{
  "type": "Feature",
  "properties": {
    "iso:country":"XX",
    "qs_pg:name":"Zona Centro",
    "qs_pg:name_adm0":"M\u00e9xico",
    "qs_pg:name_adm1":"Chiapas",
    "qs_pg:photos":1934,
    "qs_pg:photos_1k":392,
    "qs_pg:photos_9k":9,
    "qs_pg:photos_9r":9,
    "qs_pg:photos_all":1934,
    "qs_pg:photos_sr":15,
    "qs_pg:pop_sr":0,
    "qs_pg:qs_pg_placetype":"neighbourhood",
    "qs_pg:qs_pg_placetype_gp":"Suburb",
    "qs_pg:woe_adm0":23424900,
    "woe:adm0_id":23424900,
    "woe:name_adm0":"M\u00e9xico",
    "woe:name_adm1":"Chiapas",
    "woe:placetype":"Suburb",
    "wof:name":"Zona Centro",
    "wof:placetype":"neighbourhood"
},
  "geometry": {"coordinates":[-92.638351,16.736742],"type":"Point"}
}