{
  "type": "Feature",
  "properties": {
    "iso:country":"XX",
    "qs_pg:name":"Guadalupe Proletaria",
    "qs_pg:name_adm0":"M\u00e9xico",
    "qs_pg:name_adm1":"Distrito Federal",
    "qs_pg:photos":8,
    "qs_pg:photos_1k":2,
    "qs_pg:photos_9k":1,
    "qs_pg:photos_9r":1,
    "qs_pg:photos_all":8,
    "qs_pg:photos_sr":1,
    "qs_pg:pop_sr":0,
    "qs_pg:qs_pg_placetype":"neighbourhood",
    "qs_pg:qs_pg_placetype_gp":"Suburb",
    "qs_pg:woe_adm0":23424900,
    "woe:adm0_id":23424900,
    "woe:name_adm0":"M\u00e9xico",
    "woe:name_adm1":"Distrito Federal",
    "woe:placetype":"Suburb",
    "wof:name":"Guadalupe Proletaria",
    "wof:placetype":"neighbourhood"
},
  "geometry": {"coordinates":[-99.1599415,19.5216585],"type":"Point"}
}