{
  "type": "Feature",
  "properties": {
    "iso:country":"XX",
    "qs_pg:name":"S\u0103p\u00een\u021ba",
    "qs_pg:name_adm0":"Rom\u00e2nia",
    "qs_pg:name_adm1":"Maramures",
    "qs_pg:photos":658,
    "qs_pg:photos_1k":133,
    "qs_pg:photos_9k":3,
    "qs_pg:photos_9r":5,
    "qs_pg:photos_all":658,
    "qs_pg:photos_sr":8,
    "qs_pg:pop_sr":0,
    "qs_pg:qs_pg_placetype":"locality",
    "qs_pg:qs_pg_placetype_gp":"Town",
    "qs_pg:woe_adm0":23424933,
    "woe:adm0_id":23424933,
    "woe:name_adm0":"Rom\u00e2nia",
    "woe:name_adm1":"Maramures",
    "woe:placetype":"Town",
    "wof:name":"S\u0103p\u00een\u021ba",
    "wof:placetype":"locality"
},
  "geometry": {"coordinates":[23.698797,47.9713425],"type":"Point"}
}