{
  "type": "Feature",
  "properties": {
    "iso:country":"XX",
    "name:bos_x_preferred":[
        "Pivka"
    ],
    "name:dut_x_preferred":[
        "Pivka"
    ],
    "name:eng_x_preferred":[
        "Pivka"
    ],
    "name:hrv_x_preferred":[
        "Pivka"
    ],
    "name:rum_x_preferred":[
        "Pivka"
    ],
    "name:rus_x_preferred":[
        "\u041f\u0438\u0432\u043a\u0430"
    ],
    "name:slv_x_preferred":[
        "Pivka"
    ],
    "name:swe_x_preferred":[
        "Pivka"
    ],
    "name:ukr_x_preferred":[
        "\u041f\u0456\u0432\u043a\u0430"
    ],
    "name:vie_x_preferred":[
        "Pivka"
    ],
    "qs_pg:name":"Pivka",
    "qs_pg:name_adm0":"Slovenija",
    "qs_pg:name_adm1":"Postojna",
    "qs_pg:photos":46,
    "qs_pg:photos_1k":9,
    "qs_pg:photos_9k":1,
    "qs_pg:photos_9r":2,
    "qs_pg:photos_all":46,
    "qs_pg:photos_sr":2,
    "qs_pg:pop_sr":0,
    "qs_pg:qs_pg_placetype":"locality",
    "qs_pg:qs_pg_placetype_gp":"Town",
    "qs_pg:woe_adm0":23424945,
    "woe:adm0_id":23424945,
    "woe:name_adm0":"Slovenija",
    "woe:name_adm1":"Postojna",
    "woe:placetype":"Town",
    "wof:name":"Pivka",
    "wof:placetype":"locality"
},
  "geometry": {"coordinates":[14.197382,45.682522],"type":"Point"}
}