{
  "type": "Feature",
  "properties": {
    "iso:country":"XX",
    "qs_pg:name":"\uff12\u4e01\u76ee",
    "qs_pg:name_adm0":"\u65e5\u672c",
    "qs_pg:name_adm1":"\u6771\u4eac\u90fd",
    "qs_pg:photos":130,
    "qs_pg:photos_1k":26,
    "qs_pg:photos_9k":1,
    "qs_pg:photos_9r":3,
    "qs_pg:photos_all":130,
    "qs_pg:photos_sr":3,
    "qs_pg:pop_sr":0,
    "qs_pg:qs_pg_placetype":"neighbourhood",
    "qs_pg:qs_pg_placetype_gp":"Suburb",
    "qs_pg:woe_adm0":23424856,
    "woe:adm0_id":23424856,
    "woe:name_adm0":"\u65e5\u672c",
    "woe:name_adm1":"\u6771\u4eac\u90fd",
    "woe:placetype":"Suburb",
    "wof:name":"\uff12\u4e01\u76ee",
    "wof:placetype":"neighbourhood"
},
  "geometry": {"coordinates":[139.66799750000001,35.642523],"type":"Point"}
}