{
  "type": "Feature",
  "properties": {
    "iso:country":"XX",
    "qs_pg:name":"Great Carrot Bay",
    "qs_pg:name_adm0":"British Virgin Islands",
    "qs_pg:photos":2167,
    "qs_pg:photos_1k":439,
    "qs_pg:photos_9k":10,
    "qs_pg:photos_9r":9,
    "qs_pg:photos_all":2167,
    "qs_pg:photos_sr":16,
    "qs_pg:pop_sr":0,
    "qs_pg:qs_pg_placetype":"locality",
    "qs_pg:qs_pg_placetype_gp":"Town",
    "qs_pg:woe_adm0":23424983,
    "woe:adm0_id":23424983,
    "woe:name_adm0":"British Virgin Islands",
    "woe:placetype":"Town",
    "wof:name":"Great Carrot Bay",
    "wof:placetype":"locality"
},
  "geometry": {"coordinates":[-64.67393800000001,18.39004],"type":"Point"}
}