{
  "type": "Feature",
  "properties": {
    "iso:country":"XX",
    "qs_pg:name":"Highway 62 Highlands",
    "qs_pg:name_adm0":"United States",
    "qs_pg:name_adm1":"Arkansas",
    "qs_pg:photos":161,
    "qs_pg:photos_1k":33,
    "qs_pg:photos_9k":1,
    "qs_pg:photos_9r":4,
    "qs_pg:photos_all":161,
    "qs_pg:photos_sr":4,
    "qs_pg:pop_sr":0,
    "qs_pg:qs_pg_placetype":"neighbourhood",
    "qs_pg:qs_pg_placetype_gp":"Suburb",
    "qs_pg:woe_adm0":23424977,
    "woe:adm0_id":23424977,
    "woe:name_adm0":"United States",
    "woe:name_adm1":"Arkansas",
    "woe:placetype":"Suburb",
    "wof:name":"Highway 62 Highlands",
    "wof:placetype":"neighbourhood"
},
  "geometry": {"coordinates":[-94.027838,36.446493],"type":"Point"}
}