{
  "type": "Feature",
  "properties": {
    "iso:country":"XX",
    "qs_pg:name":"A\u015f \u015e\u0101lih\u0327\u012byah",
    "qs_pg:name_adm0":"Iraq",
    "qs_pg:name_adm1":"\u0628\u063a\u062f\u0627\u062f",
    "qs_pg:photos":528,
    "qs_pg:photos_1k":107,
    "qs_pg:photos_9k":2,
    "qs_pg:photos_9r":5,
    "qs_pg:photos_all":528,
    "qs_pg:photos_sr":7,
    "qs_pg:pop_sr":0,
    "qs_pg:qs_pg_placetype":"neighbourhood",
    "qs_pg:qs_pg_placetype_gp":"Suburb",
    "qs_pg:woe_adm0":23424855,
    "woe:adm0_id":23424855,
    "woe:name_adm0":"Iraq",
    "woe:name_adm1":"\u0628\u063a\u062f\u0627\u062f",
    "woe:placetype":"Suburb",
    "wof:name":"A\u015f \u015e\u0101lih\u0327\u012byah",
    "wof:placetype":"neighbourhood"
},
  "geometry": {"coordinates":[44.377223,33.314714],"type":"Point"}
}