{
  "type": "Feature",
  "properties": {
    "iso:country":"XX",
    "name:ces_x_preferred":[
        "Bavli"
    ],
    "name:heb_x_preferred":[
        "\u05e9\u05d9\u05db\u05d5\u05df \u05d1\u05d1\u05dc\u05d9"
    ],
    "name:pol_x_preferred":[
        "Bawli"
    ],
    "qs_pg:name":"Bavli",
    "qs_pg:name_adm0":"Israel",
    "qs_pg:name_adm1":"Tel Aviv",
    "qs_pg:photos":494,
    "qs_pg:photos_1k":100,
    "qs_pg:photos_9k":2,
    "qs_pg:photos_9r":5,
    "qs_pg:photos_all":494,
    "qs_pg:photos_sr":7,
    "qs_pg:pop_sr":0,
    "qs_pg:qs_pg_placetype":"neighbourhood",
    "qs_pg:qs_pg_placetype_gp":"Suburb",
    "qs_pg:woe_adm0":23424852,
    "woe:adm0_id":23424852,
    "woe:name_adm0":"Israel",
    "woe:name_adm1":"Tel Aviv",
    "woe:placetype":"Suburb",
    "wof:name":"Bavli",
    "wof:placetype":"neighbourhood"
},
  "geometry": {"coordinates":[34.797821,32.099517],"type":"Point"}
}