{
  "type": "Feature",
  "properties": {
    "iso:country":"XX",
    "name:ast_x_preferred":[
        "Nova Pazova"
    ],
    "name:ceb_x_preferred":[
        "Nova Pazova"
    ],
    "name:ces_x_preferred":[
        "Nova Pazova"
    ],
    "name:deu_x_preferred":[
        "Nova Pazova"
    ],
    "name:eng_x_preferred":[
        "Nova Pazova"
    ],
    "name:epo_x_preferred":[
        "Nova Pazova"
    ],
    "name:fas_x_preferred":[
        "\u0646\u0648\u0648\u0627 \u067e\u0627\u0632\u0648\u0648\u0627"
    ],
    "name:fra_x_preferred":[
        "Nova Pazova"
    ],
    "name:hrv_x_preferred":[
        "Nova Pazova"
    ],
    "name:hun_x_preferred":[
        "\u00dajpazova"
    ],
    "name:ita_x_preferred":[
        "Nova Pazova"
    ],
    "name:msa_x_preferred":[
        "Nova Pazova"
    ],
    "name:nld_x_preferred":[
        "Nova Pazova"
    ],
    "name:pol_x_preferred":[
        "Nova Pazova"
    ],
    "name:ron_x_preferred":[
        "Nova Pazova"
    ],
    "name:slv_x_preferred":[
        "Nova Pazova"
    ],
    "name:srp_x_preferred":[
        "\u041d\u043e\u0432\u0430 \u041f\u0430\u0437\u043e\u0432\u0430"
    ],
    "name:swe_x_preferred":[
        "Nova Pazova"
    ],
    "name:zho_x_preferred":[
        "\u65b0\u5e15\u4f50\u74e6"
    ],
    "qs_pg:name":"Nova Pazova",
    "qs_pg:name_adm0":"Serbia",
    "qs_pg:name_adm1":"Srem",
    "qs_pg:photos":280,
    "qs_pg:photos_1k":57,
    "qs_pg:photos_9k":1,
    "qs_pg:photos_9r":4,
    "qs_pg:photos_all":280,
    "qs_pg:photos_sr":5,
    "qs_pg:pop_sr":0,
    "qs_pg:qs_pg_placetype":"locality",
    "qs_pg:qs_pg_placetype_gp":"Town",
    "qs_pg:woe_adm0":20069818,
    "woe:adm0_id":20069818,
    "woe:name_adm0":"Serbia",
    "woe:name_adm1":"Srem",
    "woe:placetype":"Town",
    "wof:name":"Nova Pazova",
    "wof:placetype":"locality"
},
  "geometry": {"coordinates":[20.246558,44.932891],"type":"Point"}
}