{
  "type": "Feature",
  "properties": {
    "iso:country":"XX",
    "qs_pg:name":"Beiu\u0219",
    "qs_pg:name_adm0":"Rom\u00e2nia",
    "qs_pg:name_adm1":"Bihor",
    "qs_pg:photos":584,
    "qs_pg:photos_1k":118,
    "qs_pg:photos_9k":3,
    "qs_pg:photos_9r":5,
    "qs_pg:photos_all":584,
    "qs_pg:photos_sr":8,
    "qs_pg:pop_sr":0,
    "qs_pg:qs_pg_placetype":"locality",
    "qs_pg:qs_pg_placetype_gp":"Town",
    "qs_pg:woe_adm0":23424933,
    "woe:adm0_id":23424933,
    "woe:name_adm0":"Rom\u00e2nia",
    "woe:name_adm1":"Bihor",
    "woe:placetype":"Town",
    "wof:name":"Beiu\u0219",
    "wof:placetype":"locality"
},
  "geometry": {"coordinates":[22.359409,46.664811],"type":"Point"}
}