{
  "type": "Feature",
  "properties": {
    "iso:country":"XX",
    "qs_pg:name":"\u4e5d\u9f8d\u7063",
    "qs_pg:name_adm0":"\u9999\u6e2f",
    "qs_pg:name_adm1":"\u4e5d\u9f8d",
    "qs_pg:photos":5000,
    "qs_pg:photos_1k":1000,
    "qs_pg:photos_9k":22,
    "qs_pg:photos_9r":14,
    "qs_pg:photos_all":5000,
    "qs_pg:photos_sr":24,
    "qs_pg:pop_sr":0,
    "qs_pg:qs_pg_placetype":"locality",
    "qs_pg:qs_pg_placetype_gp":"Town",
    "qs_pg:woe_adm0":24865698,
    "woe:adm0_id":24865698,
    "woe:name_adm0":"\u9999\u6e2f",
    "woe:name_adm1":"\u4e5d\u9f8d",
    "woe:placetype":"Town",
    "wof:name":"\u4e5d\u9f8d\u7063",
    "wof:placetype":"locality"
},
  "geometry": {"coordinates":[114.20699999999999,22.32336],"type":"Point"}
}