{
  "type": "Feature",
  "properties": {
    "iso:country":"XX",
    "qs_pg:name":"Reston Town Center",
    "qs_pg:name_adm0":"United States",
    "qs_pg:name_adm1":"Virginia",
    "qs_pg:photos":3718,
    "qs_pg:photos_1k":753,
    "qs_pg:photos_9k":16,
    "qs_pg:photos_9r":12,
    "qs_pg:photos_all":3718,
    "qs_pg:photos_sr":21,
    "qs_pg:pop_sr":0,
    "qs_pg:qs_pg_placetype":"neighbourhood",
    "qs_pg:qs_pg_placetype_gp":"Suburb",
    "qs_pg:woe_adm0":23424977,
    "woe:adm0_id":23424977,
    "woe:name_adm0":"United States",
    "woe:name_adm1":"Virginia",
    "woe:placetype":"Suburb",
    "wof:name":"Reston Town Center",
    "wof:placetype":"neighbourhood"
},
  "geometry": {"coordinates":[-77.358591,38.958958],"type":"Point"}
}