{
  "type": "Feature",
  "properties": {
    "iso:country":"XX",
    "qs_pg:name":"Hewitt Farm",
    "qs_pg:name_adm0":"United States",
    "qs_pg:name_adm1":"Virginia",
    "qs_pg:photos":2210,
    "qs_pg:photos_1k":448,
    "qs_pg:photos_9k":10,
    "qs_pg:photos_9r":9,
    "qs_pg:photos_all":2210,
    "qs_pg:photos_sr":16,
    "qs_pg:pop_sr":0,
    "qs_pg:qs_pg_placetype":"neighbourhood",
    "qs_pg:qs_pg_placetype_gp":"Suburb",
    "qs_pg:woe_adm0":23424977,
    "woe:adm0_id":23424977,
    "woe:name_adm0":"United States",
    "woe:name_adm1":"Virginia",
    "woe:placetype":"Suburb",
    "wof:name":"Hewitt Farm",
    "wof:placetype":"neighbourhood"
},
  "geometry": {"coordinates":[-76.23271099999999,36.92266],"type":"Point"}
}