{
  "type": "Feature",
  "properties": {
    "iso:country":"XX",
    "qs_pg:name":"Sofa\u00efa",
    "qs_pg:name_adm0":"Guadeloupe",
    "qs_pg:name_adm1":"Basse-Terre",
    "qs_pg:photos":113,
    "qs_pg:photos_1k":23,
    "qs_pg:photos_9k":1,
    "qs_pg:photos_9r":3,
    "qs_pg:photos_all":113,
    "qs_pg:photos_sr":3,
    "qs_pg:pop_sr":0,
    "qs_pg:qs_pg_placetype":"locality",
    "qs_pg:qs_pg_placetype_gp":"Town",
    "qs_pg:woe_adm0":23424831,
    "woe:adm0_id":23424831,
    "woe:name_adm0":"Guadeloupe",
    "woe:name_adm1":"Basse-Terre",
    "woe:placetype":"Town",
    "wof:name":"Sofa\u00efa",
    "wof:placetype":"locality"
},
  "geometry": {"coordinates":[-61.692334,16.268666],"type":"Point"}
}