{
  "type": "Feature",
  "properties": {
    "iso:country":"XX",
    "qs_pg:name":"New Plymouth Central",
    "qs_pg:name_adm0":"New Zealand",
    "qs_pg:name_adm1":"Taranaki",
    "qs_pg:photos":1287,
    "qs_pg:photos_1k":261,
    "qs_pg:photos_9k":6,
    "qs_pg:photos_9r":7,
    "qs_pg:photos_all":1287,
    "qs_pg:photos_sr":12,
    "qs_pg:pop_sr":0,
    "qs_pg:qs_pg_placetype":"neighbourhood",
    "qs_pg:qs_pg_placetype_gp":"Suburb",
    "qs_pg:woe_adm0":23424916,
    "woe:adm0_id":23424916,
    "woe:name_adm0":"New Zealand",
    "woe:name_adm1":"Taranaki",
    "woe:placetype":"Suburb",
    "wof:name":"New Plymouth Central",
    "wof:placetype":"neighbourhood"
},
  "geometry": {"coordinates":[174.073386,-39.058056],"type":"Point"}
}