{
  "type": "Feature",
  "properties": {
    "iso:country":"XX",
    "name:ara_x_preferred":[
        "\u0628\u0648\u0648\u064a\u062a\u0634"
    ],
    "name:bos_x_preferred":[
        "Bovec"
    ],
    "name:cat_x_preferred":[
        "Bovec"
    ],
    "name:chi_x_preferred":[
        "\u535a\u97cb\u8328"
    ],
    "name:cze_x_preferred":[
        "Bovec"
    ],
    "name:dut_x_preferred":[
        "Bovec"
    ],
    "name:eng_x_preferred":[
        "Bovec"
    ],
    "name:fre_x_preferred":[
        "Bovec"
    ],
    "name:ger_x_preferred":[
        "Bovec"
    ],
    "name:hrv_x_preferred":[
        "Bovec"
    ],
    "name:hun_x_preferred":[
        "Bovec"
    ],
    "name:ita_x_preferred":[
        "Plezzo"
    ],
    "name:jpn_x_preferred":[
        "\u30dc\u30f4\u30a7\u30c4"
    ],
    "name:kor_x_preferred":[
        "\ubcf4\ubca0\uce20"
    ],
    "name:lat_x_preferred":[
        "Ampletium"
    ],
    "name:lit_x_preferred":[
        "Bovecas"
    ],
    "name:nob_x_preferred":[
        "Bovec"
    ],
    "name:oci_x_preferred":[
        "Bovec"
    ],
    "name:per_x_preferred":[
        "\u0628\u0648\u062a\u0633\u060c \u0627\u0633\u0644\u0648\u0648\u0646\u06cc"
    ],
    "name:pol_x_preferred":[
        "Bovec"
    ],
    "name:por_x_preferred":[
        "Bovec"
    ],
    "name:rum_x_preferred":[
        "Bovec"
    ],
    "name:rus_x_preferred":[
        "\u0411\u043e\u0432\u0435\u0446"
    ],
    "name:slo_x_preferred":[
        "Bovec"
    ],
    "name:slv_x_preferred":[
        "Bovec"
    ],
    "name:spa_x_preferred":[
        "Bovec"
    ],
    "name:srp_x_preferred":[
        "\u0411\u043e\u0432\u0435\u0446"
    ],
    "name:swe_x_preferred":[
        "Bovec"
    ],
    "name:tat_x_preferred":[
        "\u0411\u043e\u0432\u0435\u0442\u0441"
    ],
    "name:ukr_x_preferred":[
        "\u0411\u043e\u0432\u0435\u0446"
    ],
    "name:urd_x_preferred":[
        "\u0628\u0648\u0648\u06cc\u062a\u0633"
    ],
    "name:vie_x_preferred":[
        "Bovec"
    ],
    "qs_pg:name":"Bovec",
    "qs_pg:name_adm0":"Slovenija",
    "qs_pg:name_adm1":"Tolmin",
    "qs_pg:photos":1091,
    "qs_pg:photos_1k":221,
    "qs_pg:photos_9k":5,
    "qs_pg:photos_9r":7,
    "qs_pg:photos_all":1091,
    "qs_pg:photos_sr":11,
    "qs_pg:pop_sr":0,
    "qs_pg:qs_pg_placetype":"locality",
    "qs_pg:qs_pg_placetype_gp":"Town",
    "qs_pg:woe_adm0":23424945,
    "woe:adm0_id":23424945,
    "woe:name_adm0":"Slovenija",
    "woe:name_adm1":"Tolmin",
    "woe:placetype":"Town",
    "wof:name":"Bovec",
    "wof:placetype":"locality"
},
  "geometry": {"coordinates":[13.551635,46.336439],"type":"Point"}
}