{
  "type": "Feature",
  "properties": {
    "iso:country":"XX",
    "qs_pg:name":"Stafford Lakes Village-Medallion Series",
    "qs_pg:name_adm0":"United States",
    "qs_pg:name_adm1":"Virginia",
    "qs_pg:photos":9,
    "qs_pg:photos_1k":2,
    "qs_pg:photos_9k":1,
    "qs_pg:photos_9r":1,
    "qs_pg:photos_all":9,
    "qs_pg:photos_sr":1,
    "qs_pg:pop_sr":0,
    "qs_pg:qs_pg_placetype":"neighbourhood",
    "qs_pg:qs_pg_placetype_gp":"Suburb",
    "qs_pg:woe_adm0":23424977,
    "woe:adm0_id":23424977,
    "woe:name_adm0":"United States",
    "woe:name_adm1":"Virginia",
    "woe:placetype":"Suburb",
    "wof:name":"Stafford Lakes Village-Medallion Series",
    "wof:placetype":"neighbourhood"
},
  "geometry": {"coordinates":[-77.53099,38.359796],"type":"Point"}
}