{
  "type": "Feature",
  "properties": {
    "iso:country":"XX",
    "qs_pg:name":"Northeast Teaneck",
    "qs_pg:name_adm0":"United States",
    "qs_pg:name_adm1":"New Jersey",
    "qs_pg:photos":146,
    "qs_pg:photos_1k":30,
    "qs_pg:photos_9k":1,
    "qs_pg:photos_9r":3,
    "qs_pg:photos_all":146,
    "qs_pg:photos_sr":3,
    "qs_pg:pop_sr":0,
    "qs_pg:qs_pg_placetype":"neighbourhood",
    "qs_pg:qs_pg_placetype_gp":"Suburb",
    "qs_pg:woe_adm0":23424977,
    "woe:adm0_id":23424977,
    "woe:name_adm0":"United States",
    "woe:name_adm1":"New Jersey",
    "woe:placetype":"Suburb",
    "wof:name":"Northeast Teaneck",
    "wof:placetype":"neighbourhood"
},
  "geometry": {"coordinates":[-73.998541,40.904788],"type":"Point"}
}