{
  "type": "Feature",
  "properties": {
    "iso:country":"XX",
    "qs_pg:name":"Tingu\u00ed",
    "qs_pg:name_adm0":"Brasil",
    "qs_pg:name_adm1":"Paran\u00e1",
    "qs_pg:photos":170,
    "qs_pg:photos_1k":34,
    "qs_pg:photos_9k":1,
    "qs_pg:photos_9r":4,
    "qs_pg:photos_all":170,
    "qs_pg:photos_sr":4,
    "qs_pg:pop_sr":0,
    "qs_pg:qs_pg_placetype":"neighbourhood",
    "qs_pg:qs_pg_placetype_gp":"Suburb",
    "qs_pg:woe_adm0":23424768,
    "woe:adm0_id":23424768,
    "woe:name_adm0":"Brasil",
    "woe:name_adm1":"Paran\u00e1",
    "woe:placetype":"Suburb",
    "wof:name":"Tingu\u00ed",
    "wof:placetype":"neighbourhood"
},
  "geometry": {"coordinates":[-49.225616,-25.384142],"type":"Point"}
}