{
  "type": "Feature",
  "properties": {
    "iso:country":"XX",
    "name:eng_x_preferred":[
        "Alma\u0219u"
    ],
    "name:epo_x_preferred":[
        "Alma\u0219u"
    ],
    "name:fas_x_preferred":[
        "\u0627\u0644\u0645\u0627\u0633\u0648"
    ],
    "name:fra_x_preferred":[
        "Alma\u0219u"
    ],
    "name:hun_x_preferred":[
        "V\u00e1ralm\u00e1s"
    ],
    "name:ita_x_preferred":[
        "Alma\u0219u"
    ],
    "name:msa_x_preferred":[
        "Alma\u0219u"
    ],
    "name:nld_x_preferred":[
        "Alma\u0219u"
    ],
    "name:por_x_preferred":[
        "Alma\u0219u"
    ],
    "name:ron_x_preferred":[
        "Alma\u0219u"
    ],
    "name:ukr_x_preferred":[
        "\u0410\u043b\u043c\u0430\u0448\u0443"
    ],
    "name:vie_x_preferred":[
        "Almasu"
    ],
    "name:vol_x_preferred":[
        "Alma\u0219u"
    ],
    "qs_pg:name":"Alma\u0219u",
    "qs_pg:name_adm0":"Rom\u00e2nia",
    "qs_pg:name_adm1":"Salaj",
    "qs_pg:photos":12,
    "qs_pg:photos_1k":2,
    "qs_pg:photos_9k":1,
    "qs_pg:photos_9r":1,
    "qs_pg:photos_all":12,
    "qs_pg:photos_sr":1,
    "qs_pg:pop_sr":0,
    "qs_pg:qs_pg_placetype":"locality",
    "qs_pg:qs_pg_placetype_gp":"Town",
    "qs_pg:woe_adm0":23424933,
    "woe:adm0_id":23424933,
    "woe:name_adm0":"Rom\u00e2nia",
    "woe:name_adm1":"Salaj",
    "woe:placetype":"Town",
    "wof:name":"Alma\u0219u",
    "wof:placetype":"locality"
},
  "geometry": {"coordinates":[23.128967,46.952371],"type":"Point"}
}