{
  "type": "Feature",
  "properties": {
    "iso:country":"XX",
    "qs_pg:name":"Chambrell",
    "qs_pg:name_adm0":"United States",
    "qs_pg:name_adm1":"Virginia",
    "qs_pg:photos":500,
    "qs_pg:photos_1k":101,
    "qs_pg:photos_9k":2,
    "qs_pg:photos_9r":5,
    "qs_pg:photos_all":500,
    "qs_pg:photos_sr":7,
    "qs_pg:pop_sr":0,
    "qs_pg:qs_pg_placetype":"neighbourhood",
    "qs_pg:qs_pg_placetype_gp":"Suburb",
    "qs_pg:woe_adm0":23424977,
    "woe:adm0_id":23424977,
    "woe:name_adm0":"United States",
    "woe:name_adm1":"Virginia",
    "woe:placetype":"Suburb",
    "wof:name":"Chambrell",
    "wof:placetype":"neighbourhood"
},
  "geometry": {"coordinates":[-76.72113899999999,37.278381],"type":"Point"}
}