{
  "type": "Feature",
  "properties": {
    "iso:country":"XX",
    "name:fas_x_preferred":[
        "\u0641\u0627\u0631 \u0648\u0633\u062a"
    ],
    "name:fra_x_preferred":[
        "Far West"
    ],
    "name:spa_x_preferred":[
        "Far West"
    ],
    "qs_pg:name":"Far West",
    "qs_pg:name_adm0":"United States",
    "qs_pg:name_adm1":"Virginia",
    "qs_pg:photos":2859,
    "qs_pg:photos_1k":579,
    "qs_pg:photos_9k":13,
    "qs_pg:photos_9r":11,
    "qs_pg:photos_all":2859,
    "qs_pg:photos_sr":19,
    "qs_pg:pop_sr":0,
    "qs_pg:qs_pg_placetype":"neighbourhood",
    "qs_pg:qs_pg_placetype_gp":"Suburb",
    "qs_pg:woe_adm0":23424977,
    "woe:adm0_id":23424977,
    "woe:name_adm0":"United States",
    "woe:name_adm1":"Virginia",
    "woe:placetype":"Suburb",
    "wof:name":"Far West",
    "wof:placetype":"neighbourhood"
},
  "geometry": {"coordinates":[-77.537823,37.579038],"type":"Point"}
}