{
  "type": "Feature",
  "properties": {
    "iso:country":"XX",
    "qs_pg:name":"Rebou\u00e7as",
    "qs_pg:name_adm0":"Brasil",
    "qs_pg:name_adm1":"Paran\u00e1",
    "qs_pg:photos":1387,
    "qs_pg:photos_1k":281,
    "qs_pg:photos_9k":6,
    "qs_pg:photos_9r":7,
    "qs_pg:photos_all":1387,
    "qs_pg:photos_sr":12,
    "qs_pg:pop_sr":0,
    "qs_pg:qs_pg_placetype":"neighbourhood",
    "qs_pg:qs_pg_placetype_gp":"Suburb",
    "qs_pg:woe_adm0":23424768,
    "woe:adm0_id":23424768,
    "woe:name_adm0":"Brasil",
    "woe:name_adm1":"Paran\u00e1",
    "woe:placetype":"Suburb",
    "wof:name":"Rebou\u00e7as",
    "wof:placetype":"neighbourhood"
},
  "geometry": {"coordinates":[-49.265742,-25.44277],"type":"Point"}
}