{
  "type": "Feature",
  "properties": {
    "iso:country":"XX",
    "name:ces_x_preferred":[
        "Giv'at Amal Bet"
    ],
    "name:heb_x_preferred":[
        "\u05d2\u05d1\u05e2\u05ea \u05e2\u05de\u05dc \u05d1'"
    ],
    "name:pol_x_preferred":[
        "Giwat Amal Bet"
    ],
    "qs_pg:name":"Giv'at Amal Bet",
    "qs_pg:name_adm0":"Israel",
    "qs_pg:name_adm1":"Tel Aviv",
    "qs_pg:photos":213,
    "qs_pg:photos_1k":43,
    "qs_pg:photos_9k":1,
    "qs_pg:photos_9r":4,
    "qs_pg:photos_all":213,
    "qs_pg:photos_sr":4,
    "qs_pg:pop_sr":0,
    "qs_pg:qs_pg_placetype":"neighbourhood",
    "qs_pg:qs_pg_placetype_gp":"Suburb",
    "qs_pg:woe_adm0":23424852,
    "woe:adm0_id":23424852,
    "woe:name_adm0":"Israel",
    "woe:name_adm1":"Tel Aviv",
    "woe:placetype":"Suburb",
    "wof:name":"Giv'at Amal Bet",
    "wof:placetype":"neighbourhood"
},
  "geometry": {"coordinates":[34.793166,32.092028],"type":"Point"}
}