{
  "type": "Feature",
  "properties": {
    "iso:country":"XX",
    "qs_pg:name":"\uff11\u4e01\u76ee",
    "qs_pg:name_adm0":"\u65e5\u672c",
    "qs_pg:name_adm1":"\u9577\u91ce\u770c",
    "qs_pg:photos":19,
    "qs_pg:photos_1k":4,
    "qs_pg:photos_9k":1,
    "qs_pg:photos_9r":1,
    "qs_pg:photos_all":19,
    "qs_pg:photos_sr":1,
    "qs_pg:pop_sr":0,
    "qs_pg:qs_pg_placetype":"neighbourhood",
    "qs_pg:qs_pg_placetype_gp":"Suburb",
    "qs_pg:woe_adm0":23424856,
    "woe:adm0_id":23424856,
    "woe:name_adm0":"\u65e5\u672c",
    "woe:name_adm1":"\u9577\u91ce\u770c",
    "woe:placetype":"Suburb",
    "wof:name":"\uff11\u4e01\u76ee",
    "wof:placetype":"neighbourhood"
},
  "geometry": {"coordinates":[137.96236099999999,36.205916],"type":"Point"}
}