{
  "type": "Feature",
  "properties": {
    "iso:country":"XX",
    "qs_pg:name":"Shikun Llit",
    "qs_pg:name_adm0":"Israel",
    "qs_pg:name_adm1":"Tel Aviv",
    "qs_pg:photos":249,
    "qs_pg:photos_1k":50,
    "qs_pg:photos_9k":1,
    "qs_pg:photos_9r":4,
    "qs_pg:photos_all":249,
    "qs_pg:photos_sr":4,
    "qs_pg:pop_sr":0,
    "qs_pg:qs_pg_placetype":"neighbourhood",
    "qs_pg:qs_pg_placetype_gp":"Suburb",
    "qs_pg:woe_adm0":23424852,
    "woe:adm0_id":23424852,
    "woe:name_adm0":"Israel",
    "woe:name_adm1":"Tel Aviv",
    "woe:placetype":"Suburb",
    "wof:name":"Shikun Llit",
    "wof:placetype":"neighbourhood"
},
  "geometry": {"coordinates":[34.807629,32.093464],"type":"Point"}
}