{
  "type": "Feature",
  "properties": {
    "iso:country":"XX",
    "name:eng_x_preferred":[
        "Kahouanne"
    ],
    "name:nld_x_preferred":[
        "Kahouanne"
    ],
    "qs_pg:name":"Kahouanne",
    "qs_pg:name_adm0":"Guadeloupe",
    "qs_pg:name_adm1":"Pointe-\u00c0-Pitre",
    "qs_pg:photos":573,
    "qs_pg:photos_1k":116,
    "qs_pg:photos_9k":3,
    "qs_pg:photos_9r":5,
    "qs_pg:photos_all":573,
    "qs_pg:photos_sr":8,
    "qs_pg:pop_sr":0,
    "qs_pg:qs_pg_placetype":"locality",
    "qs_pg:qs_pg_placetype_gp":"Town",
    "qs_pg:woe_adm0":23424831,
    "woe:adm0_id":23424831,
    "woe:name_adm0":"Guadeloupe",
    "woe:name_adm1":"Pointe-\u00c0-Pitre",
    "woe:placetype":"Town",
    "wof:name":"Kahouanne",
    "wof:placetype":"locality"
},
  "geometry": {"coordinates":[-61.175308,16.249286],"type":"Point"}
}