{
  "type": "Feature",
  "properties": {
    "iso:country":"XX",
    "qs_pg:name":"Tapera Da Base",
    "qs_pg:name_adm0":"Brasil",
    "qs_pg:name_adm1":"Santa Catarina",
    "qs_pg:photos":187,
    "qs_pg:photos_1k":38,
    "qs_pg:photos_9k":1,
    "qs_pg:photos_9r":4,
    "qs_pg:photos_all":187,
    "qs_pg:photos_sr":4,
    "qs_pg:pop_sr":0,
    "qs_pg:qs_pg_placetype":"neighbourhood",
    "qs_pg:qs_pg_placetype_gp":"Suburb",
    "qs_pg:woe_adm0":23424768,
    "woe:adm0_id":23424768,
    "woe:name_adm0":"Brasil",
    "woe:name_adm1":"Santa Catarina",
    "woe:placetype":"Suburb",
    "wof:name":"Tapera Da Base",
    "wof:placetype":"neighbourhood"
},
  "geometry": {"coordinates":[-48.567177,-27.677447],"type":"Point"}
}