{
  "type": "Feature",
  "properties": {
    "iso:country":"XX",
    "qs_pg:name":"Tarum\u00e3",
    "qs_pg:name_adm0":"Brasil",
    "qs_pg:name_adm1":"Paran\u00e1",
    "qs_pg:photos":1168,
    "qs_pg:photos_1k":237,
    "qs_pg:photos_9k":5,
    "qs_pg:photos_9r":7,
    "qs_pg:photos_all":1168,
    "qs_pg:photos_sr":11,
    "qs_pg:pop_sr":0,
    "qs_pg:qs_pg_placetype":"neighbourhood",
    "qs_pg:qs_pg_placetype_gp":"Suburb",
    "qs_pg:woe_adm0":23424768,
    "woe:adm0_id":23424768,
    "woe:name_adm0":"Brasil",
    "woe:name_adm1":"Paran\u00e1",
    "woe:placetype":"Suburb",
    "wof:name":"Tarum\u00e3",
    "wof:placetype":"neighbourhood"
},
  "geometry": {"coordinates":[-49.226238,-25.428053],"type":"Point"}
}