{
  "type": "Feature",
  "properties": {
    "iso:country":"XX",
    "qs_pg:name":"Karanageri",
    "qs_pg:name_adm0":"India",
    "qs_pg:name_adm1":"Karnataka",
    "qs_pg:photos":40,
    "qs_pg:photos_1k":8,
    "qs_pg:photos_9k":1,
    "qs_pg:photos_9r":2,
    "qs_pg:photos_all":40,
    "qs_pg:photos_sr":2,
    "qs_pg:pop_sr":0,
    "qs_pg:qs_pg_placetype":"neighbourhood",
    "qs_pg:qs_pg_placetype_gp":"Suburb",
    "qs_pg:woe_adm0":23424848,
    "woe:adm0_id":23424848,
    "woe:name_adm0":"India",
    "woe:name_adm1":"Karnataka",
    "woe:placetype":"Suburb",
    "wof:name":"Karanageri",
    "wof:placetype":"neighbourhood"
},
  "geometry": {"coordinates":[75.80016999999999,12.432232],"type":"Point"}
}