{
  "type": "Feature",
  "properties": {
    "iso:country":"XX",
    "qs_pg:name":"Fracc Paseo de Los Cazos",
    "qs_pg:name_adm0":"M\u00e9xico",
    "qs_pg:name_adm1":"Jalisco",
    "qs_pg:photos":110,
    "qs_pg:photos_1k":22,
    "qs_pg:photos_9k":1,
    "qs_pg:photos_9r":3,
    "qs_pg:photos_all":110,
    "qs_pg:photos_sr":3,
    "qs_pg:pop_sr":0,
    "qs_pg:qs_pg_placetype":"neighbourhood",
    "qs_pg:qs_pg_placetype_gp":"Suburb",
    "qs_pg:woe_adm0":23424900,
    "woe:adm0_id":23424900,
    "woe:name_adm0":"M\u00e9xico",
    "woe:name_adm1":"Jalisco",
    "woe:placetype":"Suburb",
    "wof:name":"Fracc Paseo de Los Cazos",
    "wof:placetype":"neighbourhood"
},
  "geometry": {"coordinates":[-103.03462,19.905333],"type":"Point"}
}