{
  "type": "Feature",
  "properties": {
    "iso:country":"XX",
    "qs_pg:name":"Narrabeen Peninsula",
    "qs_pg:name_adm0":"Australia",
    "qs_pg:name_adm1":"New South Wales",
    "qs_pg:photos":558,
    "qs_pg:photos_1k":113,
    "qs_pg:photos_9k":2,
    "qs_pg:photos_9r":5,
    "qs_pg:photos_all":558,
    "qs_pg:photos_sr":8,
    "qs_pg:pop_sr":0,
    "qs_pg:qs_pg_placetype":"neighbourhood",
    "qs_pg:qs_pg_placetype_gp":"Suburb",
    "qs_pg:woe_adm0":23424748,
    "woe:adm0_id":23424748,
    "woe:name_adm0":"Australia",
    "woe:name_adm1":"New South Wales",
    "woe:placetype":"Suburb",
    "wof:name":"Narrabeen Peninsula",
    "wof:placetype":"neighbourhood"
},
  "geometry": {"coordinates":[151.30081899999999,-33.711024],"type":"Point"}
}