{
  "type": "Feature",
  "properties": {
    "iso:country":"XX",
    "qs_pg:name":"Barracks Road",
    "qs_pg:name_adm0":"United States",
    "qs_pg:name_adm1":"Virginia",
    "qs_pg:photos":2850,
    "qs_pg:photos_1k":578,
    "qs_pg:photos_9k":13,
    "qs_pg:photos_9r":11,
    "qs_pg:photos_all":2850,
    "qs_pg:photos_sr":19,
    "qs_pg:pop_sr":0,
    "qs_pg:qs_pg_placetype":"neighbourhood",
    "qs_pg:qs_pg_placetype_gp":"Suburb",
    "qs_pg:woe_adm0":23424977,
    "woe:adm0_id":23424977,
    "woe:name_adm0":"United States",
    "woe:name_adm1":"Virginia",
    "woe:placetype":"Suburb",
    "wof:name":"Barracks Road",
    "wof:placetype":"neighbourhood"
},
  "geometry": {"coordinates":[-78.510875,38.04684],"type":"Point"}
}