{
  "type": "Feature",
  "properties": {
    "iso:country":"XX",
    "qs_pg:name":"Campo Grande",
    "qs_pg:name_adm0":"Brasil",
    "qs_pg:name_adm1":"S\u00e3o Paulo",
    "qs_pg:photos":1832,
    "qs_pg:photos_1k":371,
    "qs_pg:photos_9k":8,
    "qs_pg:photos_9r":9,
    "qs_pg:photos_all":1832,
    "qs_pg:photos_sr":14,
    "qs_pg:pop_sr":0,
    "qs_pg:qs_pg_placetype":"neighbourhood",
    "qs_pg:qs_pg_placetype_gp":"Suburb",
    "qs_pg:woe_adm0":23424768,
    "woe:adm0_id":23424768,
    "woe:name_adm0":"Brasil",
    "woe:name_adm1":"S\u00e3o Paulo",
    "woe:placetype":"Suburb",
    "wof:name":"Campo Grande",
    "wof:placetype":"neighbourhood"
},
  "geometry": {"coordinates":[-46.348571,-23.968607],"type":"Point"}
}