{
  "type": "Feature",
  "properties": {
    "iso:country":"XX",
    "qs_pg:name":"Ignacio Altamirano",
    "qs_pg:name_adm0":"M\u00e9xico",
    "qs_pg:name_adm1":"Baja California",
    "qs_pg:photos":276,
    "qs_pg:photos_1k":56,
    "qs_pg:photos_9k":1,
    "qs_pg:photos_9r":4,
    "qs_pg:photos_all":276,
    "qs_pg:photos_sr":5,
    "qs_pg:pop_sr":0,
    "qs_pg:qs_pg_placetype":"neighbourhood",
    "qs_pg:qs_pg_placetype_gp":"Suburb",
    "qs_pg:woe_adm0":23424900,
    "woe:adm0_id":23424900,
    "woe:name_adm0":"M\u00e9xico",
    "woe:name_adm1":"Baja California",
    "woe:placetype":"Suburb",
    "wof:name":"Ignacio Altamirano",
    "wof:placetype":"neighbourhood"
},
  "geometry": {"coordinates":[-116.62831,31.863691],"type":"Point"}
}