{
  "type": "Feature",
  "properties": {
    "iso:country":"XX",
    "qs_pg:name":"Chalan Pupulu",
    "qs_pg:name_adm0":"Northern Mariana Islands",
    "qs_pg:name_adm1":"Saipan",
    "qs_pg:photos":9,
    "qs_pg:photos_1k":2,
    "qs_pg:photos_9k":1,
    "qs_pg:photos_9r":1,
    "qs_pg:photos_all":9,
    "qs_pg:photos_sr":1,
    "qs_pg:pop_sr":0,
    "qs_pg:qs_pg_placetype":"locality",
    "qs_pg:qs_pg_placetype_gp":"Town",
    "qs_pg:woe_adm0":23424788,
    "woe:adm0_id":23424788,
    "woe:name_adm0":"Northern Mariana Islands",
    "woe:name_adm1":"Saipan",
    "woe:placetype":"Town",
    "wof:name":"Chalan Pupulu",
    "wof:placetype":"locality"
},
  "geometry": {"coordinates":[145.71956599999999,15.185016],"type":"Point"}
}