{
  "type": "Feature",
  "properties": {
    "iso:country":"XX",
    "name:bos_x_preferred":[
        "Naklo"
    ],
    "name:ceb_x_preferred":[
        "Naklo"
    ],
    "name:deu_x_preferred":[
        "Naklo"
    ],
    "name:eng_x_preferred":[
        "Naklo"
    ],
    "name:fra_x_preferred":[
        "Naklo"
    ],
    "name:hrv_x_preferred":[
        "Naklo"
    ],
    "name:hun_x_preferred":[
        "Naklo"
    ],
    "name:ita_x_preferred":[
        "Naklo"
    ],
    "name:jpn_x_preferred":[
        "\u30ca\u30af\u30ed"
    ],
    "name:kor_x_preferred":[
        "\ub098\ud074\ub85c"
    ],
    "name:lit_x_preferred":[
        "Naklas"
    ],
    "name:nld_x_preferred":[
        "Naklo"
    ],
    "name:pol_x_preferred":[
        "Gmina Naklo"
    ],
    "name:pol_x_variant":[
        "Naklo"
    ],
    "name:por_x_preferred":[
        "Naklo"
    ],
    "name:ron_x_preferred":[
        "Naklo"
    ],
    "name:slv_x_preferred":[
        "Naklo"
    ],
    "name:srp_x_preferred":[
        "\u041d\u0430\u043a\u043b\u043e"
    ],
    "name:swe_x_preferred":[
        "Naklo"
    ],
    "name:ukr_x_preferred":[
        "\u041d\u0430\u043a\u043b\u043e"
    ],
    "name:vie_x_preferred":[
        "Naklo"
    ],
    "name:zho_x_preferred":[
        "\u7d0d\u514b\u6d1b"
    ],
    "qs_pg:name":"Naklo",
    "qs_pg:name_adm0":"Slovenija",
    "qs_pg:name_adm1":"Kranj",
    "qs_pg:photos":11,
    "qs_pg:photos_1k":2,
    "qs_pg:photos_9k":1,
    "qs_pg:photos_9r":1,
    "qs_pg:photos_all":11,
    "qs_pg:photos_sr":1,
    "qs_pg:pop_sr":0,
    "qs_pg:qs_pg_placetype":"locality",
    "qs_pg:qs_pg_placetype_gp":"Town",
    "qs_pg:woe_adm0":23424945,
    "woe:adm0_id":23424945,
    "woe:name_adm0":"Slovenija",
    "woe:name_adm1":"Kranj",
    "woe:placetype":"Town",
    "wof:name":"Naklo",
    "wof:placetype":"locality"
},
  "geometry": {"coordinates":[14.313666,46.270719],"type":"Point"}
}