{
  "type": "Feature",
  "properties": {
    "iso:country":"XX",
    "qs_pg:name":"Gurunanak Wara",
    "qs_pg:name_adm0":"India",
    "qs_pg:name_adm1":"Punjab",
    "qs_pg:photos":5,
    "qs_pg:photos_1k":1,
    "qs_pg:photos_9k":1,
    "qs_pg:photos_9r":1,
    "qs_pg:photos_all":5,
    "qs_pg:photos_sr":1,
    "qs_pg:pop_sr":0,
    "qs_pg:qs_pg_placetype":"neighbourhood",
    "qs_pg:qs_pg_placetype_gp":"Suburb",
    "qs_pg:woe_adm0":23424848,
    "woe:adm0_id":23424848,
    "woe:name_adm0":"India",
    "woe:name_adm1":"Punjab",
    "woe:placetype":"Suburb",
    "wof:name":"Gurunanak Wara",
    "wof:placetype":"neighbourhood"
},
  "geometry": {"coordinates":[74.838425,31.634106],"type":"Point"}
}