{
  "type": "Feature",
  "properties": {
    "iso:country":"XX",
    "qs_pg:name":"Smederevo",
    "qs_pg:name_adm0":"Serbia",
    "qs_pg:name_adm1":"Podunavlje",
    "qs_pg:photos":300,
    "qs_pg:photos_1k":61,
    "qs_pg:photos_9k":1,
    "qs_pg:photos_9r":4,
    "qs_pg:photos_all":300,
    "qs_pg:photos_sr":5,
    "qs_pg:pop_sr":0,
    "qs_pg:qs_pg_placetype":"locality",
    "qs_pg:qs_pg_placetype_gp":"Town",
    "qs_pg:woe_adm0":20069818,
    "woe:adm0_id":20069818,
    "woe:name_adm0":"Serbia",
    "woe:name_adm1":"Podunavlje",
    "woe:placetype":"Town",
    "wof:name":"Smederevo",
    "wof:placetype":"locality"
},
  "geometry": {"coordinates":[20.9313365,44.6673705],"type":"Point"}
}