{
  "type": "Feature",
  "properties": {
    "iso:country":"XX",
    "qs_pg:name":"Seyrantepe",
    "qs_pg:name_adm0":"Turkey",
    "qs_pg:name_adm1":"\u0130stanbul",
    "qs_pg:photos":215,
    "qs_pg:photos_1k":44,
    "qs_pg:photos_9k":1,
    "qs_pg:photos_9r":4,
    "qs_pg:photos_all":215,
    "qs_pg:photos_sr":4,
    "qs_pg:pop_sr":0,
    "qs_pg:qs_pg_placetype":"neighbourhood",
    "qs_pg:qs_pg_placetype_gp":"Suburb",
    "qs_pg:woe_adm0":23424969,
    "woe:adm0_id":23424969,
    "woe:name_adm0":"Turkey",
    "woe:name_adm1":"\u0130stanbul",
    "woe:placetype":"Suburb",
    "wof:name":"Seyrantepe",
    "wof:placetype":"neighbourhood"
},
  "geometry": {"coordinates":[28.991082,41.102638],"type":"Point"}
}