{
  "type": "Feature",
  "properties": {
    "iso:country":"XX",
    "qs_pg:name":"Whitiora",
    "qs_pg:name_adm0":"New Zealand",
    "qs_pg:name_adm1":"Waikato",
    "qs_pg:photos":616,
    "qs_pg:photos_1k":125,
    "qs_pg:photos_9k":3,
    "qs_pg:photos_9r":5,
    "qs_pg:photos_all":616,
    "qs_pg:photos_sr":8,
    "qs_pg:pop_sr":0,
    "qs_pg:qs_pg_placetype":"neighbourhood",
    "qs_pg:qs_pg_placetype_gp":"Suburb",
    "qs_pg:woe_adm0":23424916,
    "woe:adm0_id":23424916,
    "woe:name_adm0":"New Zealand",
    "woe:name_adm1":"Waikato",
    "woe:placetype":"Suburb",
    "wof:name":"Whitiora",
    "wof:placetype":"neighbourhood"
},
  "geometry": {"coordinates":[175.26743849999997,-37.781688],"type":"Point"}
}