{
  "type": "Feature",
  "properties": {
    "iso:country":"XX",
    "qs_pg:name":"Juarez",
    "qs_pg:name_adm0":"Costa Rica",
    "qs_pg:name_adm1":"San Jose",
    "qs_pg:photos":160,
    "qs_pg:photos_1k":32,
    "qs_pg:photos_9k":1,
    "qs_pg:photos_9r":4,
    "qs_pg:photos_all":160,
    "qs_pg:photos_sr":4,
    "qs_pg:pop_sr":0,
    "qs_pg:qs_pg_placetype":"neighbourhood",
    "qs_pg:qs_pg_placetype_gp":"Suburb",
    "qs_pg:woe_adm0":23424791,
    "woe:adm0_id":23424791,
    "woe:name_adm0":"Costa Rica",
    "woe:name_adm1":"San Jose",
    "woe:placetype":"Suburb",
    "wof:name":"Juarez",
    "wof:placetype":"neighbourhood"
},
  "geometry": {"coordinates":[-84.090728,9.940445],"type":"Point"}
}