{
  "type": "Feature",
  "properties": {
    "iso:country":"XX",
    "qs_pg:name":"Apra Harbor",
    "qs_pg:name_adm0":"Guam",
    "qs_pg:name_adm1":"Santa Rita",
    "qs_pg:photos":818,
    "qs_pg:photos_1k":166,
    "qs_pg:photos_9k":4,
    "qs_pg:photos_9r":6,
    "qs_pg:photos_all":818,
    "qs_pg:photos_sr":9,
    "qs_pg:pop_sr":0,
    "qs_pg:qs_pg_placetype":"locality",
    "qs_pg:qs_pg_placetype_gp":"Town",
    "qs_pg:woe_adm0":23424832,
    "woe:adm0_id":23424832,
    "woe:name_adm0":"Guam",
    "woe:name_adm1":"Santa Rita",
    "woe:placetype":"Town",
    "wof:name":"Apra Harbor",
    "wof:placetype":"locality"
},
  "geometry": {"coordinates":[144.66985700000001,13.440046],"type":"Point"}
}