{
  "type": "Feature",
  "properties": {
    "iso:country":"XX",
    "qs_pg:name":"Ibarrilla Poniente",
    "qs_pg:name_adm0":"M\u00e9xico",
    "qs_pg:name_adm1":"Guanajuato",
    "qs_pg:photos":64,
    "qs_pg:photos_1k":13,
    "qs_pg:photos_9k":1,
    "qs_pg:photos_9r":2,
    "qs_pg:photos_all":64,
    "qs_pg:photos_sr":2,
    "qs_pg:pop_sr":0,
    "qs_pg:qs_pg_placetype":"neighbourhood",
    "qs_pg:qs_pg_placetype_gp":"Suburb",
    "qs_pg:woe_adm0":23424900,
    "woe:adm0_id":23424900,
    "woe:name_adm0":"M\u00e9xico",
    "woe:name_adm1":"Guanajuato",
    "woe:placetype":"Suburb",
    "wof:name":"Ibarrilla Poniente",
    "wof:placetype":"neighbourhood"
},
  "geometry": {"coordinates":[-101.649584,21.186292],"type":"Point"}
}