{
  "type": "Feature",
  "properties": {
    "iso:country":"XX",
    "name:bre_x_preferred":[
        "Santa Clara"
    ],
    "name:bul_x_preferred":[
        "\u0421\u0430\u043d\u0442\u0430 \u041a\u043b\u0430\u0440\u0430"
    ],
    "name:cat_x_preferred":[
        "Santa Clara"
    ],
    "name:ceb_x_preferred":[
        "Santa Clara"
    ],
    "name:ces_x_preferred":[
        "Santa Clara"
    ],
    "name:deu_x_preferred":[
        "Santa Clara"
    ],
    "name:eus_x_preferred":[
        "Santa Clara"
    ],
    "name:fas_x_preferred":[
        "\u0633\u0627\u0646\u062a\u0627 \u06a9\u0644\u0627\u0631\u0627"
    ],
    "name:fin_x_preferred":[
        "Santa Clara"
    ],
    "name:fra_x_preferred":[
        "Santa Clara"
    ],
    "name:frr_x_preferred":[
        "Santa Clara"
    ],
    "name:glg_x_preferred":[
        "Santa Clara"
    ],
    "name:heb_x_preferred":[
        "\u05e1\u05e0\u05d8\u05d4 \u05e7\u05dc\u05e8\u05d4"
    ],
    "name:hun_x_preferred":[
        "Santa Clara"
    ],
    "name:ita_x_preferred":[
        "Santa Clara"
    ],
    "name:jpn_x_preferred":[
        "\u30b5\u30f3\u30bf\u30af\u30e9\u30e9"
    ],
    "name:kaz_x_preferred":[
        "\u0421\u0430\u043d\u0442\u0430-\u041a\u043b\u0430\u0440\u0430"
    ],
    "name:kor_x_preferred":[
        "\uc0b0\ud0c0\ud074\ub77c\ub77c"
    ],
    "name:ltz_x_preferred":[
        "Santa Clara"
    ],
    "name:nds_x_preferred":[
        "Santa Clara"
    ],
    "name:nld_x_preferred":[
        "Santa Clara"
    ],
    "name:nor_x_preferred":[
        "Santa Clara"
    ],
    "name:pol_x_preferred":[
        "Santa Clara"
    ],
    "name:por_x_preferred":[
        "Santa Clara"
    ],
    "name:ron_x_preferred":[
        "Santa Clara"
    ],
    "name:rus_x_preferred":[
        "\u0421\u0430\u043d\u0442\u0430-\u041a\u043b\u0430\u0440\u0430"
    ],
    "name:sco_x_preferred":[
        "Santa Clara"
    ],
    "name:slk_x_preferred":[
        "Santa Clara"
    ],
    "name:spa_x_preferred":[
        "Santa Clara"
    ],
    "name:srp_x_preferred":[
        "\u0421\u0430\u043d\u0442\u0430 \u041a\u043b\u0430\u0440\u0430"
    ],
    "name:swe_x_preferred":[
        "Santa Clara"
    ],
    "name:tur_x_preferred":[
        "Santa Clara"
    ],
    "name:ukr_x_preferred":[
        "\u0421\u0430\u043d\u0442\u0430-\u041a\u043b\u0430\u0440\u0430"
    ],
    "name:vie_x_preferred":[
        "Santa Clara"
    ],
    "name:vol_x_preferred":[
        "Santa Clara"
    ],
    "name:war_x_preferred":[
        "Santa Clara"
    ],
    "name:zho_x_preferred":[
        "\u5723\u514b\u62c9\u62c9"
    ],
    "qs_pg:name":"Santa Clara",
    "qs_pg:name_adm0":"M\u00e9xico",
    "qs_pg:name_adm1":"Baja California",
    "qs_pg:photos":21,
    "qs_pg:photos_1k":4,
    "qs_pg:photos_9k":1,
    "qs_pg:photos_9r":1,
    "qs_pg:photos_all":21,
    "qs_pg:photos_sr":1,
    "qs_pg:pop_sr":0,
    "qs_pg:qs_pg_placetype":"neighbourhood",
    "qs_pg:qs_pg_placetype_gp":"Suburb",
    "qs_pg:woe_adm0":23424900,
    "woe:adm0_id":23424900,
    "woe:name_adm0":"M\u00e9xico",
    "woe:name_adm1":"Baja California",
    "woe:placetype":"Suburb",
    "wof:name":"Santa Clara",
    "wof:placetype":"neighbourhood"
},
  "geometry": {"coordinates":[-115.5077,32.673311],"type":"Point"}
}