{
  "type": "Feature",
  "properties": {
    "gn:fcode":"PPLX",
    "gn:population":0,
    "iso:country":"XX",
    "qs_pg:gn_fcode":"PPLX",
    "qs_pg:gn_pop":0,
    "qs_pg:name":"Cit\u00e9 Pascaline",
    "qs_pg:name_adm0":"Guyane Fran\u00e7aise",
    "qs_pg:name_adm1":"Cayenne",
    "qs_pg:photos":5,
    "qs_pg:photos_1k":1,
    "qs_pg:photos_9k":1,
    "qs_pg:photos_9r":1,
    "qs_pg:photos_all":5,
    "qs_pg:photos_sr":1,
    "qs_pg:pop_sr":0,
    "qs_pg:qs_pg_placetype":"neighbourhood",
    "qs_pg:qs_pg_placetype_gp":"Suburb",
    "qs_pg:woe_adm0":23424811,
    "woe:adm0_id":23424811,
    "woe:name_adm0":"Guyane Fran\u00e7aise",
    "woe:name_adm1":"Cayenne",
    "woe:placetype":"Suburb",
    "wof:name":"Cit\u00e9 Pascaline",
    "wof:placetype":"neighbourhood"
},
  "geometry": {"coordinates":[-52.31643,4.92658],"type":"Point"}
}