{
  "type": "Feature",
  "properties": {
    "iso:country":"XX",
    "qs_pg:name":"Ste.-Menehould",
    "qs_pg:name_adm0":"France",
    "qs_pg:name_adm1":"Champagne-Ardenne",
    "qs_pg:photos":29,
    "qs_pg:photos_1k":6,
    "qs_pg:photos_9k":1,
    "qs_pg:photos_9r":2,
    "qs_pg:photos_all":29,
    "qs_pg:photos_sr":2,
    "qs_pg:pop_sr":0,
    "qs_pg:qs_pg_placetype":"locality",
    "qs_pg:qs_pg_placetype_gp":"Town",
    "qs_pg:woe_adm0":23424819,
    "woe:adm0_id":23424819,
    "woe:name_adm0":"France",
    "woe:name_adm1":"Champagne-Ardenne",
    "woe:placetype":"Town",
    "wof:name":"Ste.-Menehould",
    "wof:placetype":"locality"
},
  "geometry": {"coordinates":[4.897399,49.09163],"type":"Point"}
}