{
  "type": "Feature",
  "properties": {
    "iso:country":"XX",
    "qs_pg:name":"Hipodromo",
    "qs_pg:name_adm0":"M\u00e9xico",
    "qs_pg:name_adm1":"Distrito Federal",
    "qs_pg:photos":4020,
    "qs_pg:photos_1k":815,
    "qs_pg:photos_9k":18,
    "qs_pg:photos_9r":12,
    "qs_pg:photos_all":4020,
    "qs_pg:photos_sr":22,
    "qs_pg:pop_sr":0,
    "qs_pg:qs_pg_placetype":"neighbourhood",
    "qs_pg:qs_pg_placetype_gp":"Suburb",
    "qs_pg:woe_adm0":23424900,
    "woe:adm0_id":23424900,
    "woe:name_adm0":"M\u00e9xico",
    "woe:name_adm1":"Distrito Federal",
    "woe:placetype":"Suburb",
    "wof:name":"Hipodromo",
    "wof:placetype":"neighbourhood"
},
  "geometry": {"coordinates":[-99.169549,19.412829],"type":"Point"}
}