{
  "type": "Feature",
  "properties": {
    "iso:country":"XX",
    "name:alb_x_preferred":[
        "Alibunari"
    ],
    "name:ara_x_preferred":[
        "\u0623\u0644\u064a\u0628\u0648\u0646\u0627\u0631"
    ],
    "name:bos_x_preferred":[
        "Alibunar"
    ],
    "name:bul_x_preferred":[
        "\u0410\u043b\u0438\u0431\u0443\u043d\u0430\u0440"
    ],
    "name:chi_x_preferred":[
        "\u963f\u5229\u5e03\u8afe\u723e"
    ],
    "name:cze_x_preferred":[
        "Alibunar"
    ],
    "name:dut_x_preferred":[
        "Alibunar"
    ],
    "name:eng_x_preferred":[
        "Alibunar"
    ],
    "name:epo_x_preferred":[
        "Alibunar"
    ],
    "name:fre_x_preferred":[
        "Alibunar"
    ],
    "name:hrv_x_preferred":[
        "Alibunar"
    ],
    "name:hun_x_preferred":[
        "Alibun\u00e1r"
    ],
    "name:ita_x_preferred":[
        "Alibunar"
    ],
    "name:jpn_x_preferred":[
        "\u30a2\u30ea\u30d6\u30ca\u30eb"
    ],
    "name:may_x_preferred":[
        "Alibunar"
    ],
    "name:per_x_preferred":[
        "\u0627\u0644\u06cc\u0628\u0648\u0646\u0627\u0631"
    ],
    "name:pnb_x_preferred":[
        "\u0627\u0644\u06cc\u0628\u0648\u0646\u0627\u0631"
    ],
    "name:pol_x_preferred":[
        "Alibunar"
    ],
    "name:rum_x_preferred":[
        "Alibunar"
    ],
    "name:rus_x_preferred":[
        "\u0410\u043b\u0438\u0431\u0443\u043d\u0430\u0440"
    ],
    "name:slv_x_preferred":[
        "Alibunar"
    ],
    "name:srp_x_preferred":[
        "\u0410\u043b\u0438\u0431\u0443\u043d\u0430\u0440"
    ],
    "name:tat_x_preferred":[
        "\u0410\u043b\u0438\u0431\u0443\u043d\u0430\u0440"
    ],
    "qs_pg:name":"Alibunar",
    "qs_pg:name_adm0":"Serbia",
    "qs_pg:name_adm1":"Juzhni Banat",
    "qs_pg:photos":37,
    "qs_pg:photos_1k":7,
    "qs_pg:photos_9k":1,
    "qs_pg:photos_9r":2,
    "qs_pg:photos_all":37,
    "qs_pg:photos_sr":2,
    "qs_pg:pop_sr":0,
    "qs_pg:qs_pg_placetype":"locality",
    "qs_pg:qs_pg_placetype_gp":"Town",
    "qs_pg:woe_adm0":20069818,
    "woe:adm0_id":20069818,
    "woe:name_adm0":"Serbia",
    "woe:name_adm1":"Juzhni Banat",
    "woe:placetype":"Town",
    "wof:name":"Alibunar",
    "wof:placetype":"locality"
},
  "geometry": {"coordinates":[20.967407,45.081036],"type":"Point"}
}