{
  "type": "Feature",
  "properties": {
    "iso:country":"XX",
    "name:deu_x_preferred":[
        "The Forest"
    ],
    "name:fra_x_preferred":[
        "The Forest"
    ],
    "name:heb_x_preferred":[
        "\u05d4\u05d9\u05e2\u05e8"
    ],
    "name:ita_x_preferred":[
        "The Forest"
    ],
    "name:spa_x_preferred":[
        "The Forest"
    ],
    "qs_pg:name":"The Forest",
    "qs_pg:name_adm0":"Anguilla",
    "qs_pg:name_adm1":"The Quarter",
    "qs_pg:photos":114,
    "qs_pg:photos_1k":23,
    "qs_pg:photos_9k":1,
    "qs_pg:photos_9r":3,
    "qs_pg:photos_all":114,
    "qs_pg:photos_sr":3,
    "qs_pg:pop_sr":0,
    "qs_pg:qs_pg_placetype":"locality",
    "qs_pg:qs_pg_placetype_gp":"Town",
    "qs_pg:woe_adm0":23424751,
    "woe:adm0_id":23424751,
    "woe:name_adm0":"Anguilla",
    "woe:name_adm1":"The Quarter",
    "woe:placetype":"Town",
    "wof:name":"The Forest",
    "wof:placetype":"locality"
},
  "geometry": {"coordinates":[-63.030195,18.212719],"type":"Point"}
}