{
  "type": "Feature",
  "properties": {
    "iso:country":"XX",
    "qs_pg:name":"Bahia Vistamar",
    "qs_pg:name_adm0":"Puerto Rico",
    "qs_pg:name_adm1":"Carolina",
    "qs_pg:photos":80,
    "qs_pg:photos_1k":16,
    "qs_pg:photos_9k":1,
    "qs_pg:photos_9r":3,
    "qs_pg:photos_all":80,
    "qs_pg:photos_sr":3,
    "qs_pg:pop_sr":0,
    "qs_pg:qs_pg_placetype":"neighbourhood",
    "qs_pg:qs_pg_placetype_gp":"Suburb",
    "qs_pg:woe_adm0":23424935,
    "woe:adm0_id":23424935,
    "woe:name_adm0":"Puerto Rico",
    "woe:name_adm1":"Carolina",
    "woe:placetype":"Suburb",
    "wof:name":"Bahia Vistamar",
    "wof:placetype":"neighbourhood"
},
  "geometry": {"coordinates":[-65.9668125,18.4521845],"type":"Point"}
}