{
  "type": "Feature",
  "properties": {
    "iso:country":"XX",
    "name:eng_x_preferred":[
        "Luncavi\u021ba"
    ],
    "name:epo_x_preferred":[
        "Luncavi\u021ba"
    ],
    "name:hun_x_preferred":[
        "Luncavi\u021ba"
    ],
    "name:ita_x_preferred":[
        "Luncavi\u021ba"
    ],
    "name:msa_x_preferred":[
        "Luncavi\u021ba"
    ],
    "name:nld_x_preferred":[
        "Luncavi\u021ba"
    ],
    "name:por_x_preferred":[
        "Luncavi\u021ba"
    ],
    "name:ron_x_preferred":[
        "Luncavi\u021ba"
    ],
    "name:ukr_x_preferred":[
        "\u041b\u0443\u043d\u043a\u0430\u0432\u0456\u0446\u0430"
    ],
    "qs_pg:name":"Luncavi\u021ba",
    "qs_pg:name_adm0":"Rom\u00e2nia",
    "qs_pg:name_adm1":"Tulcea",
    "qs_pg:photos":4,
    "qs_pg:photos_1k":1,
    "qs_pg:photos_9k":1,
    "qs_pg:photos_9r":1,
    "qs_pg:photos_all":4,
    "qs_pg:photos_sr":1,
    "qs_pg:pop_sr":0,
    "qs_pg:qs_pg_placetype":"locality",
    "qs_pg:qs_pg_placetype_gp":"Town",
    "qs_pg:woe_adm0":23424933,
    "woe:adm0_id":23424933,
    "woe:name_adm0":"Rom\u00e2nia",
    "woe:name_adm1":"Tulcea",
    "woe:placetype":"Town",
    "wof:name":"Luncavi\u021ba",
    "wof:placetype":"locality"
},
  "geometry": {"coordinates":[28.284332,45.286783],"type":"Point"}
}