{
  "type": "Feature",
  "properties": {
    "iso:country":"XX",
    "qs_pg:name":"Centro C\u00edvico",
    "qs_pg:name_adm0":"Brasil",
    "qs_pg:name_adm1":"Paran\u00e1",
    "qs_pg:photos":8352,
    "qs_pg:photos_1k":1000,
    "qs_pg:photos_9k":37,
    "qs_pg:photos_9r":15,
    "qs_pg:photos_all":8352,
    "qs_pg:photos_sr":25,
    "qs_pg:pop_sr":0,
    "qs_pg:qs_pg_placetype":"neighbourhood",
    "qs_pg:qs_pg_placetype_gp":"Suburb",
    "qs_pg:woe_adm0":23424768,
    "woe:adm0_id":23424768,
    "woe:name_adm0":"Brasil",
    "woe:name_adm1":"Paran\u00e1",
    "woe:placetype":"Suburb",
    "wof:name":"Centro C\u00edvico",
    "wof:placetype":"neighbourhood"
},
  "geometry": {"coordinates":[-49.268145,-25.413082],"type":"Point"}
}