{
  "type": "Feature",
  "properties": {
    "iso:country":"XX",
    "name:aze_x_preferred":[
        "Peqli"
    ],
    "name:bel_x_preferred":[
        "\u041f\u0435\u043b\u044c\u0456"
    ],
    "name:cym_x_preferred":[
        "Pegli"
    ],
    "name:dan_x_preferred":[
        "Pegli"
    ],
    "name:deu_x_preferred":[
        "Pegli"
    ],
    "name:eng_x_preferred":[
        "Pegli"
    ],
    "name:fra_x_preferred":[
        "Pegli"
    ],
    "name:ita_x_preferred":[
        "Pegli"
    ],
    "name:lat_x_preferred":[
        "Pyla Veituriorum"
    ],
    "name:lij_x_preferred":[
        "P\u00eagi"
    ],
    "name:nld_x_preferred":[
        "Pegli"
    ],
    "name:pol_x_preferred":[
        "Pegli"
    ],
    "name:por_x_preferred":[
        "Pegli"
    ],
    "name:spa_x_preferred":[
        "Pegli"
    ],
    "name:ukr_x_preferred":[
        "\u041f\u0435\u043b\u044c\u0457"
    ],
    "wof:name":"Pegli",
    "wof:placetype":"neighbourhood"
},
  "geometry": {"coordinates":[8.81553305090129,44.42607456128648],"type":"Point"}
}