{
  "type": "Feature",
  "properties": {
    "iso:country":"XX",
    "name:ceb_x_preferred":[
        "Greenbrier"
    ],
    "name:deu_x_preferred":[
        "Greenbrier"
    ],
    "name:fra_x_preferred":[
        "Greenbrier"
    ],
    "name:ita_x_preferred":[
        "Greenbrier"
    ],
    "name:nld_x_preferred":[
        "Greenbrier"
    ],
    "name:pol_x_preferred":[
        "Greenbrier"
    ],
    "name:por_x_preferred":[
        "Greenbrier"
    ],
    "name:rus_x_preferred":[
        "\u0413\u0440\u0438\u043d\u0431\u0440\u0430\u0439\u0435\u0440"
    ],
    "name:spa_x_preferred":[
        "Greenbrier"
    ],
    "name:srp_x_preferred":[
        "\u0413\u0440\u0438\u043d\u0431\u0440\u0430\u0458\u0435\u0440"
    ],
    "qs_pg:name":"Greenbrier",
    "qs_pg:name_adm0":"United States",
    "qs_pg:name_adm1":"Virginia",
    "qs_pg:photos":359,
    "qs_pg:photos_1k":73,
    "qs_pg:photos_9k":2,
    "qs_pg:photos_9r":5,
    "qs_pg:photos_all":359,
    "qs_pg:photos_sr":6,
    "qs_pg:pop_sr":0,
    "qs_pg:qs_pg_placetype":"neighbourhood",
    "qs_pg:qs_pg_placetype_gp":"Suburb",
    "qs_pg:woe_adm0":23424977,
    "woe:adm0_id":23424977,
    "woe:name_adm0":"United States",
    "woe:name_adm1":"Virginia",
    "woe:placetype":"Suburb",
    "wof:name":"Greenbrier",
    "wof:placetype":"neighbourhood"
},
  "geometry": {"coordinates":[-78.476377,38.053316],"type":"Point"}
}