{
  "type": "Feature",
  "properties": {
    "iso:country":"XX",
    "qs_pg:name":"Hosur",
    "qs_pg:name_adm0":"India",
    "qs_pg:name_adm1":"Karnataka",
    "qs_pg:photos":145,
    "qs_pg:photos_1k":29,
    "qs_pg:photos_9k":1,
    "qs_pg:photos_9r":3,
    "qs_pg:photos_all":145,
    "qs_pg:photos_sr":3,
    "qs_pg:pop_sr":0,
    "qs_pg:qs_pg_placetype":"neighbourhood",
    "qs_pg:qs_pg_placetype_gp":"Suburb",
    "qs_pg:woe_adm0":23424848,
    "woe:adm0_id":23424848,
    "woe:name_adm0":"India",
    "woe:name_adm1":"Karnataka",
    "woe:placetype":"Suburb",
    "wof:name":"Hosur",
    "wof:placetype":"neighbourhood"
},
  "geometry": {"coordinates":[76.3694,15.279631],"type":"Point"}
}