{
  "type": "Feature",
  "properties": {
    "iso:country":"XX",
    "name:bih_x_preferred":[
        "\u0939\u094b\u0938\u0941\u0930"
    ],
    "name:bpy_x_preferred":[
        "\u09b9\u09cb\u09b8\u09c1\u09b0"
    ],
    "name:cat_x_preferred":[
        "Hosur"
    ],
    "name:ceb_x_preferred":[
        "Hos\u016br"
    ],
    "name:deu_x_preferred":[
        "Hosur"
    ],
    "name:hin_x_preferred":[
        "\u0939\u094b\u0938\u0942\u0930"
    ],
    "name:ita_x_preferred":[
        "Hosur"
    ],
    "name:kan_x_preferred":[
        "\u0cb9\u0cca\u0cb8\u0cc2\u0cb0\u0cc1"
    ],
    "name:mar_x_preferred":[
        "\u0939\u094b\u0938\u0942\u0930"
    ],
    "name:mlg_x_preferred":[
        "Hosur"
    ],
    "name:msa_x_preferred":[
        "Hosur"
    ],
    "name:new_x_preferred":[
        "\u0939\u094b\u0938\u0941\u0930"
    ],
    "name:spa_x_preferred":[
        "Hosur"
    ],
    "name:swe_x_preferred":[
        "Hosur"
    ],
    "name:tam_x_preferred":[
        "\u0b93\u0b9a\u0bc2\u0bb0\u0bcd"
    ],
    "name:urd_x_preferred":[
        "\u06c1\u0648\u0633\u0648\u0631"
    ],
    "name:vie_x_preferred":[
        "Hosur"
    ],
    "name:zho_x_preferred":[
        "\u970d\u82cf\u5c14"
    ],
    "qs_pg:name":"Hosur",
    "qs_pg:name_adm0":"India",
    "qs_pg:name_adm1":"Karnataka",
    "qs_pg:photos":145,
    "qs_pg:photos_1k":29,
    "qs_pg:photos_9k":1,
    "qs_pg:photos_9r":3,
    "qs_pg:photos_all":145,
    "qs_pg:photos_sr":3,
    "qs_pg:pop_sr":0,
    "qs_pg:qs_pg_placetype":"neighbourhood",
    "qs_pg:qs_pg_placetype_gp":"Suburb",
    "qs_pg:woe_adm0":23424848,
    "woe:adm0_id":23424848,
    "woe:name_adm0":"India",
    "woe:name_adm1":"Karnataka",
    "woe:placetype":"Suburb",
    "wof:name":"Hosur",
    "wof:placetype":"neighbourhood"
},
  "geometry": {"coordinates":[76.3694,15.279631],"type":"Point"}
}