{
  "type": "Feature",
  "properties": {
    "iso:country":"XX",
    "name:arz_x_preferred":[
        "\u0647\u0627\u0631\u062f\u064a\u0646\u0631\u0627\u064a\u0643\u0633\u062a\u0627\u064a\u0646"
    ],
    "name:cat_x_preferred":[
        "Heidenreichstein"
    ],
    "name:ceb_x_preferred":[
        "Heidenreichstein"
    ],
    "name:ces_x_preferred":[
        "Heidenreichstein"
    ],
    "name:che_x_preferred":[
        "\u0425\u0430\u0439\u0434\u0435\u043d\u0440\u0430\u0439\u0445\u0448\u0442\u0430\u0439\u043d"
    ],
    "name:deu_x_preferred":[
        "Heidenreichstein"
    ],
    "name:eng_x_preferred":[
        "Heidenreichstein"
    ],
    "name:epo_x_preferred":[
        "Heidenreichstein"
    ],
    "name:fas_x_preferred":[
        "\u0647\u0627\u06cc\u062f\u0646 \u0631\u0627\u06cc\u06a9\u0633\u0646"
    ],
    "name:fra_x_preferred":[
        "Heidenreichstein"
    ],
    "name:hun_x_preferred":[
        "Heidenreichstein"
    ],
    "name:ita_x_preferred":[
        "Heidenreichstein"
    ],
    "name:jpn_x_preferred":[
        "\u30cf\u30a4\u30c7\u30f3\u30e9\u30a4\u30d2\u30b7\u30e5\u30bf\u30a4\u30f3"
    ],
    "name:kaz_x_preferred":[
        "\u0425\u0430\u0439\u0434\u0435\u043d\u0440\u0430\u0439\u0445\u0448\u0442\u0430\u0439\u043d"
    ],
    "name:lld_x_preferred":[
        "Heidenreichstein"
    ],
    "name:nld_x_preferred":[
        "Heidenreichstein"
    ],
    "name:nno_x_preferred":[
        "Heidenreichstein"
    ],
    "name:nob_x_preferred":[
        "Heidenreichstein"
    ],
    "name:pol_x_preferred":[
        "Heidenreichstein"
    ],
    "name:por_x_preferred":[
        "Heidenreichstein"
    ],
    "name:rus_x_preferred":[
        "\u0425\u0430\u0439\u0434\u0435\u043d\u0440\u0430\u0439\u0445\u0448\u0442\u0430\u0439\u043d"
    ],
    "name:slk_x_preferred":[
        "Heidenreichstein"
    ],
    "name:spa_x_preferred":[
        "Heidenreichstein"
    ],
    "name:swe_x_preferred":[
        "Heidenreichstein"
    ],
    "name:tat_x_preferred":[
        "\u0425\u0430\u0439\u0434\u0435\u043d\u0440\u0430\u0439\u0445\u0448\u0442\u0430\u0439\u043d"
    ],
    "name:uzb_x_preferred":[
        "Heidenreichstein"
    ],
    "name:vec_x_preferred":[
        "Heidenreichstein"
    ],
    "name:vie_x_preferred":[
        "Heidenreichstein"
    ],
    "name:vol_x_preferred":[
        "Heidenreichstein"
    ],
    "name:war_x_preferred":[
        "Heidenreichstein"
    ],
    "name:zho_x_preferred":[
        "Heidenreichstein"
    ],
    "qs_pg:name":"Heidenreichstein",
    "qs_pg:name_adm0":"\u00d6sterreich",
    "qs_pg:name_adm1":"Nieder\u00f6sterreich",
    "qs_pg:photos":217,
    "qs_pg:photos_1k":44,
    "qs_pg:photos_9k":1,
    "qs_pg:photos_9r":4,
    "qs_pg:photos_all":217,
    "qs_pg:photos_sr":4,
    "qs_pg:pop_sr":0,
    "qs_pg:qs_pg_placetype":"locality",
    "qs_pg:qs_pg_placetype_gp":"Town",
    "qs_pg:woe_adm0":23424750,
    "woe:adm0_id":23424750,
    "woe:name_adm0":"\u00d6sterreich",
    "woe:name_adm1":"Nieder\u00f6sterreich",
    "woe:placetype":"Town",
    "wof:name":"Heidenreichstein",
    "wof:placetype":"locality"
},
  "geometry": {"coordinates":[15.12322,48.865741],"type":"Point"}
}