{
  "type": "Feature",
  "properties": {
    "iso:country":"XX",
    "qs_pg:name":"\u4f5b\u5802 \u6fb3",
    "qs_pg:name_adm0":"\u9999\u6e2f",
    "qs_pg:name_adm1":"\u65b0\u754c",
    "qs_pg:photos":513,
    "qs_pg:photos_1k":104,
    "qs_pg:photos_9k":2,
    "qs_pg:photos_9r":5,
    "qs_pg:photos_all":513,
    "qs_pg:photos_sr":7,
    "qs_pg:pop_sr":0,
    "qs_pg:qs_pg_placetype":"locality",
    "qs_pg:qs_pg_placetype_gp":"Town",
    "qs_pg:woe_adm0":24865698,
    "woe:adm0_id":24865698,
    "woe:name_adm0":"\u9999\u6e2f",
    "woe:name_adm1":"\u65b0\u754c",
    "woe:placetype":"Town",
    "wof:name":"\u4f5b\u5802 \u6fb3",
    "wof:placetype":"locality"
},
  "geometry": {"coordinates":[114.28459100000001,22.255919],"type":"Point"}
}