{
  "type": "Feature",
  "properties": {
    "iso:country":"XX",
    "qs_pg:name":"Arnsdorf bei Radeberg",
    "qs_pg:name_adm0":"Deutschland",
    "qs_pg:name_adm1":"Sachsen",
    "qs_pg:photos":19,
    "qs_pg:photos_1k":4,
    "qs_pg:photos_9k":1,
    "qs_pg:photos_9r":1,
    "qs_pg:photos_all":19,
    "qs_pg:photos_sr":1,
    "qs_pg:pop_sr":0,
    "qs_pg:qs_pg_placetype":"locality",
    "qs_pg:qs_pg_placetype_gp":"Town",
    "qs_pg:woe_adm0":23424829,
    "woe:adm0_id":23424829,
    "woe:name_adm0":"Deutschland",
    "woe:name_adm1":"Sachsen",
    "woe:placetype":"Town",
    "wof:name":"Arnsdorf bei Radeberg",
    "wof:placetype":"locality"
},
  "geometry": {"coordinates":[13.990058,51.096515],"type":"Point"}
}