{
  "type": "Feature",
  "properties": {
    "iso:country":"XX",
    "qs_pg:name":"Los Morales Secc Palmas",
    "qs_pg:name_adm0":"M\u00e9xico",
    "qs_pg:name_adm1":"Distrito Federal",
    "qs_pg:photos":296,
    "qs_pg:photos_1k":60,
    "qs_pg:photos_9k":1,
    "qs_pg:photos_9r":4,
    "qs_pg:photos_all":296,
    "qs_pg:photos_sr":5,
    "qs_pg:pop_sr":0,
    "qs_pg:qs_pg_placetype":"neighbourhood",
    "qs_pg:qs_pg_placetype_gp":"Suburb",
    "qs_pg:woe_adm0":23424900,
    "woe:adm0_id":23424900,
    "woe:name_adm0":"M\u00e9xico",
    "woe:name_adm1":"Distrito Federal",
    "woe:placetype":"Suburb",
    "wof:name":"Los Morales Secc Palmas",
    "wof:placetype":"neighbourhood"
},
  "geometry": {"coordinates":[-99.20216499999999,19.438969],"type":"Point"}
}