{
  "type": "Feature",
  "properties": {
    "iso:country":"XX",
    "qs_pg:name":"Puerto Vallarta Centro",
    "qs_pg:name_adm0":"M\u00e9xico",
    "qs_pg:name_adm1":"Jalisco",
    "qs_pg:photos":5197,
    "qs_pg:photos_1k":1000,
    "qs_pg:photos_9k":23,
    "qs_pg:photos_9r":14,
    "qs_pg:photos_all":5197,
    "qs_pg:photos_sr":24,
    "qs_pg:pop_sr":0,
    "qs_pg:qs_pg_placetype":"neighbourhood",
    "qs_pg:qs_pg_placetype_gp":"Suburb",
    "qs_pg:woe_adm0":23424900,
    "woe:adm0_id":23424900,
    "woe:name_adm0":"M\u00e9xico",
    "woe:name_adm1":"Jalisco",
    "woe:placetype":"Suburb",
    "wof:name":"Puerto Vallarta Centro",
    "wof:placetype":"neighbourhood"
},
  "geometry": {"coordinates":[-105.23465899999999,20.611255],"type":"Point"}
}