{
  "type": "Feature",
  "properties": {
    "iso:country":"XX",
    "qs_pg:name":"HMAS Watson",
    "qs_pg:name_adm0":"Australia",
    "qs_pg:name_adm1":"New South Wales",
    "qs_pg:photos":2483,
    "qs_pg:photos_1k":503,
    "qs_pg:photos_9k":11,
    "qs_pg:photos_9r":10,
    "qs_pg:photos_all":2483,
    "qs_pg:photos_sr":17,
    "qs_pg:pop_sr":0,
    "qs_pg:qs_pg_placetype":"neighbourhood",
    "qs_pg:qs_pg_placetype_gp":"Suburb",
    "qs_pg:woe_adm0":23424748,
    "woe:adm0_id":23424748,
    "woe:name_adm0":"Australia",
    "woe:name_adm1":"New South Wales",
    "woe:placetype":"Suburb",
    "wof:name":"HMAS Watson",
    "wof:placetype":"neighbourhood"
},
  "geometry": {"coordinates":[151.279978,-33.833563],"type":"Point"}
}