{
  "type": "Feature",
  "properties": {
    "iso:country":"XX",
    "qs_pg:name":"\uff08\u4e01\u76ee\u306a\u3057\uff09",
    "qs_pg:name_adm0":"\u65e5\u672c",
    "qs_pg:name_adm1":"\u795e\u5948\u5ddd\u770c",
    "qs_pg:photos":99,
    "qs_pg:photos_1k":20,
    "qs_pg:photos_9k":1,
    "qs_pg:photos_9r":3,
    "qs_pg:photos_all":99,
    "qs_pg:photos_sr":3,
    "qs_pg:pop_sr":0,
    "qs_pg:qs_pg_placetype":"neighbourhood",
    "qs_pg:qs_pg_placetype_gp":"Suburb",
    "qs_pg:woe_adm0":23424856,
    "woe:adm0_id":23424856,
    "woe:name_adm0":"\u65e5\u672c",
    "woe:name_adm1":"\u795e\u5948\u5ddd\u770c",
    "woe:placetype":"Suburb",
    "wof:name":"\uff08\u4e01\u76ee\u306a\u3057\uff09",
    "wof:placetype":"neighbourhood"
},
  "geometry": {"coordinates":[139.25366600000001,35.3825],"type":"Point"}
}