{
  "type": "Feature",
  "properties": {
    "iso:country":"XX",
    "qs_pg:name":"Mcguire",
    "qs_pg:name_adm0":"United States",
    "qs_pg:name_adm1":"Idaho",
    "qs_pg:photos":38,
    "qs_pg:photos_1k":8,
    "qs_pg:photos_9k":1,
    "qs_pg:photos_9r":2,
    "qs_pg:photos_all":38,
    "qs_pg:photos_sr":2,
    "qs_pg:pop_sr":0,
    "qs_pg:qs_pg_placetype":"neighbourhood",
    "qs_pg:qs_pg_placetype_gp":"Suburb",
    "qs_pg:woe_adm0":23424977,
    "woe:adm0_id":23424977,
    "woe:name_adm0":"United States",
    "woe:name_adm1":"Idaho",
    "woe:placetype":"Suburb",
    "wof:name":"Mcguire",
    "wof:placetype":"neighbourhood"
},
  "geometry": {"coordinates":[-117.001654,47.7073025],"type":"Point"}
}