{
  "type": "Feature",
  "properties": {
    "iso:country":"XX",
    "qs_pg:name":"Lewis Mountain",
    "qs_pg:name_adm0":"United States",
    "qs_pg:name_adm1":"Virginia",
    "qs_pg:photos":925,
    "qs_pg:photos_1k":187,
    "qs_pg:photos_9k":4,
    "qs_pg:photos_9r":6,
    "qs_pg:photos_all":925,
    "qs_pg:photos_sr":10,
    "qs_pg:pop_sr":0,
    "qs_pg:qs_pg_placetype":"neighbourhood",
    "qs_pg:qs_pg_placetype_gp":"Suburb",
    "qs_pg:woe_adm0":23424977,
    "woe:adm0_id":23424977,
    "woe:name_adm0":"United States",
    "woe:name_adm1":"Virginia",
    "woe:placetype":"Suburb",
    "wof:name":"Lewis Mountain",
    "wof:placetype":"neighbourhood"
},
  "geometry": {"coordinates":[-78.508172,38.043663],"type":"Point"}
}