{
  "type": "Feature",
  "properties": {
    "iso:country":"XX",
    "qs_pg:name":"San Rafael",
    "qs_pg:name_adm0":"M\u00e9xico",
    "qs_pg:name_adm1":"Distrito Federal",
    "qs_pg:photos":1269,
    "qs_pg:photos_1k":257,
    "qs_pg:photos_9k":6,
    "qs_pg:photos_9r":7,
    "qs_pg:photos_all":1269,
    "qs_pg:photos_sr":12,
    "qs_pg:pop_sr":0,
    "qs_pg:qs_pg_placetype":"neighbourhood",
    "qs_pg:qs_pg_placetype_gp":"Suburb",
    "qs_pg:woe_adm0":23424900,
    "woe:adm0_id":23424900,
    "woe:name_adm0":"M\u00e9xico",
    "woe:name_adm1":"Distrito Federal",
    "woe:placetype":"Suburb",
    "wof:name":"San Rafael",
    "wof:placetype":"neighbourhood"
},
  "geometry": {"coordinates":[-99.15997900000001,19.434538],"type":"Point"}
}