{
  "type": "Feature",
  "properties": {
    "iso:country":"XX",
    "qs_pg:name":"Bahia Ensenada",
    "qs_pg:name_adm0":"M\u00e9xico",
    "qs_pg:name_adm1":"Baja California",
    "qs_pg:photos":1157,
    "qs_pg:photos_1k":234,
    "qs_pg:photos_9k":5,
    "qs_pg:photos_9r":7,
    "qs_pg:photos_all":1157,
    "qs_pg:photos_sr":11,
    "qs_pg:pop_sr":0,
    "qs_pg:qs_pg_placetype":"neighbourhood",
    "qs_pg:qs_pg_placetype_gp":"Suburb",
    "qs_pg:woe_adm0":23424900,
    "woe:adm0_id":23424900,
    "woe:name_adm0":"M\u00e9xico",
    "woe:name_adm1":"Baja California",
    "woe:placetype":"Suburb",
    "wof:name":"Bahia Ensenada",
    "wof:placetype":"neighbourhood"
},
  "geometry": {"coordinates":[-116.621323,31.859844],"type":"Point"}
}