{
  "type": "Feature",
  "properties": {
    "iso:country":"XX",
    "qs_pg:name":"Ni\u00b5ka Banja",
    "qs_pg:name_adm0":"Serbia",
    "qs_pg:name_adm1":"Nishava",
    "qs_pg:photos":26,
    "qs_pg:photos_1k":5,
    "qs_pg:photos_9k":1,
    "qs_pg:photos_9r":2,
    "qs_pg:photos_all":26,
    "qs_pg:photos_sr":2,
    "qs_pg:pop_sr":0,
    "qs_pg:qs_pg_placetype":"locality",
    "qs_pg:qs_pg_placetype_gp":"Town",
    "qs_pg:woe_adm0":20069818,
    "woe:adm0_id":20069818,
    "woe:name_adm0":"Serbia",
    "woe:name_adm1":"Nishava",
    "woe:placetype":"Town",
    "wof:name":"Ni\u00b5ka Banja",
    "wof:placetype":"locality"
},
  "geometry": {"coordinates":[21.993255,43.282141],"type":"Point"}
}