{
  "type": "Feature",
  "properties": {
    "iso:country":"XX",
    "name:eng_x_preferred":[
        "Cankurtaran"
    ],
    "name:tur_x_preferred":[
        "Cankurtaran"
    ],
    "qs_pg:name":"Cankurtaran",
    "qs_pg:name_adm0":"Turkey",
    "qs_pg:name_adm1":"\u0130stanbul",
    "qs_pg:photos":6191,
    "qs_pg:photos_1k":1000,
    "qs_pg:photos_9k":27,
    "qs_pg:photos_9r":14,
    "qs_pg:photos_all":6191,
    "qs_pg:photos_sr":24,
    "qs_pg:pop_sr":0,
    "qs_pg:qs_pg_placetype":"neighbourhood",
    "qs_pg:qs_pg_placetype_gp":"Suburb",
    "qs_pg:woe_adm0":23424969,
    "woe:adm0_id":23424969,
    "woe:name_adm0":"Turkey",
    "woe:name_adm1":"\u0130stanbul",
    "woe:placetype":"Suburb",
    "wof:name":"Cankurtaran",
    "wof:placetype":"neighbourhood"
},
  "geometry": {"coordinates":[28.983221,41.011446],"type":"Point"}
}