{
  "type": "Feature",
  "properties": {
    "iso:country":"XX",
    "qs_pg:name":"Torupilli",
    "qs_pg:name_adm0":"Eesti",
    "qs_pg:name_adm1":"Harjumaa",
    "qs_pg:photos":1590,
    "qs_pg:photos_1k":322,
    "qs_pg:photos_9k":7,
    "qs_pg:photos_9r":8,
    "qs_pg:photos_all":1590,
    "qs_pg:photos_sr":13,
    "qs_pg:pop_sr":0,
    "qs_pg:qs_pg_placetype":"neighbourhood",
    "qs_pg:qs_pg_placetype_gp":"Suburb",
    "qs_pg:woe_adm0":23424805,
    "woe:adm0_id":23424805,
    "woe:name_adm0":"Eesti",
    "woe:name_adm1":"Harjumaa",
    "woe:placetype":"Suburb",
    "wof:name":"Torupilli",
    "wof:placetype":"neighbourhood"
},
  "geometry": {"coordinates":[24.783182,59.434612],"type":"Point"}
}