{
  "type": "Feature",
  "properties": {
    "iso:country":"XX",
    "name:eng_x_preferred":[
        "Tr\u00e5nghalla"
    ],
    "name:fas_x_preferred":[
        "\u062a\u0631\u0648\u0646\u06af\u0627\u0644\u0627"
    ],
    "name:fra_x_preferred":[
        "Tr\u00e5nghalla"
    ],
    "name:ita_x_preferred":[
        "Tr\u00e5nghalla"
    ],
    "name:nld_x_preferred":[
        "Tr\u00e5nghalla"
    ],
    "name:nno_x_preferred":[
        "Tr\u00e5nghalla"
    ],
    "name:nob_x_preferred":[
        "Tr\u00e5nghalla"
    ],
    "name:swe_x_preferred":[
        "Tr\u00e5nghalla"
    ],
    "qs_pg:name":"Tranghalla",
    "qs_pg:name_adm0":"Sverige",
    "qs_pg:name_adm1":"J\u00f6nk\u00f6pings L\u00e4n",
    "qs_pg:photos":7,
    "qs_pg:photos_1k":1,
    "qs_pg:photos_9k":1,
    "qs_pg:photos_9r":1,
    "qs_pg:photos_all":7,
    "qs_pg:photos_sr":1,
    "qs_pg:pop_sr":0,
    "qs_pg:qs_pg_placetype":"locality",
    "qs_pg:qs_pg_placetype_gp":"Town",
    "qs_pg:woe_adm0":23424954,
    "woe:adm0_id":23424954,
    "woe:name_adm0":"Sverige",
    "woe:name_adm1":"J\u00f6nk\u00f6pings L\u00e4n",
    "woe:placetype":"Town",
    "wof:name":"Tranghalla",
    "wof:placetype":"locality"
},
  "geometry": {"coordinates":[14.149317,57.841507],"type":"Point"}
}