{
  "type": "Feature",
  "properties": {
    "iso:country":"XX",
    "name:deu_x_preferred":[
        "Velox"
    ],
    "name:fin_x_preferred":[
        "Velox"
    ],
    "name:nld_x_preferred":[
        "Velox"
    ],
    "name:por_x_preferred":[
        "Oi Velox"
    ],
    "qs_pg:name":"Velox",
    "qs_pg:name_adm0":"United States",
    "qs_pg:name_adm1":"Washington",
    "qs_pg:photos":27,
    "qs_pg:photos_1k":5,
    "qs_pg:photos_9k":1,
    "qs_pg:photos_9r":2,
    "qs_pg:photos_all":27,
    "qs_pg:photos_sr":2,
    "qs_pg:pop_sr":0,
    "qs_pg:qs_pg_placetype":"neighbourhood",
    "qs_pg:qs_pg_placetype_gp":"Suburb",
    "qs_pg:woe_adm0":23424977,
    "woe:adm0_id":23424977,
    "woe:name_adm0":"United States",
    "woe:name_adm1":"Washington",
    "woe:placetype":"Suburb",
    "wof:name":"Velox",
    "wof:placetype":"neighbourhood"
},
  "geometry": {"coordinates":[-117.165026,47.699667],"type":"Point"}
}