{
  "type": "Feature",
  "properties": {
    "iso:country":"XX",
    "name:ceb_x_preferred":[
        "Carbonera"
    ],
    "name:ita_x_preferred":[
        "Carbonera"
    ],
    "name:lat_x_preferred":[
        "Carbonera"
    ],
    "name:lmo_x_preferred":[
        "Carbonera"
    ],
    "name:spa_x_preferred":[
        "Carbonera"
    ],
    "name:srp_x_preferred":[
        "Carbonera"
    ],
    "name:swe_x_preferred":[
        "Carbonera"
    ],
    "qs_pg:name":"Carbonera",
    "qs_pg:name_adm0":"United States",
    "qs_pg:name_adm1":"California",
    "qs_pg:photos":502,
    "qs_pg:photos_1k":102,
    "qs_pg:photos_9k":2,
    "qs_pg:photos_9r":5,
    "qs_pg:photos_all":502,
    "qs_pg:photos_sr":7,
    "qs_pg:pop_sr":0,
    "qs_pg:qs_pg_placetype":"neighbourhood",
    "qs_pg:qs_pg_placetype_gp":"Suburb",
    "qs_pg:woe_adm0":23424977,
    "woe:adm0_id":23424977,
    "woe:name_adm0":"United States",
    "woe:name_adm1":"California",
    "woe:placetype":"Suburb",
    "wof:name":"Carbonera",
    "wof:placetype":"neighbourhood"
},
  "geometry": {"coordinates":[-122.00458999999999,37.009929],"type":"Point"}
}