{
  "type": "Feature",
  "properties": {
    "iso:country":"XX",
    "qs_pg:name":"Skeidhflotur",
    "qs_pg:name_adm0":"\u00cdsland",
    "qs_pg:name_adm1":"Vestur-Skaftafellssysla",
    "qs_pg:photos":941,
    "qs_pg:photos_1k":191,
    "qs_pg:photos_9k":4,
    "qs_pg:photos_9r":6,
    "qs_pg:photos_all":941,
    "qs_pg:photos_sr":10,
    "qs_pg:pop_sr":0,
    "qs_pg:qs_pg_placetype":"locality",
    "qs_pg:qs_pg_placetype_gp":"Town",
    "qs_pg:woe_adm0":23424845,
    "woe:adm0_id":23424845,
    "woe:name_adm0":"\u00cdsland",
    "woe:name_adm1":"Vestur-Skaftafellssysla",
    "woe:placetype":"Town",
    "wof:name":"Skeidhflotur",
    "wof:placetype":"locality"
},
  "geometry": {"coordinates":[-19.150543,63.42487],"type":"Point"}
}