{
  "type": "Feature",
  "properties": {
    "iso:country":"XX",
    "qs_pg:name":"Drni\u00b5",
    "qs_pg:name_adm0":"Hrvatska",
    "qs_pg:name_adm1":"Sibenska",
    "qs_pg:photos":22,
    "qs_pg:photos_1k":4,
    "qs_pg:photos_9k":1,
    "qs_pg:photos_9r":1,
    "qs_pg:photos_all":22,
    "qs_pg:photos_sr":1,
    "qs_pg:pop_sr":0,
    "qs_pg:qs_pg_placetype":"locality",
    "qs_pg:qs_pg_placetype_gp":"Town",
    "qs_pg:woe_adm0":23424843,
    "woe:adm0_id":23424843,
    "woe:name_adm0":"Hrvatska",
    "woe:name_adm1":"Sibenska",
    "woe:placetype":"Town",
    "wof:name":"Drni\u00b5",
    "wof:placetype":"locality"
},
  "geometry": {"coordinates":[16.159665,43.860586],"type":"Point"}
}