{
  "type": "Feature",
  "properties": {
    "iso:country":"XX",
    "qs_pg:name":"Poligono Molino del Pilar",
    "qs_pg:name_adm0":"Espa\u00f1a",
    "qs_pg:name_adm1":"Arag\u00f3n",
    "qs_pg:photos":228,
    "qs_pg:photos_1k":46,
    "qs_pg:photos_9k":1,
    "qs_pg:photos_9r":4,
    "qs_pg:photos_all":228,
    "qs_pg:photos_sr":4,
    "qs_pg:pop_sr":0,
    "qs_pg:qs_pg_placetype":"neighbourhood",
    "qs_pg:qs_pg_placetype_gp":"Suburb",
    "qs_pg:woe_adm0":23424950,
    "woe:adm0_id":23424950,
    "woe:name_adm0":"Espa\u00f1a",
    "woe:name_adm1":"Arag\u00f3n",
    "woe:placetype":"Suburb",
    "wof:name":"Poligono Molino del Pilar",
    "wof:placetype":"neighbourhood"
},
  "geometry": {"coordinates":[-0.869561,41.686013],"type":"Point"}
}