{
  "type": "Feature",
  "properties": {
    "iso:country":"XX",
    "qs_pg:name":"Verona North Side",
    "qs_pg:name_adm0":"United States",
    "qs_pg:name_adm1":"New Jersey",
    "qs_pg:photos":272,
    "qs_pg:photos_1k":55,
    "qs_pg:photos_9k":1,
    "qs_pg:photos_9r":4,
    "qs_pg:photos_all":272,
    "qs_pg:photos_sr":5,
    "qs_pg:pop_sr":0,
    "qs_pg:qs_pg_placetype":"neighbourhood",
    "qs_pg:qs_pg_placetype_gp":"Suburb",
    "qs_pg:woe_adm0":23424977,
    "woe:adm0_id":23424977,
    "woe:name_adm0":"United States",
    "woe:name_adm1":"New Jersey",
    "woe:placetype":"Suburb",
    "wof:name":"Verona North Side",
    "wof:placetype":"neighbourhood"
},
  "geometry": {"coordinates":[-74.24306149999998,40.841411],"type":"Point"}
}