{
  "type": "Feature",
  "properties": {
    "iso:country":"XX",
    "qs_pg:name":"Stazione di Fiumefreddo Bruzio",
    "qs_pg:name_adm0":"Italia",
    "qs_pg:name_adm1":"Calabria",
    "qs_pg:photos":15,
    "qs_pg:photos_1k":3,
    "qs_pg:photos_9k":1,
    "qs_pg:photos_9r":1,
    "qs_pg:photos_all":15,
    "qs_pg:photos_sr":1,
    "qs_pg:pop_sr":0,
    "qs_pg:qs_pg_placetype":"locality",
    "qs_pg:qs_pg_placetype_gp":"Town",
    "qs_pg:woe_adm0":23424853,
    "woe:adm0_id":23424853,
    "woe:name_adm0":"Italia",
    "woe:name_adm1":"Calabria",
    "woe:placetype":"Town",
    "wof:name":"Stazione di Fiumefreddo Bruzio",
    "wof:placetype":"locality"
},
  "geometry": {"coordinates":[16.060681,39.244759],"type":"Point"}
}