{
  "type": "Feature",
  "properties": {
    "iso:country":"XX",
    "qs_pg:name":"Puesta de Sol",
    "qs_pg:name_adm0":"M\u00e9xico",
    "qs_pg:name_adm1":"Colima",
    "qs_pg:photos":78,
    "qs_pg:photos_1k":16,
    "qs_pg:photos_9k":1,
    "qs_pg:photos_9r":3,
    "qs_pg:photos_all":78,
    "qs_pg:photos_sr":3,
    "qs_pg:pop_sr":0,
    "qs_pg:qs_pg_placetype":"neighbourhood",
    "qs_pg:qs_pg_placetype_gp":"Suburb",
    "qs_pg:woe_adm0":23424900,
    "woe:adm0_id":23424900,
    "woe:name_adm0":"M\u00e9xico",
    "woe:name_adm1":"Colima",
    "woe:placetype":"Suburb",
    "wof:name":"Puesta de Sol",
    "wof:placetype":"neighbourhood"
},
  "geometry": {"coordinates":[-104.402732,19.106436],"type":"Point"}
}