{
  "type": "Feature",
  "properties": {
    "iso:country":"XX",
    "qs_pg:name":"Crawley-Nedlands",
    "qs_pg:name_adm0":"Australia",
    "qs_pg:name_adm1":"Western Australia",
    "qs_pg:photos":96,
    "qs_pg:photos_1k":19,
    "qs_pg:photos_9k":1,
    "qs_pg:photos_9r":3,
    "qs_pg:photos_all":96,
    "qs_pg:photos_sr":3,
    "qs_pg:pop_sr":0,
    "qs_pg:qs_pg_placetype":"neighbourhood",
    "qs_pg:qs_pg_placetype_gp":"Suburb",
    "qs_pg:woe_adm0":23424748,
    "woe:adm0_id":23424748,
    "woe:name_adm0":"Australia",
    "woe:name_adm1":"Western Australia",
    "woe:placetype":"Suburb",
    "wof:name":"Crawley-Nedlands",
    "wof:placetype":"neighbourhood"
},
  "geometry": {"coordinates":[115.799401,-31.980582],"type":"Point"}
}