{
  "type": "Feature",
  "properties": {
    "iso:country":"XX",
    "qs_pg:name":"Mansione de Garden Hills",
    "qs_pg:name_adm0":"Puerto Rico",
    "qs_pg:name_adm1":"Guaynabo",
    "qs_pg:photos":2,
    "qs_pg:photos_1k":1,
    "qs_pg:photos_9k":1,
    "qs_pg:photos_9r":1,
    "qs_pg:photos_all":2,
    "qs_pg:photos_sr":1,
    "qs_pg:pop_sr":0,
    "qs_pg:qs_pg_placetype":"neighbourhood",
    "qs_pg:qs_pg_placetype_gp":"Suburb",
    "qs_pg:woe_adm0":23424935,
    "woe:adm0_id":23424935,
    "woe:name_adm0":"Puerto Rico",
    "woe:name_adm1":"Guaynabo",
    "woe:placetype":"Suburb",
    "wof:name":"Mansione de Garden Hills",
    "wof:placetype":"neighbourhood"
},
  "geometry": {"coordinates":[-66.1065,18.402417],"type":"Point"}
}