{
  "type": "Feature",
  "properties": {
    "iso:country":"XX",
    "qs_pg:name":"Canfranc Estacion",
    "qs_pg:name_adm0":"Espa\u00f1a",
    "qs_pg:name_adm1":"Arag\u00f3n",
    "qs_pg:photos":421,
    "qs_pg:photos_1k":85,
    "qs_pg:photos_9k":2,
    "qs_pg:photos_9r":5,
    "qs_pg:photos_all":421,
    "qs_pg:photos_sr":6,
    "qs_pg:pop_sr":0,
    "qs_pg:qs_pg_placetype":"locality",
    "qs_pg:qs_pg_placetype_gp":"Town",
    "qs_pg:woe_adm0":23424950,
    "woe:adm0_id":23424950,
    "woe:name_adm0":"Espa\u00f1a",
    "woe:name_adm1":"Arag\u00f3n",
    "woe:placetype":"Town",
    "wof:name":"Canfranc Estacion",
    "wof:placetype":"locality"
},
  "geometry": {"coordinates":[-0.514715,42.748296],"type":"Point"}
}