{
  "type": "Feature",
  "properties": {
    "iso:country":"XX",
    "qs_pg:name":"Caminhos de Ferro",
    "qs_pg:name_adm0":"Portugal",
    "qs_pg:name_adm1":"Lisboa",
    "qs_pg:photos":485,
    "qs_pg:photos_1k":98,
    "qs_pg:photos_9k":2,
    "qs_pg:photos_9r":5,
    "qs_pg:photos_all":485,
    "qs_pg:photos_sr":7,
    "qs_pg:pop_sr":0,
    "qs_pg:qs_pg_placetype":"neighbourhood",
    "qs_pg:qs_pg_placetype_gp":"Suburb",
    "qs_pg:woe_adm0":23424925,
    "woe:adm0_id":23424925,
    "woe:name_adm0":"Portugal",
    "woe:name_adm1":"Lisboa",
    "woe:placetype":"Suburb",
    "wof:name":"Caminhos de Ferro",
    "wof:placetype":"neighbourhood"
},
  "geometry": {"coordinates":[-9.11922,38.718331],"type":"Point"}
}