{
  "type": "Feature",
  "properties": {
    "iso:country":"XX",
    "qs_pg:name":"Barrenjoey Head",
    "qs_pg:name_adm0":"Australia",
    "qs_pg:name_adm1":"New South Wales",
    "qs_pg:photos":1422,
    "qs_pg:photos_1k":288,
    "qs_pg:photos_9k":6,
    "qs_pg:photos_9r":7,
    "qs_pg:photos_all":1422,
    "qs_pg:photos_sr":12,
    "qs_pg:pop_sr":0,
    "qs_pg:qs_pg_placetype":"neighbourhood",
    "qs_pg:qs_pg_placetype_gp":"Suburb",
    "qs_pg:woe_adm0":23424748,
    "woe:adm0_id":23424748,
    "woe:name_adm0":"Australia",
    "woe:name_adm1":"New South Wales",
    "woe:placetype":"Suburb",
    "wof:name":"Barrenjoey Head",
    "wof:placetype":"neighbourhood"
},
  "geometry": {"coordinates":[151.32718499999999,-33.580875],"type":"Point"}
}