{
  "type": "Feature",
  "properties": {
    "iso:country":"XX",
    "name:bos_x_preferred":[
        "Para\u0107in"
    ],
    "name:bul_x_preferred":[
        "\u041f\u0430\u0440\u0430\u0447\u0438\u043d"
    ],
    "name:ces_x_preferred":[
        "Para\u0107in"
    ],
    "name:ckb_x_preferred":[
        "\u067e\u0627\u0631\u0627\u0686\u06cc\u0646"
    ],
    "name:deu_x_preferred":[
        "Para\u0107in"
    ],
    "name:eng_x_preferred":[
        "Para\u0107in"
    ],
    "name:fas_x_preferred":[
        "\u067e\u0627\u0631\u0627\u0686\u06cc\u0646"
    ],
    "name:fra_x_preferred":[
        "Para\u0107in"
    ],
    "name:hrv_x_preferred":[
        "Para\u0107in"
    ],
    "name:hun_x_preferred":[
        "Para\u0107in"
    ],
    "name:ita_x_preferred":[
        "Para\u0107in"
    ],
    "name:jpn_x_preferred":[
        "\u30d1\u30e9\u30c1\u30f3"
    ],
    "name:kor_x_preferred":[
        "\ud30c\ub77c\uce5c"
    ],
    "name:lit_x_preferred":[
        "Para\u010dinas"
    ],
    "name:mkd_x_preferred":[
        "\u041f\u0430\u0440\u0430\u045c\u0438\u043d"
    ],
    "name:msa_x_preferred":[
        "Para\u0107in"
    ],
    "name:nld_x_preferred":[
        "Para\u0107in"
    ],
    "name:pnb_x_preferred":[
        "\u067e\u0627\u0631\u0627\u0633\u0646"
    ],
    "name:pol_x_preferred":[
        "Para\u0107in"
    ],
    "name:por_x_preferred":[
        "Para\u0107in"
    ],
    "name:slv_x_preferred":[
        "Para\u0107in"
    ],
    "name:srp_x_preferred":[
        "\u041f\u0430\u0440\u0430\u045b\u0438\u043d"
    ],
    "name:swe_x_preferred":[
        "Para\u0107in"
    ],
    "name:tat_x_preferred":[
        "\u041f\u0430\u0440\u0430\u0447\u0438\u043d"
    ],
    "name:vie_x_preferred":[
        "Para\u0107in"
    ],
    "name:zho_x_preferred":[
        "\u5e15\u62c9\u6b3d"
    ],
    "qs_pg:name":"Para\u0107in",
    "qs_pg:name_adm0":"Serbia",
    "qs_pg:name_adm1":"Pomoravlje",
    "qs_pg:photos":13,
    "qs_pg:photos_1k":3,
    "qs_pg:photos_9k":1,
    "qs_pg:photos_9r":1,
    "qs_pg:photos_all":13,
    "qs_pg:photos_sr":1,
    "qs_pg:pop_sr":0,
    "qs_pg:qs_pg_placetype":"locality",
    "qs_pg:qs_pg_placetype_gp":"Town",
    "qs_pg:woe_adm0":20069818,
    "woe:adm0_id":20069818,
    "woe:name_adm0":"Serbia",
    "woe:name_adm1":"Pomoravlje",
    "woe:placetype":"Town",
    "wof:name":"Para\u0107in",
    "wof:placetype":"locality"
},
  "geometry": {"coordinates":[21.411752,43.869435],"type":"Point"}
}