{
  "type": "Feature",
  "properties": {
    "iso:country":"XX",
    "name:ast_x_preferred":[
        "Jaime Torres Bodet"
    ],
    "name:aze_x_preferred":[
        "Hayme Torres Bodet"
    ],
    "name:cat_x_preferred":[
        "Jaime Torres Bodet"
    ],
    "name:deu_x_preferred":[
        "Jaime Torres Bodet"
    ],
    "name:epo_x_preferred":[
        "Jaime Torres Bodet"
    ],
    "name:fra_x_preferred":[
        "Jaime Torres Bodet"
    ],
    "name:glg_x_preferred":[
        "Jaime Torres Bodet"
    ],
    "name:ita_x_preferred":[
        "Jaime Torres Bodet"
    ],
    "name:nld_x_preferred":[
        "Jaime Torres Bodet"
    ],
    "name:pol_x_preferred":[
        "Jaime Torres Bodet"
    ],
    "name:por_x_preferred":[
        "Jaime Torres Bodet"
    ],
    "name:rus_x_preferred":[
        "\u0422\u043e\u0440\u0440\u0435\u0441 \u0411\u043e\u0434\u0435\u0442"
    ],
    "name:spa_x_preferred":[
        "Jaime Torres Bodet"
    ],
    "name:ukr_x_preferred":[
        "\u0425\u0430\u0439\u043c\u0435 \u0422\u043e\u0440\u0440\u0435\u0441 \u0411\u043e\u0434\u0435\u0442"
    ],
    "qs_pg:name":"Jaime Torres Bodet",
    "qs_pg:name_adm0":"M\u00e9xico",
    "qs_pg:name_adm1":"Distrito Federal",
    "qs_pg:photos":14,
    "qs_pg:photos_1k":3,
    "qs_pg:photos_9k":1,
    "qs_pg:photos_9r":1,
    "qs_pg:photos_all":14,
    "qs_pg:photos_sr":1,
    "qs_pg:pop_sr":0,
    "qs_pg:qs_pg_placetype":"neighbourhood",
    "qs_pg:qs_pg_placetype_gp":"Suburb",
    "qs_pg:woe_adm0":23424900,
    "woe:adm0_id":23424900,
    "woe:name_adm0":"M\u00e9xico",
    "woe:name_adm1":"Distrito Federal",
    "woe:placetype":"Suburb",
    "wof:name":"Jaime Torres Bodet",
    "wof:placetype":"neighbourhood"
},
  "geometry": {"coordinates":[-98.996815,19.2296555],"type":"Point"}
}