{
  "type": "Feature",
  "properties": {
    "iso:country":"XX",
    "qs_pg:name":"The Mill",
    "qs_pg:name_adm0":"British Virgin Islands",
    "qs_pg:photos":2622,
    "qs_pg:photos_1k":531,
    "qs_pg:photos_9k":12,
    "qs_pg:photos_9r":10,
    "qs_pg:photos_all":2622,
    "qs_pg:photos_sr":18,
    "qs_pg:pop_sr":0,
    "qs_pg:qs_pg_placetype":"locality",
    "qs_pg:qs_pg_placetype_gp":"Town",
    "qs_pg:woe_adm0":23424983,
    "woe:adm0_id":23424983,
    "woe:name_adm0":"British Virgin Islands",
    "woe:placetype":"Town",
    "wof:name":"The Mill",
    "wof:placetype":"locality"
},
  "geometry": {"coordinates":[-64.531631,18.447288],"type":"Point"}
}