{
  "type": "Feature",
  "properties": {
    "iso:country":"XX",
    "qs_pg:name":"Scotts Point",
    "qs_pg:name_adm0":"Australia",
    "qs_pg:name_adm1":"Queensland",
    "qs_pg:photos":73,
    "qs_pg:photos_1k":15,
    "qs_pg:photos_9k":1,
    "qs_pg:photos_9r":2,
    "qs_pg:photos_all":73,
    "qs_pg:photos_sr":2,
    "qs_pg:pop_sr":0,
    "qs_pg:qs_pg_placetype":"neighbourhood",
    "qs_pg:qs_pg_placetype_gp":"Suburb",
    "qs_pg:woe_adm0":23424748,
    "woe:adm0_id":23424748,
    "woe:name_adm0":"Australia",
    "woe:name_adm1":"Queensland",
    "woe:placetype":"Suburb",
    "wof:name":"Scotts Point",
    "wof:placetype":"neighbourhood"
},
  "geometry": {"coordinates":[153.10965200000001,-27.256742],"type":"Point"}
}