{
  "type": "Feature",
  "properties": {
    "iso:country":"XX",
    "qs_pg:name":"Avalon Beach",
    "qs_pg:name_adm0":"Australia",
    "qs_pg:name_adm1":"New South Wales",
    "qs_pg:photos":372,
    "qs_pg:photos_1k":75,
    "qs_pg:photos_9k":2,
    "qs_pg:photos_9r":5,
    "qs_pg:photos_all":372,
    "qs_pg:photos_sr":6,
    "qs_pg:pop_sr":0,
    "qs_pg:qs_pg_placetype":"neighbourhood",
    "qs_pg:qs_pg_placetype_gp":"Suburb",
    "qs_pg:woe_adm0":23424748,
    "woe:adm0_id":23424748,
    "woe:name_adm0":"Australia",
    "woe:name_adm1":"New South Wales",
    "woe:placetype":"Suburb",
    "wof:name":"Avalon Beach",
    "wof:placetype":"neighbourhood"
},
  "geometry": {"coordinates":[151.33194900000001,-33.636915],"type":"Point"}
}