{
  "type": "Feature",
  "properties": {
    "iso:country":"XX",
    "qs_pg:name":"Bol'nichnyj",
    "qs_pg:name_adm0":"Russia",
    "qs_pg:name_adm1":"Murmansk Oblast",
    "qs_pg:photos":116,
    "qs_pg:photos_1k":24,
    "qs_pg:photos_9k":1,
    "qs_pg:photos_9r":3,
    "qs_pg:photos_all":116,
    "qs_pg:photos_sr":3,
    "qs_pg:pop_sr":0,
    "qs_pg:qs_pg_placetype":"neighbourhood",
    "qs_pg:qs_pg_placetype_gp":"Suburb",
    "qs_pg:woe_adm0":23424936,
    "woe:adm0_id":23424936,
    "woe:name_adm0":"Russia",
    "woe:name_adm1":"Murmansk Oblast",
    "woe:placetype":"Suburb",
    "wof:name":"Bol'nichnyj",
    "wof:placetype":"neighbourhood"
},
  "geometry": {"coordinates":[33.100776,68.919218],"type":"Point"}
}