{
  "type": "Feature",
  "properties": {
    "iso:country":"XX",
    "name:deu_x_preferred":[
        "Carignano"
    ],
    "name:eng_x_preferred":[
        "Carignano"
    ],
    "name:fra_x_preferred":[
        "Carignano"
    ],
    "name:ita_x_preferred":[
        "Carignano"
    ],
    "name:lij_x_preferred":[
        "Caignan"
    ],
    "name:nld_x_preferred":[
        "Carignano"
    ],
    "wof:name":"Carignano",
    "wof:placetype":"neighbourhood"
},
  "geometry": {"coordinates":[8.93738407961808,44.40092231356613],"type":"Point"}
}