{
  "type": "Feature",
  "properties": {
    "gn:country":"XX",
    "iso:country":"XX",
    "qs:name":"Katal Batal",
    "qs:name_adm0":"India",
    "qs:name_adm1":"Jammu and Kashmir",
    "qs:photos":42,
    "qs:photos_1k":9,
    "qs:photos_9k":1,
    "qs:photos_9r":2,
    "qs:photos_all":42,
    "qs:photos_sr":2,
    "qs:placetype":"Town",
    "qs:pop_sr":"0",
    "wof:name":"Katal Batal",
    "wof:placetype":"locality"
},
  "geometry": {"coordinates":[74.93229650000001,32.833444],"type":"Point"}
}