{
  "type": "Feature",
  "properties": {
    "iso:country":"XX",
    "name:fas_x_preferred":[
        "\u062a\u0627\u06cc\u0633\u0646\u0633 \u06a9\u0631\u0646\u0631"
    ],
    "name:fra_x_preferred":[
        "Tysons Corner Center"
    ],
    "qs_pg:name":"Tysons Corner Center",
    "qs_pg:name_adm0":"United States",
    "qs_pg:name_adm1":"Virginia",
    "qs_pg:photos":1691,
    "qs_pg:photos_1k":343,
    "qs_pg:photos_9k":7,
    "qs_pg:photos_9r":8,
    "qs_pg:photos_all":1691,
    "qs_pg:photos_sr":14,
    "qs_pg:pop_sr":0,
    "qs_pg:qs_pg_placetype":"neighbourhood",
    "qs_pg:qs_pg_placetype_gp":"Suburb",
    "qs_pg:woe_adm0":23424977,
    "woe:adm0_id":23424977,
    "woe:name_adm0":"United States",
    "woe:name_adm1":"Virginia",
    "woe:placetype":"Suburb",
    "wof:name":"Tysons Corner Center",
    "wof:placetype":"neighbourhood"
},
  "geometry": {"coordinates":[-77.221667,38.916071],"type":"Point"}
}