{
  "type": "Feature",
  "properties": {
    "iso:country":"XX",
    "qs_pg:name":"Sector Sur",
    "qs_pg:name_adm0":"Espa\u00f1a",
    "qs_pg:name_adm1":"Andaluc\u00eda",
    "qs_pg:photos":956,
    "qs_pg:photos_1k":194,
    "qs_pg:photos_9k":4,
    "qs_pg:photos_9r":6,
    "qs_pg:photos_all":956,
    "qs_pg:photos_sr":10,
    "qs_pg:pop_sr":0,
    "qs_pg:qs_pg_placetype":"neighbourhood",
    "qs_pg:qs_pg_placetype_gp":"Suburb",
    "qs_pg:woe_adm0":23424950,
    "woe:adm0_id":23424950,
    "woe:name_adm0":"Espa\u00f1a",
    "woe:name_adm1":"Andaluc\u00eda",
    "woe:placetype":"Suburb",
    "wof:name":"Sector Sur",
    "wof:placetype":"neighbourhood"
},
  "geometry": {"coordinates":[-5.987076,37.358295],"type":"Point"}
}