{
  "type": "Feature",
  "properties": {
    "iso:country":"XX",
    "qs_pg:name":"Porto Spa\u00f1o",
    "qs_pg:name_adm0":"Bonaire Saint Eustatius and Saba",
    "qs_pg:name_adm1":"Bonaire",
    "qs_pg:photos":39,
    "qs_pg:photos_1k":8,
    "qs_pg:photos_9k":1,
    "qs_pg:photos_9r":2,
    "qs_pg:photos_all":39,
    "qs_pg:photos_sr":2,
    "qs_pg:pop_sr":0,
    "qs_pg:qs_pg_placetype":"locality",
    "qs_pg:qs_pg_placetype_gp":"Town",
    "qs_pg:woe_adm0":56558056,
    "woe:adm0_id":56558056,
    "woe:name_adm0":"Bonaire Saint Eustatius and Saba",
    "woe:name_adm1":"Bonaire",
    "woe:placetype":"Town",
    "wof:name":"Porto Spa\u00f1o",
    "wof:placetype":"locality"
},
  "geometry": {"coordinates":[-68.269234,12.230893],"type":"Point"}
}